Workbook

Sheet 요약
B1: ICMDA 숙소배정 — 요약 (Overview)
B2: 데이터 v7 기준 · 모든 값은 수식으로 자동 갱신
B4: ■ 핵심 지표
B5: 총 참가자 (행 수) | C5: =COUNTA(참가자!A2:A714)
B6: 총 인원 (가족 포함) | C6: =SUMPRODUCT(VALUE("0"&참가자!AG2:AG714))
B7: 방 필요 인원 (배정필요≠No) | C7: =SUMPRODUCT((참가자!O2:O714<>"No")*VALUE("0"&참가자!AG2:AG714))
B8: 총 객실 수 | C8: =COUNTA(객실!A2:A130)
B9: 총 수용 인원 (정원 합) | C9: =SUM(객실!H2:H130)
B10: 수용 여유 (정원 − 방필요인원) | C10: =C9-C7
B12: ■ 참가자 — 카테고리별
B13: 무료숙소신청 - 개인 | C13: =COUNTIF(참가자!C2:C714,"무료숙소신청 - 개인")
B14: 무료숙소신청 - 가족 | C14: =COUNTIF(참가자!C2:C714,"무료숙소신청 - 가족")
B15: └ 가족 인원 (가족 포함) | C15: =SUMPRODUCT((참가자!C2:C714="무료숙소신청 - 가족")*VALUE("0"&참가자!AG2:AG714))
B16: NOC 위원 | C16: =COUNTIF(참가자!C2:C714,"NOC 위원")
B17: AFF | C17: =COUNTIF(참가자!C2:C714,"AFF")
B18: 중국 | C18: =COUNTIF(참가자!C2:C714,"중국")
B19: 자원봉사팀 | C19: =COUNTIF(참가자!C2:C714,"자원봉사팀")
B20: 찬양팀 | C20: =COUNTIF(참가자!C2:C714,"찬양팀")
B21: 미디어팀 | C21: =COUNTIF(참가자!C2:C714,"미디어팀")
B23: ■ 참가자 — 팀별 (팀 컬럼)
B24: 자원봉사팀 (전체) | C24: =COUNTIF(참가자!AN2:AN714,"자원봉사팀")
B25: └ 방 필요 (배정필요=Yes) | C25: =COUNTIFS(참가자!AN2:AN714,"자원봉사팀",참가자!O2:O714,"Yes")
B26: 찬양팀 | C26: =COUNTIF(참가자!AN2:AN714,"찬양팀")
B27: 미디어팀 | C27: =COUNTIF(참가자!AN2:AN714,"미디어팀")
B29: ■ 참가자 — 성별
B30: 남 (M) | C30: =COUNTIF(참가자!G2:G714,"M")
B31: 여 (F) | C31: =COUNTIF(참가자!G2:G714,"F")
B32: 미상 (?) | C32: =COUNTIF(참가자!G2:G714,"~?")
B34: ■ 참가자 — 결제상태
B35: Paid | C35: =COUNTIF(참가자!N2:N714,"Paid")
B36: Bursary Holder | C36: =COUNTIF(참가자!N2:N714,"Bursary Holder")
B37: NA | C37: =COUNTIF(참가자!N2:N714,"NA")
B39: ■ 참가자 — 숙박일수
B40: 1박 | C40: =COUNTIF(참가자!AB2:AB714,"1박")
B41: 2박 | C41: =COUNTIF(참가자!AB2:AB714,"2박")
B42: 3박 | C42: =COUNTIF(참가자!AB2:AB714,"3박")
B43: 4박 | C43: =COUNTIF(참가자!AB2:AB714,"4박")
B44: 5박 | C44: =COUNTIF(참가자!AB2:AB714,"5박")
B45: 6박 | C45: =COUNTIF(참가자!AB2:AB714,"6박")
B46: 7박 | C46: =COUNTIF(참가자!AB2:AB714,"7박")
B47: 8박 | C47: =COUNTIF(참가자!AB2:AB714,"8박")
B48: 10박 | C48: =COUNTIF(참가자!AB2:AB714,"10박")
B49: 미지정 (0박) | C49: =COUNTBLANK(참가자!AB2:AB714)
B51: ■ 참가자 — 검토/배정 현황
B52: 검토 필요 (한글이름) | C52: =COUNTIF(참가자!AM2:AM714,"한글이름 확인")
B53: 플레이스홀더 행 | C53: =COUNTIF(참가자!AM2:AM714,"플레이스홀더")
B54: 배정숙소 기지정 | C54: =COUNTA(참가자!AI2:AI714)
B56: ■ 객실 — 숙소별 (방 수 / 정원)
B57: 부영청소년수련원 — 방 수 | C57: =COUNTIF(객실!B2:B130,"부영청소년수련원")
B58: 부영청소년수련원 — 정원 | C58: =SUMIF(객실!B2:B130,"부영청소년수련원",객실!H2:H130)
B59: 유어스호텔 — 방 수 | C59: =COUNTIF(객실!B2:B130,"유어스호텔")
B60: 유어스호텔 — 정원 | C60: =SUMIF(객실!B2:B130,"유어스호텔",객실!H2:H130)
B62: ■ 객실 — 성별구분
B63: Male | C63: =COUNTIF(객실!G2:G130,"Male")
B64: Female | C64: =COUNTIF(객실!G2:G130,"Female")
B65: Staff | C65: =COUNTIF(객실!G2:G130,"Staff")
B66: 미지정 (유어스) | C66: =COUNTBLANK(객실!G2:G130)
B68: ■ 객실 — 유형별 (호텔별)
B69: 유형 | C69: 부영청소년수련원 | D69: 유어스호텔 | E69: 합계
B70: Korean Traditional | C70: =COUNTIFS(객실!F2:F130,"Korean Traditional",객실!B2:B130,"부영청소년수련원") | D70: =COUNTIFS(객실!F2:F130,"Korean Traditional",객실!B2:B130,"유어스호텔") | E70: =COUNTIF(객실!F2:F130,"Korean Traditional")
B71: Korean Room | C71: =COUNTIFS(객실!F2:F130,"Korean Room",객실!B2:B130,"부영청소년수련원") | D71: =COUNTIFS(객실!F2:F130,"Korean Room",객실!B2:B130,"유어스호텔") | E71: =COUNTIF(객실!F2:F130,"Korean Room")
B72: Bed | C72: =COUNTIFS(객실!F2:F130,"Bed",객실!B2:B130,"부영청소년수련원") | D72: =COUNTIFS(객실!F2:F130,"Bed",객실!B2:B130,"유어스호텔") | E72: =COUNTIF(객실!F2:F130,"Bed")
B73: Bed For 2 | C73: =COUNTIFS(객실!F2:F130,"Bed For 2",객실!B2:B130,"부영청소년수련원") | D73: =COUNTIFS(객실!F2:F130,"Bed For 2",객실!B2:B130,"유어스호텔") | E73: =COUNTIF(객실!F2:F130,"Bed For 2")
B74: Deluxe Twin | C74: =COUNTIFS(객실!F2:F130,"Deluxe Twin",객실!B2:B130,"부영청소년수련원") | D74: =COUNTIFS(객실!F2:F130,"Deluxe Twin",객실!B2:B130,"유어스호텔") | E74: =COUNTIF(객실!F2:F130,"Deluxe Twin")
B75: Deluxe Family Twin | C75: =COUNTIFS(객실!F2:F130,"Deluxe Family Twin",객실!B2:B130,"부영청소년수련원") | D75: =COUNTIFS(객실!F2:F130,"Deluxe Family Twin",객실!B2:B130,"유어스호텔") | E75: =COUNTIF(객실!F2:F130,"Deluxe Family Twin")
B76: Triple Room | C76: =COUNTIFS(객실!F2:F130,"Triple Room",객실!B2:B130,"부영청소년수련원") | D76: =COUNTIFS(객실!F2:F130,"Triple Room",객실!B2:B130,"유어스호텔") | E76: =COUNTIF(객실!F2:F130,"Triple Room")
B77: Suite Corner | C77: =COUNTIFS(객실!F2:F130,"Suite Corner",객실!B2:B130,"부영청소년수련원") | D77: =COUNTIFS(객실!F2:F130,"Suite Corner",객실!B2:B130,"유어스호텔") | E77: =COUNTIF(객실!F2:F130,"Suite Corner")
B78: YOUUS Suite | C78: =COUNTIFS(객실!F2:F130,"YOUUS Suite",객실!B2:B130,"부영청소년수련원") | D78: =COUNTIFS(객실!F2:F130,"YOUUS Suite",객실!B2:B130,"유어스호텔") | E78: =COUNTIF(객실!F2:F130,"YOUUS Suite")
B80: ■ 객실 — 필수온돌
B81: 필수온돌 방 수 | C81: =COUNTIF(객실!J2:J130,"Y")

Sheet 참가자
A1: 참가자ID | B1: 그룹ID | C1: 카테고리 | D1: 구분 | E1: 이름 | F1: 한글이름 | G1: 성별 | H1: 생년월일 | I1: 국적 | J1: 이메일 | K1: 소속 | L1: 직책 | M1: WB등급 | N1: 결제상태 | O1: 배정필요 | P1: 도착일 | Q1: 출발일 | R1: 6월26일 | S1: 6월27일 | T1: 6월28일 | U1: 6월29일 | V1: 6월30일 | W1: 7월1일 | X1: 7월2일 | Y1: 7월3일 | Z1: 7월4일 | AA1: 7월5일 | AB1: 숙박일수 | AC1: 본인 | AD1: 배우자 | AE1: 자녀 | AF1: 기타 | AG1: 총인원 | AH1: 동반자요약 | AI1: 배정숙소 | AJ1: 중요사항 | AK1: 비고 | AL1: 출처 | AM1: 검토필요 | AN1: 팀
A2: P0001 | B2: G-fam-01 | C2: 무료숙소신청 - 가족 | D2: 1 | E2: NZAME YOLANDE | G2: F | H2: 1957-07-15 | I2: Gabon | J2: yolandenzame@gmail.com | K2: Gabon Medical Chrétien | L2: Membre | M2: Middle income | N2: Paid | O2: Yes | P2: 6월29일 | Q2: 7월4일 | U2: ✓ | V2: ✓ | W2: ✓ | X2: ✓ | Y2: ✓ | Z2: ✓ | AB2: 6박 | AC2: 1 | AD2: 0 | AE2: 1 | AF2: 0 | AG2: 2 | AH2: Rebecca [딸] | AL2: FINAL
A3: P0002 | B3: G-fam-02 | C3: 무료숙소신청 - 가족 | D3: 2 | E3: PAUL STEPHEN ATARO AYELLA | G3: M | H3: 1977-03-02 | I3: Uganda | J3: atarodrpapa@gmail.com | K3: ICMDA | L3: Regional Representative East Africa | M3: Low income | N3: Bursary Holder | O3: Yes | P3: 6월29일 | Q3: 7월4일 | U3: ✓ | V3: ✓ | W3: ✓ | X3: ✓ | Y3: ✓ | Z3: ✓ | AB3: 6박 | AC3: 1 | AD3: 0 | AE3: 2 | AF3: 0 | AG3: 3 | AH3: ATARO JANE KARINA, FEMALE. ATARO NEEMA ANGIOLETTA, FEMALE DAUGHTERS 딸 2명 | AL3: FINAL
A4: P0003 | B4: G-fam-03 | C4: 무료숙소신청 - 가족 | D4: 3 | E4: PETER SATHIYANATHAN MICHEAL JOHN | G4: M | H4: 1978-03-24 | I4: Malaysia | J4: doctorpeter@hotmail.com | K4: Healthcare Christian Fellowship Malaysia | L4: Doctor | M4: Middle income | N4: Paid | O4: Yes | P4: 7월1일 | Q4: 7월4일 | W4: ✓ | X4: ✓ | Y4: ✓ | Z4: ✓ | AB4: 4박 | AC4: 1 | AD4: 0 | AE4: 1 | AF4: 0 | AG4: 2 | AH4: IRINE AARATHANA PETER SATHIYANATHAN [딸, 12세] | AL4: FINAL
A5: P0004 | B5: G-fam-04 | C5: 무료숙소신청 - 가족 | D5: 4 | E5: SEMBY, JOHAN KYUNG HWA | G5: M | H5: 1966-01-20 | I5: Sweden | J5: johan.semby@gmail.com | K5: Linköping University/Linköping University Hospital Department Of Opthalmology/ ICMDA Sweden | L5: Senior Consultant In Ophthalmology/ Leader, Organizer For The Delegation From ICMDA Sweden And Finland | M5: High income | N5: Paid | O5: Yes | P5: 6월29일 | Q5: 7월4일 | U5: ✓ | V5: ✓ | W5: ✓ | X5: ✓ | Y5: ✓ | Z5: ✓ | AB5: 6박 | AC5: 1 | AD5: 0 | AE5: 1 | AF5: 0 | AG5: 2 | AH5: Joshua Semby [아들] | AL5: FINAL
A6: P0005 | B6: G-fam-05 | C6: 무료숙소신청 - 가족 | D6: 5 | E6: NURGUL MAMYROVA | G6: F | H6: 1980-03-17 | I6: Kyrgyz Republic | J6: nurgulicmda@gmail.com | K6: ICMDA | L6: Doctor | M6: Middle income | N6: Paid | O6: Yes | P6: 6월29일 | Q6: 7월4일 | U6: ✓ | V6: ✓ | W6: ✓ | X6: ✓ | Y6: ✓ | Z6: ✓ | AB6: 6박 | AC6: 1 | AD6: 1 | AE6: 2 | AF6: 0 | AG6: 4 | AH6: Simon Peter Nadeem [배우자(남편)] Shulmiyat Sarah Nadeem[딸, 18세] Timothy Simon Nadeem [아들, 13세] | AL6: FINAL
A7: P0006 | B7: G-fam-06 | C7: 무료숙소신청 - 가족 | D7: 6 | E7: DIANA | F7: Safina | G7: F | H7: 1982-10-29 | I7: Russian Federation | J7: diana.safina316@gmail.com | K7: ICMDA | L7: Regional Representative, Eurasia Training Administrator | M7: High income | N7: Bursary Holder | O7: Yes | P7: 6월29일 | Q7: 7월4일 | U7: ✓ | V7: ✓ | W7: ✓ | X7: ✓ | Y7: ✓ | Z7: ✓ | AB7: 6박 | AC7: 1 | AD7: 0 | AE7: 1 | AF7: 0 | AG7: 2 | AH7: Daria Safina [딸, 13세] | AL7: FINAL | AM7: 한글이름 확인
A8: P0007 | B8: G-fam-07 | C8: 무료숙소신청 - 가족 | D8: 7 | E8: PETER FEE | G8: M | H8: 1979-05-14 | I8: United Kingdom | J8: peterfee@doctors.org.uk | K8: Royal Belfast Children's Hospital, Belfast, UK | L8: Consultant Anaesthetist | M8: High income | N8: Paid | O8: Yes | P8: 6월29일 | Q8: 7월4일 | U8: ✓ | V8: ✓ | W8: ✓ | X8: ✓ | Y8: ✓ | Z8: ✓ | AB8: 6박 | AC8: 1 | AD8: 1 | AE8: 3 | AF8: 0 | AG8: 5 | AH8: Kerry Fee [배우자(아내)] thefees@me.com Grace Fee [딸, 12세] Joel Fee [아들, 14세] Toby Fee [아들, 10세] | AL8: FINAL
A9: P0008 | B9: G-fam-08 | C9: 무료숙소신청 - 가족 | D9: 8 | E9: GRETA GAMAL NAZIR KROSS | G9: F | H9: 1983-01-12 | I9: Egypt, Arab Rep. | J9: gretagamal@hotmail.com | K9: Cmf Egypt | L9: Pediatric Specialist (director Of Operations Of Cmf Egypt) | M9: Middle income | N9: Bursary Holder | O9: Yes | P9: 6월29일 | Q9: 7월4일 | U9: ✓ | V9: ✓ | W9: ✓ | X9: ✓ | Y9: ✓ | Z9: ✓ | AB9: 6박 | AC9: 1 | AD9: 1 | AE9: 2 | AF9: 0 | AG9: 4 | AH9: George robile [배우자(남편)] gretagamal@hotmail.com Jason george [아들, 13세] Jenny george [딸, 17세] | AL9: FINAL
A10: P0009 | B10: G-fam-09 | C10: 무료숙소신청 - 가족 | D10: 9 | E10: MASRA NGARMBAYE | G10: M | H10: 1985-01-18 | I10: Chad | J10: nmasra@yahoo.com | K10: Association Des Medecins Et Dentistes Chretiens Du Tchad- AMDCT | L10: Doctor Member | M10: Low income | N10: Bursary Holder | O10: Yes | P10: 6월29일 | Q10: 7월4일 | U10: ✓ | V10: ✓ | W10: ✓ | X10: ✓ | Y10: ✓ | Z10: ✓ | AB10: 6박 | AC10: 1 | AD10: 1 | AE10: 1 | AF10: 0 | AG10: 3 | AH10: Edith Dekoum Nelembaye [배우자(아내)] Manaseth Toulaboua Ngarmbaye [아들, 2세] | AL10: FINAL
A11: P0010 | B11: G-fam-10 | C11: 무료숙소신청 - 가족 | D11: 10 | E11: SOFAKO AMÉGANVI EGLOH | G11: M | H11: 1981-03-14 | I11: Togo | J11: esofak81@gmail.com | K11: CMF Togo | L11: Doctor | M11: Low income | N11: Bursary Holder | O11: Yes | P11: 6월29일 | Q11: 7월4일 | U11: ✓ | V11: ✓ | W11: ✓ | X11: ✓ | Y11: ✓ | Z11: ✓ | AB11: 6박 | AC11: 1 | AD11: 1 | AE11: 1 | AF11: 0 | AG11: 3 | AH11: Afi Kafui BANIBA ATOKO Epse EGLOH [배우자(아내)] Betsaleel Ewousika Améganvi EGLOH [자녀, 3세] | AL11: FINAL
A12: P0011 | B12: G-fam-11 | C12: 무료숙소신청 - 가족 | D12: 11 | E12: TRAY CHEAVKUN | G12: M | H12: 1989-08-13 | I12: Cambodia | J12: traykun@live.com | K12: Cambodian Christian Medical Fellowship | L12: Member | M12: Middle income | N12: Bursary Holder | O12: Yes | P12: 7월2일 | Q12: 7월4일 | X12: ✓ | Y12: ✓ | Z12: ✓ | AB12: 3박 | AC12: 1 | AD12: 1 | AE12: 1 | AF12: 0 | AG12: 3 | AH12: ANG SREYNIN [배우자(아내)] one daughter [딸, 3세] | AL12: FINAL
A13: P0012 | B13: G-fam-12 | C13: 무료숙소신청 - 가족 | D13: 12 | E13: GENA KEROLLOS DAWOOD GERGES | G13: F | H13: 1990-04-17 | I13: Egypt, Arab Rep. | J13: genakerollos@gmail.com | K13: CMF | L13: ENT Specialist | M13: Middle income | N13: Bursary Holder | O13: Yes | P13: 6월29일 | Q13: 7월4일 | U13: ✓ | V13: ✓ | W13: ✓ | X13: ✓ | Y13: ✓ | Z13: ✓ | AB13: 6박 | AC13: 1 | AD13: 1 | AE13: 2 | AF13: 0 | AG13: 4 | AH13: Ramy nabil [배우자(남편)] holy ramy [딸, 11세] heaven ramy [딸, 6세] | AL13: FINAL
A14: P0013 | B14: G-fam-13 | C14: 무료숙소신청 - 가족 | D14: 13 | E14: DONALD KAFA | G14: M | H14: 1976-11-04 | I14: Solomon Islands | J14: kafadonald@gmail.com | K14: Oceania ICMDA | L14: Medical Doctor | M14: Middle income | N14: Bursary Holder | O14: Yes | P14: 6월29일 | Q14: 7월1일 | U14: ✓ | V14: ✓ | W14: ✓ | AB14: 3박 | AC14: 1 | AD14: 0 | AE14: 1 | AF14: 0 | AG14: 2 | AH14: Elnisha Donald Kafa [아들, 13세] | AL14: FINAL
A15: P0014 | B15: G-fam-14 | C15: 무료숙소신청 - 가족 | D15: 14 | E15: PRISCILIA PRATAMI INTAN | G15: F | H15: 1992-07-09 | I15: Indonesia | J15: priscilia.pratami.intan@gmail.com | K15: CMDFI | L15: Saline Process Teamwork | M15: Middle income | N15: Bursary Holder | O15: Yes | P15: 6월29일 | Q15: 7월4일 | U15: ✓ | V15: ✓ | W15: ✓ | X15: ✓ | Y15: ✓ | Z15: ✓ | AB15: 6박 | AC15: 1 | AD15: 1 | AE15: 2 | AF15: 0 | AG15: 4 | AH15: Rudy.S [배우자(남편)] Kara Jessica Joetan [딸, 3세] Anya Kirana Joetan [딸] | AL15: FINAL
A16: P0015 | B16: G-fam-15 | C16: 무료숙소신청 - 가족 | D16: 15 | E16: PHOEM | F16: CHANTHEN | G16: F | H16: 1992-07-17 | I16: Cambodia | J16: drsam0701@gmail.com | K16: Cambodian Chrsitian Medical Fellowship | L16: Key Volunteer | M16: Middle income | N16: Bursary Holder | O16: Yes | P16: 7월1일 | Q16: 7월4일 | W16: ✓ | X16: ✓ | Y16: ✓ | Z16: ✓ | AB16: 4박 | AC16: 1 | AD16: 0 | AE16: 1 | AF16: 0 | AG16: 2 | AH16: Limeng Lichi [딸, 16세] | AL16: FINAL | AM16: 한글이름 확인
A17: P0016 | B17: G-fam-16 | C17: 무료숙소신청 - 가족 | D17: 16 | E17: RANI DWI CAHYANIPUTRI | G17: F | H17: 1986-08-20 | I17: Indonesia | J17: rk.tulung@gmail.com | K17: Simore Ministry | L17: Director | M17: Middle income | N17: Bursary Holder | O17: Yes | P17: 6월29일 | Q17: 7월4일 | U17: ✓ | V17: ✓ | W17: ✓ | X17: ✓ | Y17: ✓ | Z17: ✓ | AB17: 6박 | AC17: 1 | AD17: 1 | AE17: 1 | AF17: 0 | AG17: 3 | AH17: Augustine Elizabeth Pattipeilohy [모] Danzel Bezalel Tulung[아들, 0세] | AL17: FINAL
A18: P0017 | B18: G-fam-17 | C18: 무료숙소신청 - 가족 | D18: 17 | E18: PHON SOPHAI | G18: M | H18: 1985-12-16 | I18: Cambodia | J18: uhs.sophai@gmail.com | K18: CCMF | L18: Medical Doctor | M18: Middle income | N18: Bursary Holder | O18: Yes | P18: 7월1일 | Q18: 7월4일 | W18: ✓ | X18: ✓ | Y18: ✓ | Z18: ✓ | AB18: 4박 | AC18: 1 | AD18: 1 | AE18: 1 | AF18: 0 | AG18: 3 | AH18: Dy Dalen [배우자(아내)] Phay Rattanak [딸, 7세] | AL18: FINAL
A19: P0018 | B19: G-fam-18 | C19: 무료숙소신청 - 가족 | D19: 18 | E19: SYBRAND JOHANNES DE VAAL | G19: M | H19: 1980-02-20 | I19: South Africa | J19: sjdevaal@gmail.com | K19: CMF South Africa | L19: Dr | M19: Middle income | N19: Paid | O19: Yes | P19: 6월30일 | Q19: 7월4일 | V19: ✓ | W19: ✓ | X19: ✓ | Y19: ✓ | Z19: ✓ | AB19: 5박 | AC19: 1 | AD19: 1 | AE19: 5 | AF19: 0 | AG19: 7 | AH19: Celeste de Vaal [배우자(아내)] Nienke de Vaal [딸] Lira de Vaal [딸] Thandi de Vaal [딸] Ariana de Vaal [딸] | AL19: FINAL
A20: P0019 | B20: G-fam-19 | C20: 무료숙소신청 - 가족 | D20: 19 | E20: PHAM THI HUYEN | G20: F | H20: 1986-09-14 | I20: Vietnam | J20: huyentrangshaloms@gmail.com | K20: Hong Phuc General Hospital, Hai Phong, Vietnam | L20: Pharmacist | M20: Middle income | N20: Bursary Holder | O20: Yes | P20: 7월2일 | Q20: 7월4일 | X20: ✓ | Y20: ✓ | Z20: ✓ | AB20: 3박 | AC20: 1 | AD20: 0 | AE20: 1 | AF20: 0 | AG20: 2 | AH20: Nguyen Pham Viet An [아들] | AL20: FINAL
A21: P0020 | B21: G-fam-20 | C21: 무료숙소신청 - 가족 | D21: 20 | E21: HAMADO | F21: Sawadogo | G21: M | H21: 1989-12-31 | I21: Burkina Faso | J21: hamadodavidsawadogo@gmail.com | K21: ICMDA | L21: Family Physician /RR | M21: Low income | N21: Bursary Holder | O21: Yes | P21: 6월29일 | Q21: 7월4일 | U21: ✓ | V21: ✓ | W21: ✓ | X21: ✓ | Y21: ✓ | Z21: ✓ | AB21: 6박 | AC21: 1 | AD21: 0 | AE21: 1 | AF21: 0 | AG21: 2 | AH21: Sawadogo Deogracias W [딸, 5세] | AL21: FINAL | AM21: 한글이름 확인
A22: P0021 | B22: G-fam-21 | C22: 무료숙소신청 - 가족 | D22: 21 | E22: JODI ISAACS WILES | G22: F | H22: 1980-04-16 | I22: South Africa | J22: jodiandmichaelwiles@gmail.com | K22: UKZN/Queen Nandi Regional Hospital/CMF South Africa Executive Committee Member | L22: Dr | M22: Middle income | N22: Paid | O22: Yes | P22: 7월2일 | Q22: 7월4일 | X22: ✓ | Y22: ✓ | Z22: ✓ | AB22: 3박 | AC22: 1 | AD22: 0 | AE22: 2 | AF22: 0 | AG22: 3 | AH22: Amia Wiles (딸, 11세) Cayla Wiles (딸, 9세) | AL22: FINAL
A23: P0022 | B23: G-fam-22 | C23: 무료숙소신청 - 가족 | D23: 22 | E23: KYUNGMIN JANG | F23: 장경민 | G23: M | H23: 1985-11-30 | I23: Korea, Rep. | J23: jang@hishandsonafrica.org | K23: His Hands On Africa (Rwanda) | L23: Dental Mission Director And Dental Surgeon | M23: High income | N23: Paid | O23: Yes | P23: 7월1일 | Q23: 7월4일 | W23: ✓ | X23: ✓ | Y23: ✓ | Z23: ✓ | AB23: 4박 | AC23: 1 | AD23: 1 | AE23: 2 | AF23: 0 | AG23: 4 | AH23: 김민희 (배우자) 장세린 (딸, 7세) 장하린(딸, 2세) | AL23: FINAL
A24: P0023 | B24: G-fam-23 | C24: 무료숙소신청 - 가족 | D24: 23 | E24: CHI MA | G24: F | H24: 1986-07-04 | I24: China | J24: mamachi07@gmail.com edgarwu@msn.com | K24: Peniel Church Muzha | L24: Doctor | M24: Middle income | N24: Paid | O24: Yes | P24: 6월29일 | Q24: 7월4일 | U24: ✓ | V24: ✓ | W24: ✓ | X24: ✓ | Y24: ✓ | Z24: ✓ | AB24: 6박 | AC24: 1 | AD24: 1 | AE24: 2 | AF24: 0 | AG24: 4 | AH24: PIN-HSIEN WU(배우자,남편) EN-JIE WU(딸) EN-QI WU(아들) | AL24: FINAL
A25: P0024 | B25: G-fam-24 | C25: 무료숙소신청 - 가족 | D25: 24 | E25: HELENA GOMES | G25: F | H25: 1944-11-11 | I25: Brazil | J25: gomesmibr@gmail.com | K25: CMF Brazil | L25: Mother Accompanying Applicant (Mireille Gomes) | M25: Middle income | N25: Paid | O25: Yes | P25: 6월29일 | Q25: 7월4일 | U25: ✓ | V25: ✓ | W25: ✓ | X25: ✓ | Y25: ✓ | Z25: ✓ | AB25: 6박 | AC25: 1 | AD25: 0 | AE25: 1 | AF25: 0 | AG25: 2 | AH25: Mireille Gomes(딸) | AL25: FINAL
A26: P0025 | B26: G-fam-25 | C26: 무료숙소신청 - 가족 | D26: 25 | E26: MANOLITA JUNASA | G26: F | H26: 1960-01-01 | I26: Philippines | J26: mallette.p@gmail.com | K26: Kavod Center For Special Persons | L26: Founder, Executive Director | M26: Middle income | N26: Paid | O26: Yes | P26: 6월29일 | Q26: 7월4일 | U26: ✓ | V26: ✓ | W26: ✓ | X26: ✓ | Y26: ✓ | Z26: ✓ | AB26: 6박 | AC26: 1 | AD26: 0 | AE26: 1 | AF26: 0 | AG26: 2 | AH26: KYLE DAVID JUNASA(아들) | AL26: FINAL
A27: P0026 | B27: G-fam-26 | C27: 무료숙소신청 - 가족 | D27: 25 | E27: KYLE DAVID JUNASA | G27: M | H27: 1995-05-18 | I27: Philippines | J27: mallette.p@gmail.com | K27: Kavod Center For Special Persons | L27: Co-founder, Coach | M27: Middle income | N27: Paid | O27: Yes | P27: 6월29일 | Q27: 7월4일 | U27: ✓ | V27: ✓ | W27: ✓ | X27: ✓ | Y27: ✓ | Z27: ✓ | AB27: 6박 | AC27: 1 | AD27: 0 | AE27: 0 | AF27: 1 | AG27: 2 | AH27: MANOLITA JUNASA(엄마) | AL27: FINAL
A28: P0027 | C28: 무료숙소신청 - 개인 | D28: 1 | E28: ELISA MABEL GALEANO GAMARRA | G28: F | H28: 1997-07-03 | I28: Paraguay | J28: elisamedoficial@gmail.com | K28: In The Process Of Having An Association In Paraguay | L28: Doctor | M28: Middle income | N28: Bursary Holder | O28: Yes | P28: 6월29일 | Q28: 7월4일 | U28: ✓ | V28: ✓ | W28: ✓ | X28: ✓ | Y28: ✓ | Z28: ✓ | AB28: 6박 | AC28: 1 | AG28: 1 | AL28: FINAL
A29: P0028 | C29: 무료숙소신청 - 개인 | D29: 2 | E29: BLESSINGS DENDERE | G29: F | H29: 1999-10-25 | I29: Zimbabwe | J29: blessingszd@gmail.com | K29: Christian Medical Fellowship | L29: Doctor | M29: Middle income | N29: Bursary Holder | O29: Yes | P29: 6월29일 | Q29: 7월4일 | U29: ✓ | V29: ✓ | W29: ✓ | X29: ✓ | Y29: ✓ | Z29: ✓ | AB29: 6박 | AC29: 1 | AG29: 1 | AL29: FINAL
A30: P0029 | C30: 무료숙소신청 - 개인 | D30: 3 | E30: MUHUMUZA NDAMAGE STEPHEN | G30: M | H30: 1979-11-19 | I30: Rwanda | J30: stephen20130@gmail.com | K30: Rwanda Christian Medical And Dental Organization | L30: Head Of Rwanda Christian Medical And A Dental Organization | M30: Low income | N30: Bursary Holder | O30: Yes | P30: 7월4일 | Q30: 7월4일 | Z30: ✓ | AB30: 1박 | AC30: 1 | AG30: 1 | AL30: FINAL
A31: P0030 | C31: 무료숙소신청 - 개인 | D31: 4 | E31: KILACH CAROLE JESANG | G31: F | H31: 1988-03-27 | I31: Kenya | J31: carolejesang@gmail.com | K31: Christian Medical Fellowship- Kenya | L31: Dr/Miss/ Regional Leader | M31: Middle income | N31: Paid | O31: Yes | P31: 6월29일 | Q31: 7월4일 | U31: ✓ | V31: ✓ | W31: ✓ | X31: ✓ | Y31: ✓ | Z31: ✓ | AB31: 6박 | AC31: 1 | AG31: 1 | AL31: FINAL
A32: P0031 | C32: 무료숙소신청 - 개인 | D32: 5 | E32: ALINE GARCIA PEREIRA | G32: F | H32: 1989-12-05 | I32: Brazil | J32: alinegpereira1@gmail.com | K32: Uniasselvi (University)/ MDC -Medicos De Cristo | L32: I Am Student Of Health Management (graduation). But I Am Also PHD | M32: Middle income | N32: Paid | O32: Yes | P32: 6월29일 | Q32: 7월4일 | U32: ✓ | V32: ✓ | W32: ✓ | X32: ✓ | Y32: ✓ | Z32: ✓ | AB32: 6박 | AC32: 1 | AG32: 1 | AL32: FINAL
A33: P0032 | C33: 무료숙소신청 - 개인 | D33: 6 | E33: MUGABA PROSCOVIA MUJEERE | G33: F | H33: 1979-03-29 | I33: Uganda | J33: drprosiemm@gmail.com | K33: Uganda Christian Medical Fellowship (UCMF) | L33: Chairperson Of UCMF National Executive Committee | M33: Low income | N33: Bursary Holder | O33: Yes | P33: 6월30일 | Q33: 7월4일 | V33: ✓ | W33: ✓ | X33: ✓ | Y33: ✓ | Z33: ✓ | AB33: 5박 | AC33: 1 | AG33: 1 | AL33: FINAL
A34: P0033 | C34: 무료숙소신청 - 개인 | D34: 7 | E34: THEODORUS HEDWIN KADRIANTO | G34: M | H34: 1988-07-03 | I34: Indonesia | J34: theodorus.hedwin@icmda.net | K34: ICMDA | L34: AEO For East Asia, Southeast Asia, Oceania | M34: Middle income | N34: Paid | O34: Yes | P34: 6월29일 | Q34: 7월4일 | U34: ✓ | V34: ✓ | W34: ✓ | X34: ✓ | Y34: ✓ | Z34: ✓ | AB34: 6박 | AC34: 1 | AG34: 1 | AL34: FINAL
A35: P0034 | C35: 무료숙소신청 - 개인 | D35: 8 | E35: ALINA | G35: F | H35: 1999-06-23 | I35: Belarus | J35: kurdunap@gmail.com | K35: Belarussian CMF | L35: Ophtalmologist | M35: Middle income | N35: Bursary Holder | O35: Yes | P35: 6월29일 | Q35: 7월4일 | U35: ✓ | V35: ✓ | W35: ✓ | X35: ✓ | Y35: ✓ | Z35: ✓ | AB35: 6박 | AC35: 1 | AG35: 1 | AL35: FINAL
A36: P0035 | C36: 무료숙소신청 - 개인 | D36: 9 | E36: BENJAMIN DUBE | G36: M | H36: 1996-08-25 | I36: Zimbabwe | J36: benjiedube25@gmail.com | K36: National University Of Science And Technology, Zimbabwe | L36: Chairperson, NUST Christian Medical Fellowship (CMF) | M36: Middle income | N36: Bursary Holder | O36: Yes | P36: 6월29일 | Q36: 7월4일 | U36: ✓ | V36: ✓ | W36: ✓ | X36: ✓ | Y36: ✓ | Z36: ✓ | AB36: 6박 | AC36: 1 | AG36: 1 | AL36: FINAL
A37: P0036 | C37: 무료숙소신청 - 개인 | D37: 10 | E37: NAKANJAKO | F37: Sharon | G37: F | H37: 1993-02-06 | I37: Uganda | J37: sharonnakanjako2023@gmail.com | K37: Uganda Christian Medical Fellowship | L37: Clinical Psychologist | M37: #REF! | N37: Bursary Holder | O37: Yes | P37: 6월29일 | Q37: 7월4일 | U37: ✓ | V37: ✓ | W37: ✓ | X37: ✓ | Y37: ✓ | Z37: ✓ | AB37: 6박 | AC37: 1 | AG37: 1 | AL37: FINAL | AM37: 한글이름 확인
A38: P0037 | C38: 무료숙소신청 - 개인 | D38: 11 | E38: CHRISTA ADELINE | G38: F | H38: 1997-01-27 | I38: Indonesia | J38: christa.adeline@icmda.net | K38: ICMDA | L38: Regional Representative For Southeast Asia | M38: Middle income | N38: Paid | O38: Yes | P38: 6월30일 | Q38: 7월4일 | V38: ✓ | W38: ✓ | X38: ✓ | Y38: ✓ | Z38: ✓ | AB38: 5박 | AC38: 1 | AG38: 1 | AL38: FINAL
A39: P0038 | C39: 무료숙소신청 - 개인 | D39: 12 | E39: QUACY ASHEEKE GRANT | G39: M | H39: 1985-07-29 | I39: Guyana | J39: qgrant@lausanne.org | K39: Lausanne Movement Caribbean/ICMDA Guyana-Caribbean | L39: Regional Director (Lausanne Movement Caribbean) | M39: High income | N39: Bursary Holder | O39: Yes | P39: 6월29일 | Q39: 7월4일 | U39: ✓ | V39: ✓ | W39: ✓ | X39: ✓ | Y39: ✓ | Z39: ✓ | AB39: 6박 | AC39: 1 | AG39: 1 | AL39: FINAL
A40: P0039 | C40: 무료숙소신청 - 개인 | D40: 13 | E40: LOUIE BENJAMIN KWON BOU | G40: M | H40: 2005-05-03 | I40: New Zealand | J40: bklouie@outlook.com | K40: University Of Otago | L40: Medical Student | M40: High income | N40: Paid | O40: Yes | P40: 6월29일 | Q40: 7월3일 | U40: ✓ | V40: ✓ | W40: ✓ | X40: ✓ | Y40: ✓ | AB40: 5박 | AC40: 1 | AG40: 1 | AL40: FINAL
A41: P0040 | C41: 무료숙소신청 - 개인 | D41: 14 | E41: MOHALENYANE MATHEKO MARY | G41: F | H41: 1997-01-05 | I41: Lesotho | J41: matheko.mohalenyane@gmail.com | K41: Senkatana Oncology Clinic | L41: Dr. | M41: Middle income | N41: Bursary Holder | O41: Yes | P41: 6월29일 | Q41: 7월4일 | U41: ✓ | V41: ✓ | W41: ✓ | X41: ✓ | Y41: ✓ | Z41: ✓ | AB41: 6박 | AC41: 1 | AG41: 1 | AL41: FINAL
A42: P0041 | C42: 무료숙소신청 - 개인 | D42: 15 | E42: ANITHA DAVID | G42: F | H42: 1968-10-08 | I42: India | J42: anitha.david@icmda.net | K42: Emmanuel Hospital Association | L42: Dentist | M42: Middle income | N42: Bursary Holder | O42: Yes | P42: 6월29일 | Q42: 7월4일 | U42: ✓ | V42: ✓ | W42: ✓ | X42: ✓ | Y42: ✓ | Z42: ✓ | AB42: 6박 | AC42: 1 | AG42: 1 | AL42: FINAL
A43: P0042 | C43: 무료숙소신청 - 개인 | D43: 16 | E43: ABIYU TADESSE FULEA | F43: Kim | G43: M | H43: 1985-10-19 | I43: Ethiopia | J43: martabiyju@gmail.com | K43: CMF Ethiopia | L43: CMF Ethiopia Chairperson | M43: Low income | N43: Bursary Holder | O43: Yes | P43: 6월29일 | Q43: 7월4일 | U43: ✓ | V43: ✓ | W43: ✓ | X43: ✓ | Y43: ✓ | Z43: ✓ | AB43: 6박 | AC43: 1 | AG43: 1 | AL43: FINAL | AM43: 한글이름 확인
A44: P0043 | C44: 무료숙소신청 - 개인 | D44: 17 | E44: KEZIA CHRISTINA VIANI WIJAYA | F44: 케지아 크리스티나 비아니 위자야 | G44: F | H44: 2000-05-13 | I44: Indonesia | J44: keziawij@gmail.com | K44: CMDA Indonesia | L44: Member | M44: Middle income | N44: Bursary Holder | O44: Yes | P44: 7월1일 | Q44: 7월4일 | W44: ✓ | X44: ✓ | Y44: ✓ | Z44: ✓ | AB44: 4박 | AC44: 1 | AG44: 1 | AL44: FINAL
A45: P0044 | C45: 무료숙소신청 - 개인 | D45: 18 | E45: ENIMIL ANTHONY KWAME | G45: M | H45: 1971-10-18 | I45: Ghana | J45: tonash@gmail.com | K45: Kwame Nkrumah University Of Science And Technology | L45: Professor/Lecturer | M45: Middle income | N45: Paid | O45: Yes | P45: 6월29일 | Q45: 7월4일 | U45: ✓ | V45: ✓ | W45: ✓ | X45: ✓ | Y45: ✓ | Z45: ✓ | AB45: 6박 | AC45: 1 | AG45: 1 | AL45: FINAL
A46: P0045 | C46: 무료숙소신청 - 개인 | D46: 19 | E46: ALINA ISTRATI | G46: F | H46: 2002-04-26 | I46: Romania | J46: istratialina16@gmail.com | K46: Nicolae Testemiţanu Moldova State University Of Medicine And Pharmacy | L46: Student | M46: High income | N46: Bursary Holder | O46: Yes | P46: 6월29일 | Q46: 7월4일 | U46: ✓ | V46: ✓ | W46: ✓ | X46: ✓ | Y46: ✓ | Z46: ✓ | AB46: 6박 | AC46: 1 | AG46: 1 | AL46: FINAL
A47: P0046 | C47: 무료숙소신청 - 개인 | D47: 20 | E47: HERVE TISTOU HITIMANA | G47: M | H47: 1991-02-28 | I47: Burundi | J47: h.tistou@gmail.com | K47: BCMDA | L47: Dr | M47: Low income | N47: Bursary Holder | O47: Yes | P47: 6월29일 | Q47: 7월4일 | U47: ✓ | V47: ✓ | W47: ✓ | X47: ✓ | Y47: ✓ | Z47: ✓ | AB47: 6박 | AC47: 1 | AG47: 1 | AL47: FINAL
A48: P0047 | C48: 무료숙소신청 - 개인 | D48: 21 | E48: OKONGO BERFINA | G48: F | H48: 1999-09-14 | I48: Senegal | J48: o.berfina1@gmail.com | K48: Association Des Médecins Et Dentistes Chrétiens Du Sénégal | L48: Treasury | M48: Middle income | N48: Bursary Holder | O48: Yes | P48: 6월29일 | Q48: 7월4일 | U48: ✓ | V48: ✓ | W48: ✓ | X48: ✓ | Y48: ✓ | Z48: ✓ | AB48: 6박 | AC48: 1 | AG48: 1 | AL48: FINAL
A49: P0048 | C49: 무료숙소신청 - 개인 | D49: 22 | E49: ADONONSI FEGNITI MAHUTON MARIELLE | G49: F | H49: 2001-07-14 | I49: Benin | J49: mariellehy@gmail.com | K49: Association Des Médecins Et Dentistes Chrétiens Du Sénégal | L49: Student Leader | M49: Middle income | N49: Bursary Holder | O49: Yes | P49: 6월29일 | Q49: 7월4일 | U49: ✓ | V49: ✓ | W49: ✓ | X49: ✓ | Y49: ✓ | Z49: ✓ | AB49: 6박 | AC49: 1 | AG49: 1 | AL49: FINAL
A50: P0049 | C50: 무료숙소신청 - 개인 | D50: 23 | E50: REBECCA BIAYE | G50: F | H50: 1993-01-25 | I50: Senegal | J50: rebiaye@gmail.com | K50: Association Des Médecins Et Dentistes Chrétiens Du Sénégal | L50: National President | M50: Middle income | N50: Bursary Holder | O50: Yes | P50: 6월29일 | Q50: 7월4일 | U50: ✓ | V50: ✓ | W50: ✓ | X50: ✓ | Y50: ✓ | Z50: ✓ | AB50: 6박 | AC50: 1 | AG50: 1 | AL50: FINAL
A51: P0050 | C51: 무료숙소신청 - 개인 | D51: 24 | E51: OBO YAPO GILLES | G51: M | H51: 1993-06-06 | I51: Côte d’Ivoire | J51: yapogilles@yahoo.fr | K51: AMPCI | L51: Medical Officer | M51: Middle income | N51: Bursary Holder | O51: Yes | P51: 6월29일 | Q51: 7월4일 | U51: ✓ | V51: ✓ | W51: ✓ | X51: ✓ | Y51: ✓ | Z51: ✓ | AB51: 6박 | AC51: 1 | AG51: 1 | AL51: FINAL
A52: P0051 | C52: 무료숙소신청 - 개인 | D52: 25 | E52: NERMIN BOTROS ZAKARIA GOHAR | F52: 네르민 | G52: F | H52: 1993-05-10 | I52: Egypt, Arab Rep. | J52: nermenbotros22@gmail.com | K52: Faculty Of Medicine Menofia University | L52: Assistant Lecturer | M52: Middle income | N52: Bursary Holder | O52: Yes | P52: 6월29일 | Q52: 7월4일 | U52: ✓ | V52: ✓ | W52: ✓ | X52: ✓ | Y52: ✓ | Z52: ✓ | AB52: 6박 | AC52: 1 | AG52: 1 | AL52: FINAL
A53: P0052 | C53: 무료숙소신청 - 개인 | D53: 26 | E53: NANCY BOTROS ZAKRIA GOHAR | G53: F | H53: 1999-08-09 | I53: Egypt, Arab Rep. | J53: nancybotros161@gmail.com | K53: Benha University Hospital | L53: Cardiothoracic Surgery Resident | M53: Middle income | N53: Bursary Holder | O53: Yes | P53: 6월29일 | Q53: 7월4일 | U53: ✓ | V53: ✓ | W53: ✓ | X53: ✓ | Y53: ✓ | Z53: ✓ | AB53: 6박 | AC53: 1 | AG53: 1 | AL53: FINAL
A54: P0053 | C54: 무료숙소신청 - 개인 | D54: 27 | E54: BODOUA ADJO ANNE-MIREILLE | G54: F | H54: 2002-06-05 | I54: Côte d’Ivoire | J54: bodouaanno@gmail.com | K54: AMPCI | L54: Medical Student | M54: Middle income | N54: Bursary Holder | O54: Yes | P54: 6월29일 | Q54: 7월4일 | U54: ✓ | V54: ✓ | W54: ✓ | X54: ✓ | Y54: ✓ | Z54: ✓ | AB54: 6박 | AC54: 1 | AG54: 1 | AL54: FINAL
A55: P0054 | C55: 무료숙소신청 - 개인 | D55: 28 | E55: KUPUALOR DAVID AKWAFO | G55: M | H55: 1979-05-04 | I55: Ghana | J55: dkupualor@yahoo.com | K55: University Of Ghana Medical Centre/St Joseph Hospital, Koforidua | L55: Senior Specialist | M55: Middle income | N55: Paid | O55: Yes | P55: 6월29일 | Q55: 7월4일 | U55: ✓ | V55: ✓ | W55: ✓ | X55: ✓ | Y55: ✓ | Z55: ✓ | AB55: 6박 | AC55: 1 | AG55: 1 | AL55: FINAL
A56: P0055 | C56: 무료숙소신청 - 개인 | D56: 29 | E56: UHUNMWANGHO COURAGE UKPONMWAN | G56: M | H56: 1974-12-27 | I56: Nigeria | J56: ucourage@yahoo.com | K56: ICMDA West Africa | L56: Regional Secretary | M56: Middle income | N56: Bursary Holder | O56: Yes | P56: 6월29일 | Q56: 7월4일 | U56: ✓ | V56: ✓ | W56: ✓ | X56: ✓ | Y56: ✓ | Z56: ✓ | AB56: 6박 | AC56: 1 | AG56: 1 | AL56: FINAL
A57: P0056 | C57: 무료숙소신청 - 개인 | D57: 30 | E57: IKEUBA DELIGHT CHIDEBELU | F57: Delight | G57: M | H57: 2005-08-15 | I57: Nigeria | J57: delightikeuba@gmail.com | K57: Christian Medical And Dental Association | L57: Mr. | M57: Middle income | N57: Bursary Holder | O57: Yes | P57: 6월30일 | Q57: 7월4일 | V57: ✓ | W57: ✓ | X57: ✓ | Y57: ✓ | Z57: ✓ | AB57: 5박 | AC57: 1 | AG57: 1 | AL57: FINAL | AM57: 한글이름 확인
A58: P0057 | C58: 무료숙소신청 - 개인 | D58: 31 | E58: ABASIRA TRINITY MUNGUFENI | G58: M | H58: 1996-06-20 | I58: Uganda | J58: tabasiramungufeni22ag@student.kcu.ac.ug | K58: King Ceasor University, Uganda Christian Medical Fellowship | L58: Student | M58: Low income | N58: Bursary Holder | O58: Yes | P58: 6월29일 | Q58: 7월4일 | U58: ✓ | V58: ✓ | W58: ✓ | X58: ✓ | Y58: ✓ | Z58: ✓ | AB58: 6박 | AC58: 1 | AG58: 1 | AL58: FINAL
A59: P0058 | C59: 무료숙소신청 - 개인 | D59: 32 | E59: KUSONGA LABAN | G59: M | H59: 2002-10-18 | I59: Uganda | J59: labkusonga20@gmail.com | K59: Kabale University/Uganda Christian Medical Fellowship | L59: Student | M59: Low income | N59: Bursary Holder | O59: Yes | P59: 6월29일 | Q59: 7월4일 | U59: ✓ | V59: ✓ | W59: ✓ | X59: ✓ | Y59: ✓ | Z59: ✓ | AB59: 6박 | AC59: 1 | AG59: 1 | AL59: FINAL
A60: P0059 | C60: 무료숙소신청 - 개인 | D60: 33 | E60: JENNIFFER LAURA DALTRO MONTEIRO DA SILVA LOURES | G60: F | H60: 1979-06-05 | I60: Brazil | J60: jldms1@gmail.com | K60: Medicos De Cristo | L60: Icmda Fieldworker Brazil Colombia And Venezuela | M60: Middle income | N60: Bursary Holder | O60: Yes | P60: 6월29일 | Q60: 7월4일 | U60: ✓ | V60: ✓ | W60: ✓ | X60: ✓ | Y60: ✓ | Z60: ✓ | AB60: 6박 | AC60: 1 | AG60: 1 | AL60: FINAL
A61: P0060 | C61: 무료숙소신청 - 개인 | D61: 34 | E61: ELITA THEOFANI JULIAWAN | G61: F | H61: 1999-12-04 | I61: Indonesia | J61: elitatheofani@yahoo.co.id | K61: ICMDA | L61: Training Track Facilitator | M61: Middle income | N61: Paid | O61: Yes | P61: 6월30일 | Q61: 7월4일 | V61: ✓ | W61: ✓ | X61: ✓ | Y61: ✓ | Z61: ✓ | AB61: 5박 | AC61: 1 | AG61: 1 | AL61: FINAL
A62: P0061 | C62: 무료숙소신청 - 개인 | D62: 35 | E62: NEMBA GRACE VAIBRA | G62: F | H62: 2001-09-29 | I62: Chad | J62: gracevaibra777@gmail.com | K62: Association Des Medecins Et Dentistes Chretiens Du Tchad(amdct) | L62: Etudiant | M62: Low income | N62: Bursary Holder | O62: Yes | P62: 6월29일 | Q62: 7월4일 | U62: ✓ | V62: ✓ | W62: ✓ | X62: ✓ | Y62: ✓ | Z62: ✓ | AB62: 6박 | AC62: 1 | AG62: 1 | AL62: FINAL
A63: P0062 | C63: 무료숙소신청 - 개인 | D63: 36 | E63: IKA SEPTIANA ERYANI | G63: F | H63: 1993-09-07 | I63: Indonesia | J63: trifosa.ikaseptiana@gmail.com | K63: Ministry Of Health, Indonesia | L63: Health Administrator | M63: Middle income | N63: Bursary Holder | O63: Yes | P63: 7월2일 | Q63: 7월4일 | X63: ✓ | Y63: ✓ | Z63: ✓ | AB63: 3박 | AC63: 1 | AG63: 1 | AL63: FINAL
A64: P0063 | C64: 무료숙소신청 - 개인 | D64: 37 | E64: ANSINO SKYLETH | G64: F | H64: 1997-01-08 | I64: Philippines | J64: skyansinophi@gmail.com | K64: Bileg Community Outreach International | L64: Resident Physician | M64: Middle income | N64: Bursary Holder | O64: Yes | P64: 7월2일 | Q64: 7월4일 | X64: ✓ | Y64: ✓ | Z64: ✓ | AB64: 3박 | AC64: 1 | AG64: 1 | AL64: FINAL
A65: P0064 | C65: 무료숙소신청 - 개인 | D65: 38 | E65: JO VEE JAVA DIGNADICE | G65: F | H65: 1964-04-16 | I65: Philippines | J65: jov@doctor.com | K65: Icmda/mccn | L65: Global Training Track Coordinator /Director | M65: Middle income | N65: Bursary Holder | O65: Yes | P65: 6월29일 | Q65: 7월4일 | U65: ✓ | V65: ✓ | W65: ✓ | X65: ✓ | Y65: ✓ | Z65: ✓ | AB65: 6박 | AC65: 1 | AG65: 1 | AL65: FINAL
A66: P0065 | C66: 무료숙소신청 - 개인 | D66: 39 | E66: FINISH FERNANDO | G66: M | H66: 1985-08-03 | I66: Indonesia | J66: finish.fernando@gmail.com | K66: Bethesda Serukam Mission Hospital | L66: Vice Director | M66: Middle income | N66: Bursary Holder | O66: Yes | P66: 6월29일 | Q66: 7월4일 | U66: ✓ | V66: ✓ | W66: ✓ | X66: ✓ | Y66: ✓ | Z66: ✓ | AB66: 6박 | AC66: 1 | AG66: 1 | AL66: FINAL
A67: P0066 | C67: 무료숙소신청 - 개인 | D67: 40 | E67: LUNKUSE HENRIETTAH DUNGU | G67: F | H67: 2000-11-25 | I67: Uganda | J67: henriettahdungu@gmail.com | K67: Islamic University In Uganda | L67: Medical Doctor | M67: Low income | N67: Bursary Holder | O67: Yes | P67: 6월30일 | Q67: 6월30일 | V67: ✓ | AB67: 1박 | AC67: 1 | AG67: 1 | AL67: FINAL
A68: P0067 | C68: 무료숙소신청 - 개인 | D68: 41 | E68: MELVAR KELLY | G68: F | H68: 1999-08-04 | I68: Kenya | J68: kellymelvar285@gmail.com | K68: Moi University | L68: Student | M68: Middle income | N68: Bursary Holder | O68: Yes | P68: 6월29일 | Q68: 7월4일 | U68: ✓ | V68: ✓ | W68: ✓ | X68: ✓ | Y68: ✓ | Z68: ✓ | AB68: 6박 | AC68: 1 | AG68: 1 | AL68: FINAL
A69: P0068 | C69: 무료숙소신청 - 개인 | D69: 42 | E69: OGUNGBANGBE OLUTOLA ESTHER | G69: F | H69: 1999-04-03 | I69: Nigeria | J69: estherogungbangbe.eo@gmail.com | K69: Abia State University Teaching Hospital/cmda Nigeria | L69: School Welfare Director/ Sister's Coordinator | M69: Middle income | N69: Paid | O69: Yes | P69: 6월29일 | Q69: 7월4일 | U69: ✓ | V69: ✓ | W69: ✓ | X69: ✓ | Y69: ✓ | Z69: ✓ | AB69: 6박 | AC69: 1 | AG69: 1 | AL69: FINAL
A70: P0069 | C70: 무료숙소신청 - 개인 | D70: 43 | E70: IRIA DOMINION OSAYOMORE | G70: M | H70: 1997-10-09 | I70: Nigeria | J70: iriadominion@gmail.com | K70: Federal Medical Centre, Owo | L70: Doctor | M70: Middle income | N70: Bursary Holder | O70: Yes | P70: 6월29일 | Q70: 7월4일 | U70: ✓ | V70: ✓ | W70: ✓ | X70: ✓ | Y70: ✓ | Z70: ✓ | AB70: 6박 | AC70: 1 | AG70: 1 | AL70: FINAL
A71: P0070 | C71: 무료숙소신청 - 개인 | D71: 44 | E71: LINGA, FIDELIS FILIBUS | G71: M | H71: 1982-05-27 | I71: Nigeria | J71: drfillinga@gmail.com | K71: Federal Teaching Hospital, Gombe Gombe State | L71: Doctor, | M71: Middle income | N71: Bursary Holder | O71: Yes | P71: 6월29일 | Q71: 7월4일 | U71: ✓ | V71: ✓ | W71: ✓ | X71: ✓ | Y71: ✓ | Z71: ✓ | AB71: 6박 | AC71: 1 | AG71: 1 | AL71: FINAL
A72: P0071 | C72: 무료숙소신청 - 개인 | D72: 45 | E72: PAUL MAYELLAWOS KARUWA | G72: M | H72: 1997-12-09 | I72: Nigeria | J72: ataschong@gmail.com | K72: CMDA-Nigeria, Kano State Chapter | L72: Dr. | M72: Middle income | N72: Bursary Holder | O72: Yes | P72: 6월29일 | Q72: 7월4일 | U72: ✓ | V72: ✓ | W72: ✓ | X72: ✓ | Y72: ✓ | Z72: ✓ | AB72: 6박 | AC72: 1 | AG72: 1 | AL72: FINAL
A73: P0072 | C73: 무료숙소신청 - 개인 | D73: 46 | E73: ADIYANA ESTI PURWANINGRUM | G73: F | H73: 1976-06-29 | I73: Indonesia | J73: adienesti@gmail.com | K73: Indonesia Christian Medical And Dental Association | L73: Mission Division Team Work | M73: Middle income | N73: Bursary Holder | O73: Yes | P73: 6월30일 | Q73: 7월4일 | V73: ✓ | W73: ✓ | X73: ✓ | Y73: ✓ | Z73: ✓ | AB73: 5박 | AC73: 1 | AG73: 1 | AL73: FINAL
A74: P0073 | C74: 무료숙소신청 - 개인 | D74: 47 | E74: ETUBI ALEXANDER IBRAHIM | G74: M | H74: 1985-12-28 | I74: Nigeria | J74: alexetubi28@gmail.com | K74: University Of Abuja Teaching Hospital/CMDA Nigeria | L74: Dr/ICMDA Regional Representative Anglophone West Africa/Deputy CEO 2 CMDA Nigeria | M74: Middle income | N74: Bursary Holder | O74: Yes | P74: 6월29일 | Q74: 7월4일 | U74: ✓ | V74: ✓ | W74: ✓ | X74: ✓ | Y74: ✓ | Z74: ✓ | AB74: 6박 | AC74: 1 | AG74: 1 | AL74: FINAL
A75: P0074 | C75: 무료숙소신청 - 개인 | D75: 48 | E75: LINDAEL GEOFREY MLAY | G75: F | H75: 1994-10-05 | I75: Tanzania | J75: mlaylinda4@gmail.com | K75: Sanya Juu Lutheran Health Centre | L75: Medical Officer In Charge | M75: Middle income | N75: Bursary Holder | O75: Yes | P75: 6월29일 | Q75: 6월29일 | U75: ✓ | AB75: 1박 | AC75: 1 | AG75: 1 | AL75: FINAL
A76: P0075 | C76: 무료숙소신청 - 개인 | D76: 49 | E76: CORNEL MARTIN ANGOLILE | G76: M | H76: 1998-08-09 | I76: Tanzania | J76: cornelangolile@gmail.com | K76: London School Of Hygiene & Tropical Medicine | L76: Dr | M76: Middle income | N76: Bursary Holder | O76: Yes | P76: 6월29일 | Q76: 7월4일 | U76: ✓ | V76: ✓ | W76: ✓ | X76: ✓ | Y76: ✓ | Z76: ✓ | AB76: 6박 | AC76: 1 | AG76: 1 | AL76: FINAL
A77: P0076 | C77: 무료숙소신청 - 개인 | D77: 50 | E77: ERIC KIPROTICH LANGAT | G77: M | H77: 1987-08-24 | I77: Kenya | J77: ericlangat77@gmail.com | K77: Tenwek Mission Hospital | L77: Dr | M77: Middle income | N77: Bursary Holder | O77: Yes | P77: 6월29일 | Q77: 7월4일 | U77: ✓ | V77: ✓ | W77: ✓ | X77: ✓ | Y77: ✓ | Z77: ✓ | AB77: 6박 | AC77: 1 | AG77: 1 | AL77: FINAL
A78: P0077 | C78: 무료숙소신청 - 개인 | D78: 51 | E78: BIIRA EUNICE | G78: F | H78: 2002-05-04 | I78: Uganda | J78: eunycebiira@gmail.com | K78: Kampala International University | L78: Student | M78: Low income | N78: Bursary Holder | O78: Yes | P78: 6월29일 | Q78: 7월4일 | U78: ✓ | V78: ✓ | W78: ✓ | X78: ✓ | Y78: ✓ | Z78: ✓ | AB78: 6박 | AC78: 1 | AG78: 1 | AL78: FINAL
A79: P0078 | C79: 무료숙소신청 - 개인 | D79: 52 | E79: YAO MAWUENA DANSOU | G79: M | H79: 1977-12-08 | I79: Togo | J79: dansouyaomawuena@gmail.com | K79: ICMDA | L79: Dr | M79: Low income | N79: Bursary Holder | O79: Yes | P79: 6월29일 | Q79: 7월4일 | U79: ✓ | V79: ✓ | W79: ✓ | X79: ✓ | Y79: ✓ | Z79: ✓ | AB79: 6박 | AC79: 1 | AG79: 1 | AL79: FINAL
A80: P0079 | C80: 무료숙소신청 - 개인 | D80: 53 | E80: KADZAHLO KOMLA DOVENE | G80: M | H80: 1987-12-17 | I80: Togo | J80: tdkadzahlo@gmail.com | K80: National Malaria Control Program Of Togo | L80: Public Health Specialist | M80: Low income | N80: Bursary Holder | O80: Yes | P80: 6월29일 | Q80: 7월4일 | U80: ✓ | V80: ✓ | W80: ✓ | X80: ✓ | Y80: ✓ | Z80: ✓ | AB80: 6박 | AC80: 1 | AG80: 1 | AL80: FINAL
A81: P0080 | C81: 무료숙소신청 - 개인 | D81: 54 | E81: SEKO KUDZOVI MARIO | G81: M | H81: 1995-01-23 | I81: Togo | J81: kudzovimarioseko@gmail.com | K81: AMCT | L81: Doctor | M81: Low income | N81: Bursary Holder | O81: Yes | P81: 6월29일 | Q81: 7월4일 | U81: ✓ | V81: ✓ | W81: ✓ | X81: ✓ | Y81: ✓ | Z81: ✓ | AB81: 6박 | AC81: 1 | AG81: 1 | AL81: FINAL
A82: P0081 | C82: 무료숙소신청 - 개인 | D82: 55 | E82: FRISYENI AMANDA MANGULE | G82: F | H82: 2005-02-19 | I82: Indonesia | J82: amandamangule05@gmail.com | K82: Udayana Univercity | L82: Student | M82: Middle income | N82: Bursary Holder | O82: Yes | P82: 6월29일 | Q82: 7월4일 | U82: ✓ | V82: ✓ | W82: ✓ | X82: ✓ | Y82: ✓ | Z82: ✓ | AB82: 6박 | AC82: 1 | AG82: 1 | AL82: FINAL
A83: P0082 | C83: 무료숙소신청 - 개인 | D83: 56 | E83: BIGOGO HERBERT CHARLES | G83: M | H83: 1997-09-22 | I83: Uganda | J83: herbertbigogo@gmail.com | K83: Uganda Christian Medical Fellowship (UCMF) | L83: National Executive- UCMF Students Liaison Secretary | M83: Low income | N83: Bursary Holder | O83: Yes | P83: 6월29일 | Q83: 7월4일 | U83: ✓ | V83: ✓ | W83: ✓ | X83: ✓ | Y83: ✓ | Z83: ✓ | AB83: 6박 | AC83: 1 | AG83: 1 | AL83: FINAL
A84: P0083 | C84: 무료숙소신청 - 개인 | D84: 57 | E84: KYABU KAPIJIMPANGA | G84: F | H84: 2002-11-15 | I84: Zambia | J84: kyabukapiji4@gmail.com | K84: Muğla Sıtkı Koçman University | L84: Medical Student | M84: Middle income | N84: Bursary Holder | O84: Yes | P84: 6월29일 | Q84: 7월4일 | U84: ✓ | V84: ✓ | W84: ✓ | X84: ✓ | Y84: ✓ | Z84: ✓ | AB84: 6박 | AC84: 1 | AG84: 1 | AL84: FINAL
A85: P0084 | C85: 무료숙소신청 - 개인 | D85: 58 | E85: ANDRIA BURI ANAK IBRAHIM | G85: M | H85: 2002-05-09 | I85: Malaysia | J85: andriaburiibrahim@gmail.com | K85: University Of Malaysia, Sarawak | L85: Medical Student | M85: Middle income | N85: Bursary Holder | O85: Yes | P85: 6월29일 | Q85: 7월4일 | U85: ✓ | V85: ✓ | W85: ✓ | X85: ✓ | Y85: ✓ | Z85: ✓ | AB85: 6박 | AC85: 1 | AG85: 1 | AL85: FINAL
A86: P0085 | C86: 무료숙소신청 - 개인 | D86: 59 | E86: ZOTCHI KOMI | G86: M | H86: 1994-12-31 | I86: Togo | J86: kzotchi94@gmail.com | K86: AMCT (Togo) | L86: Docteur | M86: Low income | N86: Bursary Holder | O86: Yes | P86: 6월29일 | Q86: 7월4일 | U86: ✓ | V86: ✓ | W86: ✓ | X86: ✓ | Y86: ✓ | Z86: ✓ | AB86: 6박 | AC86: 1 | AG86: 1 | AL86: FINAL
A87: P0086 | C87: 무료숙소신청 - 개인 | D87: 60 | E87: ADAMU ADDISSIE NURAMO | G87: M | H87: 1973-06-01 | I87: Ethiopia | J87: adamu.addissie@aaau.edu.et | K87: Addis Ababa University And CMDDF-Ethiopia | L87: MD MPH | M87: Low income | N87: Bursary Holder | O87: Yes | P87: 6월29일 | Q87: 7월4일 | U87: ✓ | V87: ✓ | W87: ✓ | X87: ✓ | Y87: ✓ | Z87: ✓ | AB87: 6박 | AC87: 1 | AG87: 1 | AL87: FINAL
... A90: P0089 | C90: 무료숙소신청 - 개인 | D90: 63 | E90: IRAKOZE CHRISTIAN | G90: M | H90: 1989-03-19 | I90: Burundi | J90: ichris255@gmail.com | K90: Burundi Christian Medical And Dental Association | L90: Advisor, National Committee | M90: Low income | N90: Bursary Holder | O90: Yes | P90: 6월29일 | Q90: 7월4일 | U90: ✓ | V90: ✓ | W90: ✓ | X90: ✓ | Y90: ✓ | Z90: ✓ | AB90: 6박 | AC90: 1 | AG90: 1 | AL90: FINAL
A91: P0090 | C91: 무료숙소신청 - 개인 | D91: 64 | E91: PRIYANI NELUM WEERAKOON | G91: F | H91: 1989-06-25 | I91: Sri Lanka | J91: 715nelumweerakoon@gmail.com | K91: ICMDA | L91: Registered Nurse | M91: Middle income | N91: Bursary Holder | O91: Yes | P91: 6월30일 | Q91: 7월4일 | V91: ✓ | W91: ✓ | X91: ✓ | Y91: ✓ | Z91: ✓ | AB91: 5박 | AC91: 1 | AG91: 1 | AL91: FINAL
A92: P0091 | C92: 무료숙소신청 - 개인 | D92: 65 | E92: MALEKA JUSTICE ILLUSTRE | G92: M | H92: 1991-07-15 | I92: Congo,Rep. | J92: justiceillustre@gmail.com | K92: Medicals Sciences Superior Institute | L92: Doctor | M92: Middle income | N92: Bursary Holder | O92: Yes | P92: 6월29일 | Q92: 6월29일 | U92: ✓ | AB92: 1박 | AC92: 1 | AG92: 1 | AL92: FINAL
A93: P0092 | C93: 무료숙소신청 - 개인 | D93: 66 | E93: ALABI FAVOUR WEALTH | G93: F | H93: 2003-06-04 | I93: Nigeria | J93: favouralabiwealth@gmail.com | K93: Bingham University Teaching Hospital, Jos | L93: School Academic Secretary Of CMDA Student Arm Bhuth Chapter | M93: Middle income | N93: Paid | O93: Yes | P93: 6월29일 | Q93: 7월4일 | U93: ✓ | V93: ✓ | W93: ✓ | X93: ✓ | Y93: ✓ | Z93: ✓ | AB93: 6박 | AC93: 1 | AG93: 1 | AL93: FINAL
A94: P0093 | C94: 무료숙소신청 - 개인 | D94: 67 | E94: MOUSSA OUMAROU | F94: Yacouba | G94: M | H94: 2000-09-24 | I94: Nigeria | J94: yacouboum33@gmail.com | K94: AMPCN | L94: Leader Étudiant | M94: Middle income | N94: Bursary Holder | O94: Yes | P94: 6월29일 | Q94: 7월4일 | U94: ✓ | V94: ✓ | W94: ✓ | X94: ✓ | Y94: ✓ | Z94: ✓ | AB94: 6박 | AC94: 1 | AG94: 1 | AL94: FINAL | AM94: 한글이름 확인
A95: P0094 | C95: 무료숙소신청 - 개인 | D95: 68 | E95: MUPFASONI BELYSE | G95: F | H95: 1992-09-21 | I95: Burundi | J95: mupfasonib1@gmail.com | K95: University Of Ngozi | L95: DR | M95: Low income | N95: Bursary Holder | O95: Yes | P95: 6월29일 | Q95: 7월4일 | U95: ✓ | V95: ✓ | W95: ✓ | X95: ✓ | Y95: ✓ | Z95: ✓ | AB95: 6박 | AC95: 1 | AG95: 1 | AL95: FINAL
A96: P0095 | C96: 무료숙소신청 - 개인 | D96: 69 | E96: IRYNA HUSHCHA | G96: F | H96: 1992-10-31 | I96: Belarus | J96: hushchairyna@gmail.com | K96: ICMDA | L96: Fieldworker | M96: Middle income | N96: Bursary Holder | O96: Yes | P96: 6월30일 | Q96: 7월4일 | V96: ✓ | W96: ✓ | X96: ✓ | Y96: ✓ | Z96: ✓ | AB96: 5박 | AC96: 1 | AG96: 1 | AL96: FINAL
A97: P0096 | C97: 무료숙소신청 - 개인 | D97: 70 | E97: TIMOTHY TAM | G97: M | H97: 1946-10-23 | I97: Canada | J97: timtamdmd@gmail.com | K97: Christian Medical Dental Association Canada | L97: Treasurer | M97: High income | N97: Paid | O97: Yes | P97: 6월29일 | Q97: 7월4일 | U97: ✓ | V97: ✓ | W97: ✓ | X97: ✓ | Y97: ✓ | Z97: ✓ | AB97: 6박 | AC97: 1 | AG97: 1 | AL97: FINAL
A98: P0097 | C98: 무료숙소신청 - 개인 | D98: 71 | E98: MATHEW SANTHOSH THOMAS | G98: M | H98: 1960-11-15 | I98: India | J98: santhosh.mathew@icmda.net | K98: ICMDA | L98: Training In Charge | M98: Middle income | N98: Bursary Holder | O98: Yes | P98: 6월29일 | Q98: 7월4일 | U98: ✓ | V98: ✓ | W98: ✓ | X98: ✓ | Y98: ✓ | Z98: ✓ | AB98: 6박 | AC98: 1 | AG98: 1 | AL98: FINAL
A99: P0098 | C99: 무료숙소신청 - 개인 | D99: 72 | E99: LUCKY SARJONO BURANDA | G99: M | H99: 1991-12-21 | I99: Indonesia | J99: mdburanda@gmail.com | K99: Indonesia CMDF | L99: MD / Department Of Mission | M99: Middle income | N99: Bursary Holder | O99: Yes | P99: 6월29일 | Q99: 7월4일 | U99: ✓ | V99: ✓ | W99: ✓ | X99: ✓ | Y99: ✓ | Z99: ✓ | AB99: 6박 | AC99: 1 | AG99: 1 | AL99: FINAL
A100: P0099 | C100: 무료숙소신청 - 개인 | D100: 73 | E100: LAY LINHHAK | G100: M | H100: 2003-08-19 | I100: Cambodia | J100: linhhak213@gmail.com | K100: University Of Health Sciences | L100: Medical Student | M100: Middle income | N100: Bursary Holder | O100: Yes | P100: 7월1일 | Q100: 7월4일 | W100: ✓ | X100: ✓ | Y100: ✓ | Z100: ✓ | AB100: 4박 | AC100: 1 | AG100: 1 | AL100: FINAL
A101: P0100 | C101: 무료숙소신청 - 개인 | D101: 74 | E101: NARO SODAVID | G101: M | H101: 2003-09-11 | I101: Cambodia | J101: narodavidktc@gmail.com | K101: University Of Health Sciences | L101: Medical Student | M101: Middle income | N101: Bursary Holder | O101: Yes | P101: 7월1일 | Q101: 7월4일 | W101: ✓ | X101: ✓ | Y101: ✓ | Z101: ✓ | AB101: 4박 | AC101: 1 | AG101: 1 | AL101: FINAL
A102: P0101 | C102: 무료숙소신청 - 개인 | D102: 75 | E102: CHHANGSOUR YMEY | G102: M | H102: 2005-01-16 | I102: Cambodia | J102: meyboy77@gmail.com | K102: University Of Health And Sciences | L102: Medical Students | M102: Middle income | N102: Bursary Holder | O102: Yes | P102: 7월1일 | Q102: 7월4일 | W102: ✓ | X102: ✓ | Y102: ✓ | Z102: ✓ | AB102: 4박 | AC102: 1 | AG102: 1 | AL102: FINAL
...

Sheet 객실
A1: 객실ID | B1: 숙소 | C1: 동 | D1: 층 | E1: 호실 | F1: 객실유형 | G1: 성별구분 | H1: 정원 | I1: 이용가능기간 | J1: 필수온돌 | K1: 비고
A2: R001 | B2: 부영청소년수련원 | C2: A | D2: 1st | E2: 124 | F2: Korean Traditional | G2: Male | H2: 6 | I2: 6/29~7/5 | J2: Y
A3: R002 | B3: 부영청소년수련원 | C3: A | D3: 1st | E3: 125 | F3: Korean Traditional | G3: Male | H3: 6 | I3: 6/29~7/5 | J3: Y
A4: R003 | B4: 부영청소년수련원 | C4: A | D4: 1st | E4: 126 | F4: Korean Traditional | G4: Male | H4: 6 | I4: 6/29~7/5 | J4: Y
A5: R004 | B5: 부영청소년수련원 | C5: A | D5: 1st | E5: 127 | F5: Korean Traditional | G5: Male | H5: 6 | I5: 6/29~7/5 | J5: Y
A6: R005 | B6: 부영청소년수련원 | C6: A | D6: 1st | E6: 128 | F6: Korean Traditional | G6: Male | H6: 6 | I6: 6/29~7/5
A7: R006 | B7: 부영청소년수련원 | C7: A | D7: 1st | E7: 129 | F7: Korean Traditional | G7: Male | H7: 6 | I7: 6/29~7/5
A8: R007 | B8: 부영청소년수련원 | C8: A | D8: 1st | E8: 130 | F8: Korean Traditional | G8: Male | H8: 6 | I8: 6/29~7/5
A9: R008 | B9: 부영청소년수련원 | C9: A | D9: 1st | E9: 131 | F9: Korean Traditional | G9: Male | H9: 6 | I9: 6/29~7/5
A10: R009 | B10: 부영청소년수련원 | C10: A | D10: 1st | E10: 132 | F10: Korean Traditional | G10: Male | H10: 6 | I10: 6/29~7/5
A11: R010 | B11: 부영청소년수련원 | C11: A | D11: 1st | E11: 133 | F11: Korean Traditional | G11: Male | H11: 6 | I11: 6/29~7/5 | J11: Y
A12: R011 | B12: 부영청소년수련원 | C12: A | D12: 1st | E12: 134 | F12: Korean Traditional | G12: Male | H12: 6 | I12: 6/29~7/5 | J12: Y
A13: R012 | B13: 부영청소년수련원 | C13: A | D13: 1st | E13: 135 | F13: Korean Traditional | G13: Male | H13: 6 | I13: 6/29~7/5
A14: R013 | B14: 부영청소년수련원 | C14: A | D14: 1st | E14: 136 | F14: Korean Traditional | G14: Male | H14: 6 | I14: 6/29~7/5
A15: R014 | B15: 부영청소년수련원 | C15: A | D15: 1st | E15: 137 | F15: Korean Traditional | G15: Male | H15: 6 | I15: 6/29~7/5
A16: R015 | B16: 부영청소년수련원 | C16: A | D16: 1st | E16: 138 | F16: Korean Room | G16: Male | H16: 6 | I16: 6/29~7/5
A17: R016 | B17: 부영청소년수련원 | C17: A | D17: 2nd | E17: 226 | F17: Korean Traditional | G17: Female | H17: 6 | I17: 6/29~7/5
A18: R017 | B18: 부영청소년수련원 | C18: A | D18: 2nd | E18: 227 | F18: Bed For 2 | G18: Staff | H18: 2 | I18: 6/29~7/5
A19: R018 | B19: 부영청소년수련원 | C19: A | D19: 2nd | E19: 228 | F19: Korean Traditional | G19: Female | H19: 6 | I19: 6/29~7/5
A20: R019 | B20: 부영청소년수련원 | C20: A | D20: 2nd | E20: 229 | F20: Korean Traditional | G20: Female | H20: 6 | I20: 6/29~7/5
A21: R020 | B21: 부영청소년수련원 | C21: A | D21: 2nd | E21: 230 | F21: Korean Traditional | G21: Female | H21: 6 | I21: 6/29~7/5
A22: R021 | B22: 부영청소년수련원 | C22: A | D22: 2nd | E22: 231 | F22: Korean Traditional | G22: Female | H22: 6 | I22: 6/29~7/5
A23: R022 | B23: 부영청소년수련원 | C23: A | D23: 2nd | E23: 232 | F23: Korean Traditional | G23: Female | H23: 6 | I23: 6/29~7/5
A24: R023 | B24: 부영청소년수련원 | C24: A | D24: 2nd | E24: 233 | F24: Korean Traditional | G24: Female | H24: 6 | I24: 6/29~7/5
... A80: R079 | B80: 부영청소년수련원 | C80: B | D80: 2nd | E80: 225 | F80: Bed For 2 | G80: Staff | H80: 2 | I80: 6/29~7/5
A81: R080 | B81: 유어스호텔 | F81: Deluxe Twin | H81: 2 | I81: 6/29~7/6
A82: R081 | B82: 유어스호텔 | F82: Deluxe Twin | H82: 2 | I82: 6/29~7/6
A83: R082 | B83: 유어스호텔 | F83: Deluxe Twin | H83: 2 | I83: 6/29~7/6
A84: R083 | B84: 유어스호텔 | F84: Deluxe Twin | H84: 2 | I84: 6/29~7/6
A85: R084 | B85: 유어스호텔 | F85: Deluxe Twin | H85: 2 | I85: 6/29~7/6
A86: R085 | B86: 유어스호텔 | F86: Deluxe Twin | H86: 2 | I86: 6/29~7/6
A87: R086 | B87: 유어스호텔 | F87: Deluxe Twin | H87: 2 | I87: 6/29~7/6
A88: R087 | B88: 유어스호텔 | F88: Deluxe Twin | H88: 2 | I88: 6/29~7/6
A89: R088 | B89: 유어스호텔 | F89: Deluxe Twin | H89: 2 | I89: 6/29~7/6
A90: R089 | B90: 유어스호텔 | F90: Deluxe Twin | H90: 2 | I90: 6/29~7/6
A91: R090 | B91: 유어스호텔 | F91: Deluxe Twin | H91: 2 | I91: 6/29~7/6
A92: R091 | B92: 유어스호텔 | F92: Deluxe Twin | H92: 2 | I92: 6/29~7/6
... A130: R129 | B130: 유어스호텔 | F130: YOUUS Suite | H130: 4 | I130: 6/29~7/6
