Workbook

Sheet World Bank Categories
B2: World Bank Categories
B3: Country Name | C3: Gross National Income(GNI)
B4: Afghanistan | C4: Low income
B5: Albania | C5: Middle income
B6: Algeria | C6: Middle income
B7: American Samoa | C7: High income
B8: Andorra | C8: High income
B9: Angola | C9: Middle income
B10: Antigua and Barbuda | C10: High income
B11: Argentina | C11: Middle income
B12: Armenia | C12: Middle income
B13: Aruba | C13: High income
B14: Australia | C14: High income
... B220: Zimbabwe | C220: Middle income

Sheet 26.05.29 기준 전체 숙소 신청자 명단
A2: =COUNTA(B5:B14999) -> 926 | C2: Godsends 등록자 수 | D2: =COUNTIF(Q5:Q1063,"등록") -> 864 | F2: Godsends 미등록자 수 | G2: =COUNTIF(Q5:Q2999,"미등록") -> 61 | I2: paid 완료 | J2: =COUNTA(R5:R14999) -> 577
A4: Timestamp | B4: 1. Name As it appears on your passport | C4: 2. Name (Korean): | D4: 3. Gender: | E4: 4. Date of Birth: (MM-DD-YYYY) | F4: 5. Nationality As it appears on your passport | G4: 6. Affiliation School/Institution/Organization Name | H4: 7. Title/Position | I4: 8. World Bank Category Found on your Registration Tab | J4: 9. Email Address Must be the same email used for registration | K4: 10. ICMDA Event You Plan to Attend | L4: 11. Free Accommodation Request Dates | M4: 12. Accompanying Family Member(s)(Name/Gender/Relationship): Are you bringing family member(s)? If yes, please indicate how many will accompany you and provide their name, gender, and relationship (ex: 1, John Doe, male, husband, John_D@gmail.com) | N4: 동반자 전체 요악 | O4: 본인 포함 총 인원(가족 단위 경우만) | P4: 13. Consent for Personal Information Use I hereby consent to the collection and use of the personal information provided above for the purpose of evaluating my application for ICMDA free accommodation and for related communications. | Q4: 등록판정 | R4: Paid | S4: 매칭된 godsends 이름 | T4: 매칭된 godsends 생년월일 | U4: 매칭된 godsends 이메일 | V4: 판정 근거 | W4: Column 1
A5: 45841.453 | B5: Elisa Mabel Galeano Gamarra | D5: Female | E5: 35614 | F5: Paraguay | G5: in the process of having an association in Paraguay | H5: doctor | I5: =VLOOKUP(CLEAN(F5),'World Bank Categories'!$B$4:$C$220,2,FALSE) -> Middle income | J5: elisamedoficial@gmail.com | K5: Pre-Conference + Main Congress | L5: June 29, June 30, July 1, July 2, July 3, July 4 | P5: Agree | Q5: 등록 | R5: bursary | S5: Elisa Mabel Galeano Gamarra
A6: 45843.795 | B6: NZAME Yolande | D6: Female | E6: 21016 | F6: Gabon | G6: Gabon Medical Chrétien | H6: Membre | I6: =VLOOKUP(CLEAN(F6),'World Bank Categories'!$B$4:$C$220,2,FALSE) -> Middle income | J6: yolandenzame@gmail.com | K6: Main Congress Only | L6: June 29, June 30, July 1, July 2, July 3, July 4 | M6: Rebecca, féminin, fille, vierin.rebecca@hotmail.fr | N6: Rebecca [딸] | O6: 2명/ (자녀 1명) | P6: Agree | Q6: 등록 | R6: paid | S6: NZAME Yolande
A7: 45846.76 | B7: KALIBBALA EMMANUEL | D7: Male | E7: 36912 | F7: UGANDA | G7: Gulu University | H7: Mr. | I7: =VLOOKUP(CLEAN(F7),'World Bank Categories'!$B$4:$C$220,2,FALSE) -> Low income | J7: kalex122001@gmail.com | K7: Main Congress Only | L7: June 29, June 30, July 1, July 2, July 3, July 4 | P7: Agree | Q7: 등록 | S7: KALIBBALA EMMANUEL
A8: 45849.777 | B8: Edwin Njore Irungu | D8: Male | E8: 32541 | F8: Kenya | G8: PCEA Kikuyu Hospital | H8: Mr | I8: =VLOOKUP(CLEAN(F8),'World Bank Categories'!$B$4:$C$220,2,FALSE) -> Middle income | J8: irunguedwin8@gmail.com | K8: Main Congress Only | L8: June 29, June 30, July 1, July 2, July 3, July 4 | P8: Agree | Q8: 미등록
A9: 45853.25 | B9: Blessings Dendere | D9: Female | E9: 36458 | F9: Zimbabwe | G9: Christian Medical Fellowship | H9: Doctor | I9: =VLOOKUP(CLEAN(F9),'World Bank Categories'!$B$4:$C$220,2,FALSE) -> Middle income | J9: blessingszd@gmail.com | K9: Pre-Conference + Main Congress | L9: June 29, June 30, July 1, July 2, July 3, July 4 | P9: Agree | Q9: 등록 | R9: bursary | S9: Blessings Dendere
A10: 45856.25 | B10: Ilivieda Omamezi Annah | D10: Female | E10: 38134 | F10: Nigeria | G10: University of Ilorin | H10: Student | I10: =VLOOKUP(CLEAN(F10),'World Bank Categories'!$B$4:$C$220,2,FALSE) -> Middle income | J10: omasax94@gmail.com | K10: Student Conference + Main Congress | L10: June 29, June 30, July 1, July 2, July 3, July 4 | P10: Agree | Q10: 미등록
A11: 45856.751 | B11: AGNESS SAIMON KASWAGA | D11: Female | E11: 37063 | F11: Tanzania | G11: KCMC | H11: MEDICAL DOCTOR | I11: =VLOOKUP(CLEAN(F11),'World Bank Categories'!$B$4:$C$220,2,FALSE) -> Middle income | J11: Saimonagness58@gmail.com | K11: Main Congress Only | L11: June 29, June 30, July 1, July 2, July 3, July 4 | P11: Agree | Q11: 등록 | S11: AGNESS S KASWAGA | T11: 36698 | U11: Saimonagness58@gmail.com | V11: 이메일 일치, 이름 유사도 93
A12: 45857.619 | B12: Virginia Baraza Dangi | D12: Female | E12: 38314 | F12: Tanzania | G12: KCMC University | H12: Student | I12: =VLOOKUP(CLEAN(F12),'World Bank Categories'!$B$4:$C$220,2,FALSE) -> Middle income | J12: vibaseche23@gmail.com | K12: Pre-Conference + Main Congress | L12: June 29, June 30, July 1, July 2, July 3, July 4 | P12: Agree | Q12: 등록 | S12: Virginia Baraza Dangi | T12: 38314 | U12: Vibaseche23@gmail.com | V12: 생년월일 일치, 이메일 일치, 이름 완전일치
A13: 45859.287 | B13: Muhumuza Ndamage Stephen | C13: Not Korean | D13: Male | E13: 29178 | F13: Rwanda | G13: Rwanda Christian Medical and Dental Organization | H13: Head of Rwanda Christian Medical and a Dental Organization | I13: =VLOOKUP(CLEAN(F13),'World Bank Categories'!$B$4:$C$220,2,FALSE) -> Low income | J13: stephen20130@gmail.com | K13: Student Conference + Main Congress | L13: 46207 | P13: Agree | Q13: 등록 | R13: bursary | S13: Muhumuza Ndamage Stephen | T13: 29178 | U13: stephen20130@gmail.com | V13: 생년월일 일치, 이메일 일치, 이름 완전일치
A14: 45859.316 | B14: Modestin Nahimana | D14: Male | E14: 36278 | F14: Burundi | G14: Christian Medical Student Fellowship in Rwanda | H14: Member | I14: =VLOOKUP(CLEAN(F14),'World Bank Categories'!$B$4:$C$220,2,FALSE) -> Low income | J14: modestin.nahimana@gmail.com | K14: Student Conference + Main Congress | L14: June 29, June 30, July 1, July 2, July 3, July 4 | P14: Agree | Q14: 미등록
A15: 45859.598 | B15: UWIMANA Kevine | D15: Female | E15: 37368 | F15: Rwanda | G15: Rwanda Christian medical and dental organization | H15: Student | I15: =VLOOKUP(CLEAN(F15),'World Bank Categories'!$B$4:$C$220,2,FALSE) -> Low income | J15: kevineuwimana01@gmail.com | K15: Student Conference + Main Congress | L15: 46207 | Q15: 등록 | S15: Uwimana Kevine | T15: 37368 | U15: kevineuwimana01@gmail.com | V15: 생년월일 일치, 이메일 일치, 이름 완전일치
A16: 45859.6 | B16: Munezero Noella | D16: Female | E16: 35424 | F16: Rwanda | G16: Rwanda christian medical and dental organization | H16: Medical Doctor | I16: =VLOOKUP(CLEAN(F16),'World Bank Categories'!$B$4:$C$220,2,FALSE) -> Low income | J16: Munono 25@gmail.com | K16: Pre-Conference + Main Congress | L16: June 29, June 30, July 1, July 2, July 3, July 4 | P16: Agree | Q16: 등록 | S16: Munezero Noella | T16: 35424 | U16: Munono25@gmail.com | V16: 생년월일 일치, 이름 완전일치
A17: 45859.616 | B17: Uwizeyimana Marie Grace | D17: Female | E17: 37239 | F17: Rwanda | G17: Rwanda Christian medical and dental organization | H17: Student | I17: =VLOOKUP(CLEAN(F17),'World Bank Categories'!$B$4:$C$220,2,FALSE) -> Low income | J17: Umg | K17: Pre-Conference + Main Congress | L17: June 29, June 30, July 1, July 2, July 3, July 4 | P17: Agree | Q17: 미등록
A18: 45859.617 | B18: NIYOKWIZERWA Moise | D18: Male | E18: 37362 | F18: Rwanda | G18: Rwanda christian medical and dental organisation | H18: Student leader | I18: =VLOOKUP(CLEAN(F18),'World Bank Categories'!$B$4:$C$220,2,FALSE) -> Low income | J18: niyokwizerwamoise910@gmail.com | K18: Pre-Conference + Main Congress | L18: 46207 | P18: Agree | Q18: 등록 | S18: Niyokwizerwa Moise | T18: 37362 | U18: niyokwizerwamoise910@gmail.com | V18: 생년월일 일치, 이메일 일치, 이름 완전일치
A19: 45859.624 | B19: NIYIREMA Olive | D19: Female | E19: 35154 | F19: Rwanda | G19: Affiliation is RWanda Christian Medical and Dental Organization Not CMSF RWanda Christian Medical and Dental Organization | H19: Doctor | I19: =VLOOKUP(CLEAN(F19),'World Bank Categories'!$B$4:$C$220,2,FALSE) -> Low income | J19: olivenini2020@gmail.com | K19: Pre-Conference + Main Congress | L19: June 29, June 30, July 1, July 2, July 3, July 4 | P19: Agree | Q19: 등록 | S19: Olive NIYIREMA | T19: 35632 | U19: olivenini2020@gmail.com | V19: 이메일 일치, 이름 유사도 100, 이름 토큰 포함
A20: 45859.629 | B20: Tusahirwa innocent | D20: Male | E20: 37457 | F20: Rwanda | G20: Rwanda chritian medical and dental organisation | H20: Student's leader | I20: =VLOOKUP(CLEAN(F20),'World Bank Categories'!$B$4:$C$220,2,FALSE) -> Low income | J20: tuzahirwainnocent@gmail.com | K20: Student Conference + Main Congress | L20: June 29, June 30, July 1, July 2, July 3, July 4 | P20: Agree | Q20: 미등록
A21: 45859.641 | B21: ISHIMWE Jacques | C21: ISHIMWE Jacques | D21: Male | E21: 37622 | F21: Rwanda | G21: Rwanda Christian Medical and Dental organization | H21: Student | I21: =VLOOKUP(CLEAN(F21),'World Bank Categories'!$B$4:$C$220,2,FALSE) -> Low income | J21: asinathamukakarera@gmail.com | K21: Pre-Conference + Main Congress | L21: 46207 | P21: Agree | Q21: 등록 | S21: ISHIMWE Jacques | T21: 37622 | U21: asinathamukakarera@gmail.com | V21: 생년월일 일치, 이메일 일치, 이름 완전일치
A22: 45859.642 | B22: Uwingabire Marie Solange | D22: Female | E22: 38330 | F22: Rwanda | G22: University of Rwanda | H22: Student | I22: =VLOOKUP(CLEAN(F22),'World Bank Categories'!$B$4:$C$220,2,FALSE) -> Low income | J22: uwingabiresolange19@gmail.com | K22: Student Conference + Main Congress | L22: June 29, June 30, July 1, July 2, July 3, July 4 | P22: Agree | Q22: 미등록
A23: 45859.646 | B23: Tobi Joyce Omonefe | D23: Female | E23: 37760 | F23: Nigeria | G23: Rwanda Christian Medical and Dental Organization | H23: Student | I23: =VLOOKUP(CLEAN(F23),'World Bank Categories'!$B$4:$C$220,2,FALSE) -> Middle income | J23: joycie1619@gmail.com | K23: Pre-Conference + Main Congress | L23: 46207 | P23: Agree | Q23: 등록 | S23: Joyce Tobi | T23: 37760 | U23: joycie2124@gmail.com | V23: 생년월일 일치, 이름 유사도 100, 이름 토큰 포함
A24: 45859.655 | B24: Patrick GISUBIZO | D24: Male | E24: 37756 | F24: Rwanda | G24: University of Rwanda | H24: Mr. | I24: =VLOOKUP(CLEAN(F24),'World Bank Categories'!$B$4:$C$220,2,FALSE) -> Low income | J24: gisubizopatrick095@gmail.com | K24: Student Conference + Main Congress | L24: June 29, June 30, July 1, July 2, July 3, July 4 | P24: Agree | Q24: 미등록
A25: 45859.657 | B25: ABAYISENGA Stella | D25: Female | E25: 38183 | F25: Rwanda | G25: University of Rwanda | H25: Student | I25: =VLOOKUP(CLEAN(F25),'World Bank Categories'!$B$4:$C$220,2,FALSE) -> Low income | J25: stellabayisenga@gmail.com | K25: Student Conference + Main Congress | L25: June 29, June 30, July 1, July 2, July 3, July 4 | M25: 9, Stella,female, children, stellabayisenga@gmail.com | N25: Stella [자녀] | O25: 2명/ (자녀 1명) | P25: Agree | Q25: 미등록
A26: 45859.675 | B26: NGABOYUMWAMI Jean Paul | C26: Rwandan ID | D26: Male | E26: 37594 | F26: Rwanda | G26: University of Rwanda | H26: Medical Student | I26: =VLOOKUP(CLEAN(F26),'World Bank Categories'!$B$4:$C$220,2,FALSE) -> Low income | J26: jeanpaulngaboyumwami@gmail.com | K26: Student Conference + Main Congress | L26: June 29, June 30, July 1, July 2, July 3, July 4 | P26: Agree | Q26: 등록 | S26: NGABOYUMWAMI Jean Paul | T26: 45762 | U26: jeanpaulngaboyumwami@gmail.com | V26: 이메일 일치
A27: 45859.792 | B27: Mbonimpa James | D27: Male | E27: 37455 | F27: Rwanda | G27: RCMDO ( Rwanda Christian Medical and Dental Organisation | H27: Medical Student | I27: =VLOOKUP(CLEAN(F27),'World Bank Categories'!$B$4:$C$220,2,FALSE) -> Low income | J27: jamesmbonimpa904@gmail.com | K27: Pre-Conference + Main Congress | L27: June 29, June 30, July 1, July 2, July 3, July 4 | P27: Agree | Q27: 미등록
A28: 45860.185 | B28: Nsanzimfura Pacifique | C28: Nsanzimfura Pacifique | D28: Male | E28: 38109 | F28: Rwanda | G28: University of Rwanda | H28: Mr | I28: =VLOOKUP(CLEAN(F28),'World Bank Categories'!$B$4:$C$220,2,FALSE) -> Low income | J28: nsanzimfurapacifique@gmail.com | K28: Student Conference + Main Congress | L28: June 29, June 30, July 1, July 2, July 3, July 4 | P28: Agree | Q28: 등록 | S28: Nsanzimfura Pacifique | T28: 38109 | U28: nsanzimfurapacifique@gmail.com | V28: 생년월일 일치, 이메일 일치, 이름 완전일치
A29: 45860.593 | B29: Jean d'Amour HABINSHUTI | D29: Male | E29: 34335 | F29: Rwanda | G29: Rwanda Christian Medical and Dental Organization | H29: Student | I29: =VLOOKUP(CLEAN(F29),'World Bank Categories'!$B$4:$C$220,2,FALSE) -> Low income | J29: jdhabinshuti@gmail.com | K29: Pre-Conference + Main Congress | L29: 46207 | P29: Agree | Q29: 미등록
A30: 45860.797 | B30: Umuhoza Marie Claire | D30: Female | E30: 35013 | F30: Rwanda | G30: Public Hospital | H30: Junior Doctor | I30: =VLOOKUP(CLEAN(F30),'World Bank Categories'!$B$4:$C$220,2,FALSE) -> Low income | J30: umumariec1@gmail.com | K30: Main Congress Only | L30: July 1, July 2, July 3, July 4 | P30: Agree | Q30: 등록 | S30: Marie Claire Umuhoza | T30: 35013 | U30: umumariec1@gmail.com | V30: 생년월일 일치, 이메일 일치, 이름 유사도 100, 이름 토큰 포함
A31: 45860.808 | B31: MAOMBI Melanie | D31: Female | E31: 35285 | F31: Rwanda | G31: University of Rwanda | H31: Resident | I31: =VLOOKUP(CLEAN(F31),'World Bank Categories'!$B$4:$C$220,2,FALSE) -> Low income | J31: melaniemaombi@gmail.com | K31: Pre-Conference + Main Congress | L31: June 29, June 30, July 1, July 2, July 3, July 4 | M31: 1, BITEGETSIMANA GEDEON, male, husband | P31: Agree | Q31: 미등록
A32: 45860.823 | B32: Donath SINABUBARAGA | D32: Male | E32: 36362 | F32: Rwanda | G32: Rwanda Christian Medical and Dental Organization | H32: student | I32: =VLOOKUP(CLEAN(F32),'World Bank Categories'!$B$4:$C$220,2,FALSE) -> Low income | J32: dosinabubaraga@gmail.com | K32: Pre-Conference + Main Congress | L32: June 30, July 1, July 2, July 3, July 4 | P32: Agree | Q32: 미등록
A33: 45860.982 | B33: Ruvimbo Mutize | D33: Female | E33: 37253 | F33: Zimbabwe | G33: National University of Science and Technology (NUST) | H33: Student | I33: =VLOOKUP(CLEAN(F33),'World Bank Categories'!$B$4:$C$220,2,FALSE) -> Middle income | J33: mutizer28@gmail.com | K33: Main Congress Only | L33: June 30, July 1, July 2, July 3, July 4 | P33: Agree | Q33: 등록 | S33: Ruvimbo Mutize
A34: 45861.652 | B34: INGABIRE Emeline | D34: Female | E34: 36721 | F34: Rwanda | G34: Rwanda Christian Medical and Dental Organisation | H34: Student | I34: =VLOOKUP(CLEAN(F34),'World Bank Categories'!$B$4:$C$220,2,FALSE) -> Low income | J34: emelinerda@gmail.com | K34: Student Conference + Main Congress | L34: June 29, June 30, July 1, July 2, July 3, July 4 | P34: Agree | Q34: 미등록
A35: 45862.865 | B35: Unkwiye hertier | D35: Male | E35: 36536 | F35: Rwanda | G35: Rwanda Christian Medical and Dental Organization (RCMDO) | H35: President of Chritian medical student fellowship -Remera chapter | I35: =VLOOKUP(CLEAN(F35),'World Bank Categories'!$B$4:$C$220,2,FALSE) -> Low income | J35: hertierunkwiye1@gmail.com | K35: Main Congress Only | L35: June 30, July 1, July 2, July 3, July 4 | P35: Agree | Q35: 미등록
A36: 45862.937 | B36: BANA Keys Pamela | C36: Pamla Keys BANA | D36: Female | E36: 38542 | F36: Rwanda | G36: Rwanda Christian Medical and dental Organization | H36: Student | I36: =VLOOKUP(CLEAN(F36),'World Bank Categories'!$B$4:$C$220,2,FALSE) -> Low income | J36: kpamela210@gmail.com | K36: Student Conference + Main Congress | L36: June 29, June 30, July 1, July 2, July 3, July 4 | P36: Agree | Q36: 미등록
A37: 45865.161 | B37: MUTABARUKA John | D37: Male | E37: 45908 | F37: Rwanda | G37: Rwanda Christian Medical and Dental Organization. | H37: Student Leader | I37: =VLOOKUP(CLEAN(F37),'World Bank Categories'!$B$4:$C$220,2,FALSE) -> Low income | J37: mutabarukajohn250@gmail.com | K37: Pre-Conference + Main Congress | L37: June 29, June 30, July 1, July 2, July 3, July 4 | P37: Agree | Q37: 미등록
A38: 45865.165 | B38: KILACH CAROLE JESANG | D38: Female | E38: 32229 | F38: Kenya | G38: CHRISTIAN MEDICAL FELLOWSHIP- KENYA | H38: Dr/Miss/ Regional Leader | I38: =VLOOKUP(CLEAN(F38),'World Bank Categories'!$B$4:$C$220,2,FALSE) -> Middle income | J38: carolejesang@gmail.com | K38: Pre-Conference + Main Congress | L38: June 29, June 30, July 1, July 2, July 3, July 4 | P38: Agree | Q38: 등록 | R38: paid | S38: KILACH CAROLE JESANG | T38: 32229 | U38: carolejesang@gmail.com | V38: 생년월일 일치, 이메일 일치, 이름 완전일치
A39: 45865.819 | B39: Mugeni Adeline | D39: Female | E39: 28995 | F39: Rwanda | G39: Rwanda Christian Medical and Dental Organisation | H39: Dr | I39: =VLOOKUP(CLEAN(F39),'World Bank Categories'!$B$4:$C$220,2,FALSE) -> Low income | J39: mugenia23@gmail.com | K39: Pre-Conference + Main Congress | L39: June 29, June 30, July 1, July 2, July 3, July 4 | P39: Agree | Q39: 등록 | S39: Adeline Mugeni | T39: 28995 | U39: mugenia23@gmail.com | V39: 생년월일 일치, 이메일 일치, 이름 유사도 100, 이름 토큰 포함
A40: 45865.819 | B40: KANANGA Wilson | D40: Male | E40: 35647 | F40: Rwanda | G40: Nyamata level two Teaching Hospital | H40: Intern Doctor | I40: =VLOOKUP(CLEAN(F40),'World Bank Categories'!$B$4:$C$220,2,FALSE) -> Low income | J40: kanawilson01@gmail.com | K40: Pre-Conference + Main Congress | L40: June 30, July 1, July 2, July 3, July 4 | P40: Agree | Q40: 미등록
A41: 45866.256 | B41: BUTOYI Alphonse | C41: BUTOYI Alphonse | D41: Male | E41: 26966 | F41: Rwanda | G41: Legacy Clinics | H41: Senior consultant Obstetrician &Gyneacologist | I41: =VLOOKUP(CLEAN(F41),'World Bank Categories'!$B$4:$C$220,2,FALSE) -> Low income | J41: alphonse.butoyi@doctor.com | K41: Main Congress Only | L41: July 1, July 2, July 3, July 4 | P41: Agree | Q41: 미등록
A42: 45870.142 | B42: Aline Garcia Pereira | C42: Aline Garcia Pereira | D42: Female | E42: 32847 | F42: Brazil | G42: Uniasselvi (University)/ MDC -Medicos de Cristo | H42: I am student of Health Management (graduation). But I am also PHD | I42: =VLOOKUP(CLEAN(F42),'World Bank Categories'!$B$4:$C$220,2,FALSE) -> Middle income | J42: alinegpereira1@gmail.com | K42: Student Conference + Main Congress | L42: June 29, June 30, July 1, July 2, July 3, July 4 | P42: Agree | Q42: 등록 | R42: paid | S42: Aline Garcia Pereira | T42: 32847 | U42: alinegpereira1@gmail.com | V42: 생년월일 일치, 이메일 일치, 이름 완전일치
A43: 45871.144 | B43: Aida Olinda Lizano Alarcón | D43: Female | E43: 31443 | F43: Peru | G43: Asociacion Cristiana de Profesionales de la Salud del Perú | H43: Medico Internista | I43: =VLOOKUP(CLEAN(F43),'World Bank Categories'!$B$4:$C$220,2,FALSE) -> Middle income | J43: aida.lizanoo@gmail.com | K43: Main Congress Only | L43: June 29, June 30, July 1, July 2, July 3, July 4 | P43: Agree | Q43: 미등록
A44: 45871.236 | B44: PAUL STEPHEN ATARO AYELLA | D44: Male | E44: 28186 | F44: Uganda | G44: ICMDA | H44: REGIONAL REPRESENTATIVE EAST AFRICA | I44: =VLOOKUP(CLEAN(F44),'World Bank Categories'!$B$4:$C$220,2,FALSE) -> Low income | J44: ATARODRPAPA@GMAIL.COM | K44: Student Conference + Main Congress | L44: June 29, June 30, July 1, July 2, July 3, July 4 | M44: ATARO JANE KARINA, FEMALE. ATARO NEEMA ANGIOLETTA, FEMALE DAUGHTERS | N44: ATARO JANE KARINA, FEMALE. ATARO NEEMA ANGIOLETTA, FEMALE DAUGHTERS 딸 2명 | O44: 3명/ (자녀 2명) | P44: Agree | Q44: 등록 | R44: bursary | S44: Paul Stephen Ataro Ayella | T44: 28186 | U44: atarodrpapa@gmail.com | V44: 생년월일 일치, 이메일 일치, 이름 완전일치
A45: 45874.23 | B45: Mugaba Proscovia Mujeere | D45: Female | E45: 28943 | F45: Uganda | G45: Uganda Christian Medical Fellowship (UCMF) | H45: Chairperson of UCMF National Executive Committee | I45: =VLOOKUP(CLEAN(F45),'World Bank Categories'!$B$4:$C$220,2,FALSE) -> Low income | J45: drprosiemm@gmail.com | K45: Main Congress Only | L45: June 30, July 1, July 2, July 3, July 4 | P45: Agree | Q45: 등록 | R45: bursary | S45: Proscovia Mujeere Mugaba
A46: 45874.567 | B46: Mujwala Samuel Kagali | D46: Male | E46: 36651 | F46: Uganda | G46: Soroti university | H46: SOROTI UNIVRSITY CMF CHAIRPERSON | I46: =VLOOKUP(CLEAN(F46),'World Bank Categories'!$B$4:$C$220,2,FALSE) -> Low income | J46: 2101600045@sun.ac.ug | K46: Student Conference + Main Congress | L46: June 29, June 30, July 1, July 2, July 3, July 4 | P46: Agree | Q46: 등록 | S46: Mujwala Samuel Kagali | T46: 36651 | U46: 2101600045@sun.ac.ug | V46: 생년월일 일치, 이메일 일치, 이름 완전일치
A47: 45875.633 | B47: Theodorus Hedwin Kadrianto | D47: Male | E47: 32327 | F47: Indonesia | G47: ICMDA | H47: AEO for East Asia, Southeast Asia, Oceania | I47: =VLOOKUP(CLEAN(F47),'World Bank Categories'!$B$4:$C$220,2,FALSE) -> Middle income | J47: theodorus.hedwin@icmda.net | K47: Pre-Conference + Main Congress | L47: June 29, June 30, July 1, July 2, July 3, July 4 | P47: Agree | Q47: 등록 | R47: paid | S47: Theodorus Hedwin Kadrianto | T47: 32327 | U47: theodorus.hedwin@icmda.net | V47: 생년월일 일치, 이메일 일치, 이름 완전일치
A48: 45877.788 | B48: Sally John | C48: Sally | D48: Female | E48: 45883 | F48: South Africa | G48: ICMDA | H48: Dr Phd | I48: =VLOOKUP(CLEAN(F48),'World Bank Categories'!$B$4:$C$220,2,FALSE) -> Middle income | J48: Johnsally728@gmail.com | K48: Pre-Conference + Main Congress | L48: June 29, June 30, July 1, July 2, July 3, July 4 | P48: Agree | Q48: 등록 | S48: Sally John | T48: 20712 | U48: johnsally728@gmail.com | V48: 이메일 일치, 이름 완전일치
A49: 45881.297 | B49: Kamanzi | C49: Umuhire Immaculée | D49: Female | E49: 24605 | F49: Rwanda | G49: Rwanda Christian Medical and Dental Organization | H49: Dental Surgeon /Member | I49: =VLOOKUP(CLEAN(F49),'World Bank Categories'!$B$4:$C$220,2,FALSE) -> Low income | J49: immakamanziu@gmail.com | K49: Main Congress Only | L49: June 29, July 4 | M49: Kabasinge Kamanzi Icyeza Gracia, Female, Daughter, kabkamicyezagracia@gmail.com | N49: Kabasinge Kamanzi Icyeza Gracia [딸] | O49: 2명/ (자녀 1명) | P49: Agree | Q49: 미등록
A50: 45883.567 | B50: PETER SATHIYANATHAN MICHEAL JOHN | D50: Male | E50: 28573 | F50: MALAYSIA | G50: HEALTHCARE CHRISTIAN FELLOWSHIP MALAYSIA | H50: DOCTOR | I50: =VLOOKUP(CLEAN(F50),'World Bank Categories'!$B$4:$C$220,2,FALSE) -> Middle income | J50: doctorpeter@hotmail.com | K50: Main Congress Only | L50: July 1, July 2, July 3, July 4 | M50: IRINE AARATHANA PETER SATHIYANATHAN, FEMALE, - 12 YEARS OLD DAUGHTER , doctorpeter@hotmail.com | N50: IRINE AARATHANA PETER SATHIYANATHAN [딸, 12세] | O50: 2명/ (자녀 1명) | P50: Agree | Q50: 등록 | R50: paid | S50: PETER SATHIYANATHAN MICHEAL JOHN | T50: 28573 | U50: doctorpeter@hotmail.com | V50: 생년월일 일치, 이메일 일치, 이름 완전일치
A51: 45890.989 | B51: Alina | D51: Female | E51: 36334 | F51: Belarus | G51: Belarussian CMF | H51: Ophtalmologist | I51: =VLOOKUP(CLEAN(F51),'World Bank Categories'!$B$4:$C$220,2,FALSE) -> Middle income | J51: kurdunap@gmail.com | K51: Main Congress Only | L51: June 29, June 30, July 1, July 2, July 3, July 4 | P51: Agree | Q51: 등록 | R51: bursary | S51: Alina Kurdun
A52: 45891.188 | B52: Vincent, Benjamin Terfa | D52: Male | E52: 34606 | F52: Nigeria | G52: Christian Medical and Dental Association of Nigeria - Doctors' Arm | H52: Member | I52: =VLOOKUP(CLEAN(F52),'World Bank Categories'!$B$4:$C$220,2,FALSE) -> Middle income | J52: benjaminvincent76@gmail.com | K52: Pre-Conference + Main Congress | L52: June 29, June 30, July 1, July 2, July 3, July 4 | P52: Agree | Q52: 등록 | S52: Vincent Benjamin Terfa
A53: 45893.857 | B53: NTAGWABIRA Ange Bernice Shekinnah | D53: Female | E53: 36839 | F53: Rwanda | G53: RCMDO | H53: Active member | I53: =VLOOKUP(CLEAN(F53),'World Bank Categories'!$B$4:$C$220,2,FALSE) -> Low income | J53: angesheky77@gmail.com | K53: Pre-Conference + Main Congress | L53: June 29, June 30, July 1, July 2, July 3, July 4 | P53: Agree | Q53: 미등록
A54: 45893.877 | B54: Ada Mola | D54: Female | E54: 37908 | F54: Rwanda | G54: University of Global Health Equity | H54: Medical Student year 4 | I54: =VLOOKUP(CLEAN(F54),'World Bank Categories'!$B$4:$C$220,2,FALSE) -> Low income | J54: ada.mola@student.ughe.org | K54: Student Conference + Main Congress | L54: June 29, June 30, July 1, July 2, July 3, July 4 | P54: Agree | Q54: 등록 | S54: Ada Mola | T54: 37908 | U54: ada.mola@student.ughe.org | V54: 생년월일 일치, 이메일 일치, 이름 완전일치
A55: 45893.889 | B55: DUKUZIMANA Joseph | D55: Male | E55: 36281 | F55: Rwanda | G55: Nyamata L2TH | H55: Dental Surgeon | I55: =VLOOKUP(CLEAN(F55),'World Bank Categories'!$B$4:$C$220,2,FALSE) -> Low income | J55: dukuzimanajoseph@gmail.com | K55: Pre-Conference + Main Congress | L55: June 29, June 30, July 1, July 2, July 3, July 4 | P55: Agree | Q55: 미등록
A56: 45893.92 | B56: Atem Paul | D56: Male | E56: 21091 | F56: Cameroon | G56: Mount Zion Clinic, Bamenda, Cameroon | H56: Dr. | I56: =VLOOKUP(CLEAN(F56),'World Bank Categories'!$B$4:$C$220,2,FALSE) -> Middle income | J56: dratempaul2015@gmail.com | K56: Pre-Conference + Main Congress | L56: 46202 | M56: Yes. One. My wife. | P56: Agree | Q56: 등록 | S56: Paul Atem | T56: 21091 | U56: dratempaul2015@gmail.com | V56: 생년월일 일치, 이메일 일치, 이름 유사도 100, 이름 토큰 포함
A57: 45894.45 | B57: Willyanna Ravanielly Oliveira de Carvalho | D57: Female | E57: 36283 | F57: Brazil | G57: MDC Brazil | H57: Young Doctor | I57: =VLOOKUP(CLEAN(F57),'World Bank Categories'!$B$4:$C$220,2,FALSE) -> Middle income | J57: willyanna634@gmail.com | K57: Main Congress Only | L57: June 29, June 30, July 1, July 2, July 3, July 4 | P57: Agree | Q57: 등록 | S57: Willyanna Ravanielly Oliveira de Carvalho | T57: 36283 | U57: willyanna634@gmail.com | V57: 생년월일 일치, 이메일 일치, 이름 완전일치
A58: 45895.305 | B58: Semby, Johan Kyung Hwa | D58: Male | E58: 24127 | F58: Sweden | G58: Linköping University/Linköping University Hospital Department of Opthalmology/ ICMDA Sweden | H58: Senior Consultant in Ophthalmology/ Leader, organizer for the delegation from ICMDA Sweden and Finland | I58: =VLOOKUP(CLEAN(F58),'World Bank Categories'!$B$4:$C$220,2,FALSE) -> High income | J58: johan.semby@gmail.com | K58: Pre-Conference + Main Congress | L58: June 29, June 30, July 1, July 2, July 3, July 4 | M58: 1, Joshua Semby, male, son, joshua.semby7@gmail.com | N58: Joshua Semby [아들] | O58: 2명/ (자녀 1명) | P58: Agree | Q58: 등록 | R58: paid | S58: Johan Kyung Hwa Semby | T58: 24492 | U58: johan.semby@gmail.com | V58: 이메일 일치, 이름 유사도 100, 이름 토큰 포함
A59: 45897.565 | B59: Edna Ezra Umaru | D59: Female | E59: 38276 | F59: Nigeria | G59: Gombe state university Nigeria | H59: Class Academic secretary | I59: =VLOOKUP(CLEAN(F59),'World Bank Categories'!$B$4:$C$220,2,FALSE) -> Middle income | J59: ednaumaru044@gmail.com | K59: Student Conference + Main Congress | L59: June 29, June 30, July 1, July 2, July 3, July 4 | P59: Agree | Q59: 미등록
A60: 45900.026 | B60: NURGUL MAMYROVA | D60: Female | E60: 29297 | F60: Kyrgyz Republic | G60: ICMDA | H60: Doctor | I60: =VLOOKUP(CLEAN(F60),'World Bank Categories'!$B$4:$C$220,2,FALSE) -> Middle income | J60: nurgulicmda@gmail.com | K60: Student Conference + Main Congress | L60: June 29, June 30, July 1, July 2, July 3, July 4 | M60: Yes: Simon Peter Nadeem-my husband, My Daughter-Shulmiyat Sarah Nadeem, and my son -Timothy Simon Nadeem) | N60: Simon Peter Nadeem [배우자(남편)] Shulmiyat Sarah Nadeem[딸, 18세] Timothy Simon Nadeem [아들, 13세] | O60: 4명/ (자녀 2명, 배우자 1명) | P60: Agree | Q60: 등록 | R60: paid | S60: Nurgul Mamyrova | T60: 29297 | U60: nurgulicmda@gmail.com | V60: 생년월일 일치, 이메일 일치, 이름 완전일치
A61: 45908.027 | B61: Tubasiime Ronald | D61: Male | E61: 29582 | F61: Rwanda | G61: Kibogora Hospital | H61: General surgeon | I61: =VLOOKUP(CLEAN(F61),'World Bank Categories'!$B$4:$C$220,2,FALSE) -> Low income | J61: turona20@gmail.com | K61: Pre-Conference + Main Congress | L61: June 29, June 30, July 1, July 2, July 3, July 4 | P61: Agree | Q61: 등록 | S61: Ronald Tubasiime | T61: 29582 | U61: turona20@gmail.com | V61: 생년월일 일치, 이메일 일치, 이름 유사도 100, 이름 토큰 포함
A62: 45908.782 | B62: Diana | C62: Safina | D62: Female | E62: 30253 | F62: Russian Federation | G62: ICMDA | H62: Regional representative, Eurasia training administrator | I62: =VLOOKUP(CLEAN(F62),'World Bank Categories'!$B$4:$C$220,2,FALSE) -> High income | J62: diana.safina316@gmail.com | K62: Pre-Conference + Main Congress | L62: June 29, June 30, July 1, July 2, July 3, July 4 | M62: Daria Safina, female, daughter 13 years old | N62: Daria Safina [딸, 13세] | O62: 2명/ (자녀 1명) | P62: Agree | Q62: 등록 | R62: bursary | S62: Diana Safina | T62: 30253 | U62: diana.safina316@gmail.com | V62: 생년월일 일치, 이메일 일치, 이름 유사도 100
A63: 45909.158 | B63: Grishanovich Elisei | D63: Male | E63: 37263 | F63: Russian Federation | G63: Kirov Smu | H63: Student | I63: =VLOOKUP(CLEAN(F63),'World Bank Categories'!$B$4:$C$220,2,FALSE) -> High income | J63: elishagch@gmail.com | K63: Student Conference + Main Congress | L63: June 29, June 30, July 1, July 2, July 3, July 4 | P63: Agree | Q63: 등록 | S63: ELISEI GRISHANOVICH | T63: 37263 | U63: elishagch@gmail.com | V63: 생년월일 일치, 이메일 일치, 이름 유사도 100, 이름 토큰 포함
A64: 45909.696 | B64: BENJAMIN DUBE | D64: Male | E64: 35302 | F64: ZIMBABWE | G64: NATIONAL UNIVERSITY OF SCIENCE AND TECHNOLOGY, ZIMBABWE | H64: Chairperson, NUST Christian Medical Fellowship (CMF) | I64: =VLOOKUP(CLEAN(F64),'World Bank Categories'!$B$4:$C$220,2,FALSE) -> Middle income | J64: benjiedube25@gmail.com | K64: Student Conference + Main Congress | L64: June 29, June 30, July 1, July 2, July 3, July 4 | P64: Agree | Q64: 등록 | R64: bursary | S64: DUBE BENJAMIN | T64: 35302 | U64: benjiedube25@gmail.com | V64: 생년월일 일치, 이메일 일치, 이름 유사도 100, 이름 토큰 포함
A65: 45916.786 | B65: Budiani Christina Natalia | D65: Female | E65: 30307 | F65: Indonesia | G65: Bethesda Serukam Mission Hospital, West Borneo, Indonesia | H65: Anesthesiologist | I65: =VLOOKUP(CLEAN(F65),'World Bank Categories'!$B$4:$C$220,2,FALSE) -> Middle income | J65: b.christina07@gmail.com | K65: Main Congress Only | L65: July 1, July 2, July 3, July 4 | P65: Agree | Q65: 등록 | S65: Budiani Christina Natalia | T65: 30307 | U65: b.christina07@gmail.com | V65: 생년월일 일치, 이메일 일치, 이름 완전일치
A66: 45918.29 | B66: Peter Fee | D66: Male | E66: 28989 | F66: United Kingdom | G66: Royal Belfast Children's Hospital, Belfast, UK | H66: Consultant Anaesthetist | I66: =VLOOKUP(CLEAN(F66),'World Bank Categories'!$B$4:$C$220,2,FALSE) -> High income | J66: peterfee@doctors.org.uk | K66: Pre-Conference + Main Congress | L66: June 29, June 30, July 1, July 2, July 3, July 4 | M66: 4: Kerry Fee, female, wife, thefees@me.com; Grace Fee, female, daughter; Joel Fee, male, son; Toby Fee, male, son. | N66: Kerry Fee [배우자(아내)] thefees@me.com Grace Fee [딸, 12세] Joel Fee [아들, 14세] Toby Fee [아들, 10세] | O66: 5명/ (자녀 3명, 배우자 1명) | P66: Agree | Q66: 등록 | R66: paid | S66: Peter Fee | T66: 28989 | U66: peterfee@doctors.org.uk | V66: 생년월일 일치, 이메일 일치, 이름 완전일치
A67: 45918.575 | B67: Nakanjako | C67: Sharon | D67: Female | E67: 34006 | F67: Uganda | G67: Uganda Christian medical Fellowship | H67: Clinical psychologist | I67: =VLOOKUP(CLEAN(F68),'World Bank Categories'!$B$4:$C$220,2,FALSE) -> Middle income | J67: sharonnakanjako2023@gmail.com | K67: Pre-Conference + Main Congress | L67: June 29, June 30, July 1, July 2, July 3, July 4 | P67: Agree | Q67: 등록 | R67: bursary | S67: Sharon Nakanjako | T67: 34006 | U67: sharonnakanjako2023@gmail.com | V67: 생년월일 일치, 이메일 일치, 이름 유사도 100
A68: 45921.897 | B68: GERISI JOSEPH GERGES SHENODA ISSA | D68: Female | E68: 36404 | F68: Egypt, Arab Rep. | G68: CMF Egypt | H68: Dentist (GP) | J68: gracejoseph771999@gmail.com | K68: Pre-Conference + Main Congress | L68: June 29, June 30, July 1, July 2, July 3, July 4 | M68: 1, Jena Issa, female, sister, jena.joseph@ngu.edu.eg | P68: Agree | Q68: 등록 | S68: Gerisi Joseph Gerges Shenoda Issa
A69: 45922.815 | B69: Greta Gamal Nazir Kross | D69: Female | E69: 30328 | F69: Egypt, Arab Rep. | G69: Cmf egypt | H69: Pediatric specialist (director of operations of cmf egypt) | I69: =VLOOKUP(CLEAN(F69),'World Bank Categories'!$B$4:$C$220,2,FALSE) -> Middle income | J69: gretagamal@hotmail.com | K69: Pre-Conference + Main Congress | L69: June 29, June 30, July 1, July 2, July 3, July 4 | M69: George robile,male,husband Jason george,male ,son Jenny george,female,daughter | N69: George robile [배우자(남편)] gretagamal@hotmail.com Jason george [아들, 13세] Jenny george [딸, 17세] | O69: 4명/ (자녀 2명, 배우자 1명) | P69: Agree | Q69: 등록 | R69: bursary | S69: Greta Gamal
A70: 45923.699 | B70: Meilani | D70: Female | E70: 30073 | F70: Indonesia | G70: CMDF Indonesia | H70: Mrs/Coordinator of Mission Department | I70: =VLOOKUP(CLEAN(F70),'World Bank Categories'!$B$4:$C$220,2,FALSE) -> Middle income | J70: mariameilani1@gmail.com | K70: Pre-Conference + Main Congress | L70: June 29, June 30, July 1, July 2, July 3, July 4 | M70: 2. Tigor Yeheskiel, male, husband. Matthew Jordan Simanjuntak, male, son. | N70: Tigor Yeheskiel [배우자(남편)] Matthew Jordan Simanjuntak [아들, 7세] | O70: 3명/ (자녀 1명, 배우자 1명) | P70: Agree | Q70: 등록 | S70: Meilani | T70: 30073 | U70: mariameilani1@gmail.com | V70: 생년월일 일치, 이메일 일치, 이름 완전일치
A71: 45924.787 | B71: Pola Ayman Wadea Zaki | D71: Male | E71: 37309 | F71: Egypt, Arab Rep. | G71: Faculty of medicine minia university | H71: Medical student | I71: =VLOOKUP(CLEAN(F71),'World Bank Categories'!$B$4:$C$220,2,FALSE) -> Middle income | J71: polaayman333@gmail.com | K71: Pre-Conference + Main Congress | L71: June 29, June 30, July 1, July 2, July 3, July 4 | P71: Agree | Q71: 등록 | S71: Pola ayman wadea zaki | T71: 37309 | U71: polaayman333@gmail.com | V71: 생년월일 일치, 이메일 일치, 이름 완전일치
A72: 45925.89 | B72: Ebram Adel Karem | D72: Male | E72: 45927 | F72: Egypt, Arab Rep. | G72: Faculty of Medicine-Minia university | H72: Medical student | I72: =VLOOKUP(CLEAN(F72),'World Bank Categories'!$B$4:$C$220,2,FALSE) -> Middle income | J72: ebramadel264@gmail.com | K72: Pre-Conference + Main Congress | L72: June 29, June 30, July 1, July 2, July 3, July 4 | P72: Agree | Q72: 등록 | S72: Ebram Adel Karem | T72: 37372 | U72: ebramadel264@gmail.com | V72: 이메일 일치, 이름 완전일치
A73: 45926.518 | B73: Zawadi Virgily John | D73: Female | E73: 34121 | F73: Tanzania | G73: Mawenzi Refferal Regional Hospital | H73: Laboratory Scientist | I73: =VLOOKUP(CLEAN(F73),'World Bank Categories'!$B$4:$C$220,2,FALSE) -> Middle income | J73: zawadijohn103@gmail.com | K73: Pre-Conference + Main Congress | L73: June 29, June 30, July 1, July 2, July 3, July 4 | P73: Agree | Q73: 등록 | S73: Zawadi John | T73: 34121 | U73: zawadijohn103@gmail.com | V73: 생년월일 일치, 이메일 일치, 이름 유사도 100, 이름 토큰 포함
A74: 45927.529 | B74: KASONGO MWENYI MAXIME | D74: Male | E74: 26111 | F74: Congo, Dem.Rep. | G74: Centre de santé pilote et maternité de Masina/Kinshasa | H74: Chef de service ophtalmologie | I74: =VLOOKUP(CLEAN(F74),'World Bank Categories'!$B$4:$C$220,2,FALSE) -> Low income | J74: maxkasongo@gmail.com | K74: Main Congress Only | L74: June 29, June 30, July 1, July 2, July 3, July 4 | P74: Agree | Q74: 미등록
A75: 45927.904 | B75: Christa Adeline | D75: Female | E75: 35457 | F75: Indonesia | G75: ICMDA | H75: Regional Representative for Southeast Asia | I75: =VLOOKUP(CLEAN(F75),'World Bank Categories'!$B$4:$C$220,2,FALSE) -> Middle income | J75: christa.adeline@icmda.net | K75: Pre-Conference + Main Congress | L75: June 30, July 1, July 2, July 3, July 4 | P75: Agree | Q75: 등록 | R75: paid | S75: Christa Adeline | T75: 35457 | U75: christa.adeline@icmda.net | V75: 생년월일 일치, 이메일 일치, 이름 완전일치
A76: 45927.984 | B76: Quacy Asheeke Grant | D76: Male | E76: 31257 | F76: Guyana | G76: Lausanne Movement Caribbean/ICMDA Guyana-Caribbean | H76: Regional Director (Lausanne Movement Caribbean) | I76: =VLOOKUP(CLEAN(F76),'World Bank Categories'!$B$4:$C$220,2,FALSE) -> High income | J76: qgrant@lausanne.org | K76: Main Congress Only | L76: June 29, June 30, July 1, July 2, July 3, July 4 | P76: Agree | Q76: 등록 | R76: bursary | S76: Quacy Asheeke Grant
A77: 45928.771 | B77: LOUIE BENJAMIN KWON BOU | D77: Male | E77: 38475 | F77: NEW ZEALAND | G77: University of Otago | H77: Medical Student | I77: =VLOOKUP(CLEAN(F77),'World Bank Categories'!$B$4:$C$220,2,FALSE) -> High income | J77: bklouie@outlook.com | K77: Pre-Conference + Main Congress | L77: June 29, June 30, July 1, July 2, July 3 | M77: 1, Yidao Chua, male, friend, yidaochua@gmail.com | P77: Agree | Q77: 등록 | R77: paid | S77: Benjamin Louie | T77: 38475 | U77: bklouie@outlook.com | V77: 생년월일 일치, 이메일 일치, 이름 유사도 100, 이름 토큰 포함
A78: 45929.067 | B78: Mohalenyane Matheko Mary | D78: Female | E78: 35435 | F78: Lesotho | G78: Senkatana Oncology Clinic | H78: Dr. | I78: =VLOOKUP(CLEAN(F78),'World Bank Categories'!$B$4:$C$220,2,FALSE) -> Middle income | J78: matheko.mohalenyane@gmail.com | K78: Pre-Conference + Main Congress | L78: June 29, June 30, July 1, July 2, July 3, July 4 | P78: Agree | Q78: 등록 | R78: bursary | S78: Matheko Mohalenyane | T78: 35435 | U78: matheko.mohalenyane@yahoo.com | V78: 생년월일 일치, 이름 유사도 100, 이름 토큰 포함
A79: 45929.923 | B79: Sousa Lucas Cavilane | D79: Male | E79: 36423 | F79: Mozambique | G79: Associação Light for Health | H79: 2 Vogal do Conselho Nacional | I79: =VLOOKUP(CLEAN(F79),'World Bank Categories'!$B$4:$C$220,2,FALSE) -> Low income | J79: Sousacavilane@gmail.com | K79: Pre-Conference + Main Congress | L79: June 29, June 30, July 1, July 2, July 3, July 4 | P79: Agree | Q79: 등록 | S79: Sousa Lucas Cavilane | T79: 36423 | U79: sousacavilane@gmail.com | V79: 생년월일 일치, 이메일 일치, 이름 완전일치
A80: 45930.242 | B80: AKELLO GLORIA | D80: Female | E80: 36388 | F80: Uganda | G80: Makerere University | H80: Student | I80: =VLOOKUP(CLEAN(F80),'World Bank Categories'!$B$4:$C$220,2,FALSE) -> Low income | J80: gloakello@gmail.com | K80: Pre-Conference + Main Congress | L80: June 29, June 30, July 1, July 2, July 3, July 4 | P80: Agree | Q80: 등록 | S80: Akello Gloria
A81: 45930.648 | B81: Anitha David | D81: Female | E81: 25119 | F81: India | G81: Emmanuel Hospital Association | H81: Dentist | I81: =VLOOKUP(CLEAN(F81),'World Bank Categories'!$B$4:$C$220,2,FALSE) -> Middle income | J81: Anitha.David@icmda.net | K81: Pre-Conference + Main Congress | L81: June 29, June 30, July 1, July 2, July 3, July 4 | P81: Agree | Q81: 등록 | R81: bursary | S81: Anitha David | T81: 25119 | U81: Anitha.David@imcda.net
A82: 45930.815 | B82: Rumala Premika Morel | D82: Female | E82: 23997 | F82: Sri Lanka | G82: Healthcare Christian Fellowship of Lanka | H82: Student Ministry Coordinator | I82: =VLOOKUP(CLEAN(F82),'World Bank Categories'!$B$4:$C$220,2,FALSE) -> Middle income | J82: rumala.morel@gmail.com | K82: Main Congress Only | L82: June 29, June 30, July 1, July 2, July 3, July 4 | P82: Agree | Q82: 등록 | S82: Rumala Morel
A83: 45930.815 | B83: Egba Honour Joseph | D83: Male | E83: 37516 | F83: Nigeria | G83: University of Calabar, Calabar, Nigeria. | H83: School general secretary | I83: =VLOOKUP(CLEAN(F83),'World Bank Categories'!$B$4:$C$220,2,FALSE) -> Middle income | J83: honouregba9@gmail.com | K83: Pre-Conference + Main Congress | L83: June 29, June 30, July 1, July 2, July 3, July 4 | P83: Agree | Q83: 미등록
A84: 45932.036 | B84: Abiyu Tadesse Fulea | C84: Kim | D84: Male | E84: 31339 | F84: Ethiopia | G84: CMF Ethiopia | H84: CMF Ethiopia chairperson | I84: =VLOOKUP(CLEAN(F84),'World Bank Categories'!$B$4:$C$220,2,FALSE) -> Low income | J84: martabiyju@gmail.com | K84: Pre-Conference + Main Congress | L84: June 29, June 30, July 1, July 2, July 3, July 4 | P84: Agree | Q84: 등록 | R84: bursary | S84: Abiyu Tadesse Fulea | T84: 31339 | U84: martabiyju@gmail.com | V84: 생년월일 일치, 이메일 일치, 이름 완전일치
A85: 45933.041 | B85: Inayat Sunny | D85: Male | E85: 29853 | F85: Pakistan | G85: Glorious Church of Christ | H85: Pastor | I85: =VLOOKUP(CLEAN(F85),'World Bank Categories'!$B$4:$C$220,2,FALSE) -> Middle income | J85: sunny_inayat@yahoo.com | K85: Pre-Conference + Main Congress | L85: June 29, June 30, July 1, July 2, July 3, July 4 | M85: Sunny John, Male, Son | N85: Sunny John [아들] | O85: 2명/ (자녀 1명) | P85: Agree | Q85: 미등록
A86: 45933.58 | B86: Michelle Eugenia | D86: Female | E86: 36608 | F86: Indonesia | G86: CMDA Indonesia | H86: Member | I86: =VLOOKUP(CLEAN(F86),'World Bank Categories'!$B$4:$C$220,2,FALSE) -> Middle income | J86: michelle.eugenia23@gmail.com | K86: Pre-Conference + Main Congress | L86: June 29, June 30, July 1, July 2, July 3, July 4 | P86: Agree | Q86: 등록 | S86: Michelle Eugenia | T86: 36608 | U86: michelle.eugenia23@gmail.com | V86: 생년월일 일치, 이메일 일치, 이름 완전일치
A87: 45933.674 | B87: Kezia Christina Viani Wijaya | C87: 케지아 크리스티나 비아니 위자야 | D87: Female | E87: 36659 | F87: Indonesia | G87: CMDA Indonesia | H87: Member | I87: =VLOOKUP(CLEAN(F87),'World Bank Categories'!$B$4:$C$220,2,FALSE) -> Middle income | J87: keziawij@gmail.com | K87: Main Congress Only | L87: July 1, July 2, July 3, July 4 | P87: Agree | Q87: 등록 | R87: bursary | S87: Kezia Christina Viani Wijaya | T87: 36659 | U87: keziawij@gmail.com | V87: 생년월일 일치, 이메일 일치, 이름 완전일치
A88: 45936.843 | B88: ASINGYA RONALD MUMBERE | D88: Male | E88: 36383 | F88: Uganda | G88: Kampala international university | H88: Student | I88: =VLOOKUP(CLEAN(F88),'World Bank Categories'!$B$4:$C$220,2,FALSE) -> Low income | J88: asingyaronald256256@gmail.com | K88: Pre-Conference + Main Congress | L88: June 29, June 30, July 1, July 2, July 3, July 4 | P88: Agree | Q88: 등록 | S88: Asingya Ronald Mumbere | T88: 36414 | U88: asingyaronald256256@gmail.com | V88: 이메일 일치, 이름 완전일치
A89: 45936.945 | B89: OCEN JUDE OKELLO | D89: Male | E89: 37238 | F89: Uganda | G89: Gulu University | H89: Student | I89: =VLOOKUP(CLEAN(F89),'World Bank Categories'!$B$4:$C$220,2,FALSE) -> Low income | J89: ocenjudeokello@gmail.com | K89: Pre-Conference + Main Congress | L89: June 29, June 30, July 1, July 2, July 3, July 4 | P89: Agree | Q89: 등록 | S89: Ocen Jude Okello | T89: 37238 | U89: ocenjudeokello@gmail.com | V89: 생년월일 일치, 이메일 일치, 이름 완전일치
A90: 45937.12 | B90: AGENORWOT FAITH | D90: Female | E90: 37321 | F90: Uganda | G90: GULU UNIVERSITY | H90: Miss | I90: =VLOOKUP(CLEAN(F90),'World Bank Categories'!$B$4:$C$220,2,FALSE) -> Low income | J90: faithagenorwot63@gmail.com | K90: Pre-Conference + Main Congress | L90: June 29, June 30, July 1, July 2, July 3, July 4 | P90: Agree | Q90: 등록 | S90: AGENORWOT FAITH | T90: 37321 | U90: faithagenorwot63@gmail.com | V90: 생년월일 일치, 이메일 일치
A91: 45940.734 | B91: MOGES ZENEBE WEGAYEHU | D91: Male | E91: 30764 | F91: Ethiopia | G91: ADDIS ABABA UNIVERSITY, COLLEGE OF HEALTH SCIENCE | H91: Doctor, Assistant professor of Radiology | I91: =VLOOKUP(CLEAN(F91),'World Bank Categories'!$B$4:$C$220,2,FALSE) -> Low income | J91: zenebemoges@gmail.com | K91: Pre-Conference + Main Congress | L91: June 29, June 30, July 1, July 2, July 3, July 4 | P91: Agree | Q91: 등록 | S91: MOGES ZENEBE WEGAYEHU | T91: 30764 | U91: zenebemoges@gmail.com | V91: 생년월일 일치, 이메일 일치, 이름 완전일치
A92: 45942.883 | B92: OP 1067008 | C92: LUANDA MUBYALE LUTYATSO Justin | D92: Male | E92: 28912 | F92: Congo,Rep. | G92: AMC Congo Kinshasa | H92: Member | I92: =VLOOKUP(CLEAN(F92),'World Bank Categories'!$B$4:$C$220,2,FALSE) -> Middle income | J92: mluand2013@gmail.com | K92: Pre-Conference + Main Congress | L92: June 29, June 30, July 1, July 2, July 3, July 4 | M92: NSIMIRE BITWENGE Reine: Female, my spouse | P92: Agree | Q92: 미등록
A93: 45943.156 | B93: Enimil Anthony Kwame | D93: Male | E93: 26224 | F93: Ghana | G93: Kwame Nkrumah University of Science and Technology | H93: Professor/Lecturer | I93: =VLOOKUP(CLEAN(F93),'World Bank Categories'!$B$4:$C$220,2,FALSE) -> Middle income | J93: Tonash@gmail.com | K93: Pre-Conference + Main Congress | L93: June 29, June 30, July 1, July 2, July 3, July 4 | M93: Helena Enimil, Female , Spouse | P93: Agree | Q93: 등록 | R93: Paid | S93: Anthony Enimil | T93: 26224 | U93: tonash@gmail.com | V93: 생년월일 일치, 이메일 일치, 이름 유사도 100, 이름 토큰 포함
A94: 45945.978 | B94: ARINDA ANITAH | D94: Female | E94: 37213 | F94: Uganda | G94: Kampala International University Uganda | H94: Student | I94: =VLOOKUP(CLEAN(F94),'World Bank Categories'!$B$4:$C$220,2,FALSE) -> Low income | J94: anitaharinda2001@gmail.com | K94: Pre-Conference + Main Congress | L94: June 29, June 30, July 1, July 2, July 3, July 4 | P94: Agree | Q94: 등록 | S94: ARINDA ANITAH | T94: 37213 | U94: anitaharinda2001@gmail.com | V94: 생년월일 일치, 이메일 일치, 이름 완전일치
A95: 45946.597 | B95: Alina Istrati | D95: Female | E95: 37372 | F95: Romania | G95: Nicolae Testemiţanu Moldova State University of Medicine and Pharmacy | H95: Student | I95: =VLOOKUP(CLEAN(F95),'World Bank Categories'!$B$4:$C$220,2,FALSE) -> High income | J95: istratialina16@gmail.com | K95: Pre-Conference + Main Congress | L95: June 29, June 30, July 1, July 2, July 3, July 4 | P95: Agree | Q95: 등록 | R95: bursary | S95: Istrati Alina | T95: 37372 | U95: istratialina16@gmail.com | V95: 생년월일 일치, 이메일 일치, 이름 유사도 100, 이름 토큰 포함
A96: 45946.731 | B96: Bwizabwimana Lys Mika | D96: Female | E96: 37052 | F96: Burundi | G96: Hope Africa University | H96: Student | I96: =VLOOKUP(CLEAN(F96),'World Bank Categories'!$B$4:$C$220,2,FALSE) -> Low income | J96: lysmika@1gmail.com | K96: Pre-Conference + Main Congress | L96: June 29, June 30, July 1, July 2, July 3, July 4 | P96: Agree | Q96: 등록 | S96: BWIZABWIMANA Lys Mika | T96: 37052 | U96: lysmika1@gmail.com | V96: 생년월일 일치, 이름 완전일치
A97: 45946.975 | B97: Amigo Jordy Ishimwe | D97: Male | E97: 36184 | F97: Burundi | G97: BCMDA (Burundi Christian Medical and dental association) | H97: Student Leadership | I97: =VLOOKUP(CLEAN(F97),'World Bank Categories'!$B$4:$C$220,2,FALSE) -> Low income | J97: amigojordyi@gmail.com | K97: Pre-Conference + Main Congress | L97: June 29, June 30, July 1, July 2, July 3, July 4 | P97: Agree | Q97: 등록 | S97: Amigo Jordy Ishimwe | T97: 36184 | U97: amigojordyi@gmail.com | V97: 생년월일 일치, 이메일 일치, 이름 완전일치
A98: 45947.179 | B98: HERVE TISTOU HITIMANA | D98: Male | E98: 33297 | F98: Burundi | G98: BCMDA | H98: Dr | I98: =VLOOKUP(CLEAN(F98),'World Bank Categories'!$B$4:$C$220,2,FALSE) -> Low income | J98: h.tistou@gmail.com | K98: Pre-Conference + Main Congress | L98: June 29, June 30, July 1, July 2, July 3, July 4 | P98: Agree | Q98: 등록 | R98: bursary | S98: HERVE TISTOU HITIMANA | T98: 33297 | U98: h.tistou@gmail.com | V98: 생년월일 일치, 이메일 일치, 이름 완전일치
A99: 45947.18 | B99: DUSHIME GLADYS | D99: Female | E99: 33702 | F99: Burundi | G99: BCMDA | H99: During Psychiatry specialization | I99: =VLOOKUP(CLEAN(F99),'World Bank Categories'!$B$4:$C$220,2,FALSE) -> Low income | J99: simpledugla1@gmail.com | K99: Pre-Conference + Main Congress | L99: June 29, June 30, July 1, July 2, July 3, July 4 | P99: Agree | Q99: 등록 | S99: Gladys Dushime | T99: 33702 | U99: simpledugla1@gmail.com | V99: 생년월일 일치, 이메일 일치, 이름 유사도 100, 이름 토큰 포함
A100: 45947.313 | B100: OKONGO BERFINA | D100: Female | E100: 36417 | F100: Senegal | G100: Association des médecins et dentistes chrétiens du Sénégal | H100: Treasury | I100: =VLOOKUP(CLEAN(F100),'World Bank Categories'!$B$4:$C$220,2,FALSE) -> Middle income | J100: O.berfina1@gmail.com | K100: Pre-Conference + Main Congress | L100: June 29, June 30, July 1, July 2, July 3, July 4 | P100: Agree | Q100: 등록 | R100: bursary | S100: OKONGO Berfina | T100: 36417 | U100: O.berfina1@gmail.com | V100: 생년월일 일치, 이메일 일치, 이름 완전일치
A101: 45947.313 | B101: ADONONSI FEGNITI MAHUTON MARIELLE | D101: Female | E101: 37086 | F101: Benin | G101: Association des Médecins et Dentistes Chrétiens du Sénégal | H101: Student leader | I101: =VLOOKUP(CLEAN(F101),'World Bank Categories'!$B$4:$C$220,2,FALSE) -> Middle income | J101: mariellehy@gmail.com | K101: Pre-Conference + Main Congress | L101: June 29, June 30, July 1, July 2, July 3, July 4 | P101: Agree | Q101: 등록 | R101: bursary | S101: Marielle Adononsi | T101: 37086 | U101: mariellehy@gmail.com | V101: 생년월일 일치, 이메일 일치, 이름 유사도 100, 이름 토큰 포함
A102: 45947.313 | B102: Rebecca Biaye | D102: Female | E102: 33994 | F102: Senegal | G102: Association des médecins et dentistes chrétiens du Sénégal | H102: National president | I102: =VLOOKUP(CLEAN(F102),'World Bank Categories'!$B$4:$C$220,2,FALSE) -> Middle income | J102: rebiaye@gmail.com | K102: Pre-Conference + Main Congress | L102: June 29, June 30, July 1, July 2, July 3, July 4 | P102: Agree | Q102: 등록 | R102: bursary | S102: Rebecca Biaye | T102: 33994 | U102: rebiaye@gmail.com | V102: 생년월일 일치, 이메일 일치, 이름 완전일치
...

Sheet 무료숙소확정전체명단
A2: =COUNTA(B5:B14647) -> 576 | B2: 자원봉사자, 지원팀, 중국팀 등은 포함 안 된 인원 | C2: Godsends 등록자 수 | D2: =COUNTIF(Q5:Q711,"등록") -> 576 | F2: Godsends 미등록자 수 | G2: =COUNTIF(Q5:Q2647,"미등록") -> 0 | I2: paid 완료 | J2: =COUNTA(R5:R14647) -> 576
A4: Timestamp | B4: 1. Name As it appears on your passport | C4: 2. Name (Korean): | D4: 3. Gender: | E4: 4. Date of Birth: (MM-DD-YYYY) | F4: 5. Nationality As it appears on your passport | G4: 6. Affiliation School/Institution/Organization Name | H4: 7. Title/Position | I4: 8. World Bank Category Found on your Registration Tab | J4: 9. Email Address Must be the same email used for registration | K4: 10. ICMDA Event You Plan to Attend | L4: 11. Free Accommodation Request Dates | M4: 12. Accompanying Family Member(s)(Name/Gender/Relationship): Are you bringing family member(s)? If yes, please indicate how many will accompany you and provide their name, gender, and relationship (ex: 1, John Doe, male, husband, John_D@gmail.com) | N4: 동반자 전체 요악 | O4: 본인 포함 총 인원(가족 단위 경우만) | P4: 13. Consent for Personal Information Use I hereby consent to the collection and use of the personal information provided above for the purpose of evaluating my application for ICMDA free accommodation and for related communications. | Q4: 등록판정 | R4: Paid | S4: 매칭된 godsends 이름 | T4: 매칭된 godsends 생년월일 | U4: 매칭된 godsends 이메일 | V4: 판정 근거 | W4: Column 1
A5: 45841.453 | B5: Elisa Mabel Galeano Gamarra | D5: Female | E5: 35614 | F5: Paraguay | G5: in the process of having an association in Paraguay | H5: doctor | I5: =VLOOKUP(CLEAN(F5),'World Bank Categories'!$B$4:$C$220,2,FALSE) -> Middle income | J5: elisamedoficial@gmail.com | K5: Pre-Conference + Main Congress | L5: June 29, June 30, July 1, July 2, July 3, July 4 | P5: Agree | Q5: 등록 | R5: bursary | S5: Elisa Mabel Galeano Gamarra
A6: 45843.795 | B6: NZAME Yolande | D6: Female | E6: 21016 | F6: Gabon | G6: Gabon Medical Chrétien | H6: Membre | I6: =VLOOKUP(CLEAN(F6),'World Bank Categories'!$B$4:$C$220,2,FALSE) -> Middle income | J6: yolandenzame@gmail.com | K6: Main Congress Only | L6: June 29, June 30, July 1, July 2, July 3, July 4 | M6: Rebecca, féminin, fille, vierin.rebecca@hotmail.fr | N6: Rebecca [딸] | O6: 2명/ (자녀 1명) | P6: Agree | Q6: 등록 | R6: paid | S6: NZAME Yolande
A7: 45853.25 | B7: Blessings Dendere | D7: Female | E7: 36458 | F7: Zimbabwe | G7: Christian Medical Fellowship | H7: Doctor | I7: =VLOOKUP(CLEAN(F7),'World Bank Categories'!$B$4:$C$220,2,FALSE) -> Middle income | J7: blessingszd@gmail.com | K7: Pre-Conference + Main Congress | L7: June 29, June 30, July 1, July 2, July 3, July 4 | P7: Agree | Q7: 등록 | R7: bursary | S7: Blessings Dendere
A8: 45859.287 | B8: Muhumuza Ndamage Stephen | C8: Not Korean | D8: Male | E8: 29178 | F8: Rwanda | G8: Rwanda Christian Medical and Dental Organization | H8: Head of Rwanda Christian Medical and a Dental Organization | I8: =VLOOKUP(CLEAN(F8),'World Bank Categories'!$B$4:$C$220,2,FALSE) -> Low income | J8: stephen20130@gmail.com | K8: Student Conference + Main Congress | L8: 46207 | P8: Agree | Q8: 등록 | R8: bursary | S8: Muhumuza Ndamage Stephen | T8: 29178 | U8: stephen20130@gmail.com | V8: 생년월일 일치, 이메일 일치, 이름 완전일치
A9: 45865.165 | B9: KILACH CAROLE JESANG | D9: Female | E9: 32229 | F9: Kenya | G9: CHRISTIAN MEDICAL FELLOWSHIP- KENYA | H9: Dr/Miss/ Regional Leader | I9: =VLOOKUP(CLEAN(F9),'World Bank Categories'!$B$4:$C$220,2,FALSE) -> Middle income | J9: carolejesang@gmail.com | K9: Pre-Conference + Main Congress | L9: June 29, June 30, July 1, July 2, July 3, July 4 | P9: Agree | Q9: 등록 | R9: paid | S9: KILACH CAROLE JESANG | T9: 32229 | U9: carolejesang@gmail.com | V9: 생년월일 일치, 이메일 일치, 이름 완전일치
A10: 45870.142 | B10: Aline Garcia Pereira | C10: Aline Garcia Pereira | D10: Female | E10: 32847 | F10: Brazil | G10: Uniasselvi (University)/ MDC -Medicos de Cristo | H10: I am student of Health Management (graduation). But I am also PHD | I10: =VLOOKUP(CLEAN(F10),'World Bank Categories'!$B$4:$C$220,2,FALSE) -> Middle income | J10: alinegpereira1@gmail.com | K10: Student Conference + Main Congress | L10: June 29, June 30, July 1, July 2, July 3, July 4 | P10: Agree | Q10: 등록 | R10: paid | S10: Aline Garcia Pereira | T10: 32847 | U10: alinegpereira1@gmail.com | V10: 생년월일 일치, 이메일 일치, 이름 완전일치
A11: 45871.236 | B11: PAUL STEPHEN ATARO AYELLA | D11: Male | E11: 28186 | F11: Uganda | G11: ICMDA | H11: REGIONAL REPRESENTATIVE EAST AFRICA | I11: =VLOOKUP(CLEAN(F11),'World Bank Categories'!$B$4:$C$220,2,FALSE) -> Low income | J11: ATARODRPAPA@GMAIL.COM | K11: Student Conference + Main Congress | L11: June 29, June 30, July 1, July 2, July 3, July 4 | M11: ATARO JANE KARINA, FEMALE. ATARO NEEMA ANGIOLETTA, FEMALE DAUGHTERS | N11: ATARO JANE KARINA, FEMALE. ATARO NEEMA ANGIOLETTA, FEMALE DAUGHTERS 딸 2명 | O11: 3명/ (자녀 2명) | P11: Agree | Q11: 등록 | R11: bursary | S11: Paul Stephen Ataro Ayella | T11: 28186 | U11: atarodrpapa@gmail.com | V11: 생년월일 일치, 이메일 일치, 이름 완전일치
A12: 45874.23 | B12: Mugaba Proscovia Mujeere | D12: Female | E12: 28943 | F12: Uganda | G12: Uganda Christian Medical Fellowship (UCMF) | H12: Chairperson of UCMF National Executive Committee | I12: =VLOOKUP(CLEAN(F12),'World Bank Categories'!$B$4:$C$220,2,FALSE) -> Low income | J12: drprosiemm@gmail.com | K12: Main Congress Only | L12: June 30, July 1, July 2, July 3, July 4 | P12: Agree | Q12: 등록 | R12: bursary | S12: Proscovia Mujeere Mugaba
A13: 45875.633 | B13: Theodorus Hedwin Kadrianto | D13: Male | E13: 32327 | F13: Indonesia | G13: ICMDA | H13: AEO for East Asia, Southeast Asia, Oceania | I13: =VLOOKUP(CLEAN(F13),'World Bank Categories'!$B$4:$C$220,2,FALSE) -> Middle income | J13: theodorus.hedwin@icmda.net | K13: Pre-Conference + Main Congress | L13: June 29, June 30, July 1, July 2, July 3, July 4 | P13: Agree | Q13: 등록 | R13: paid | S13: Theodorus Hedwin Kadrianto | T13: 32327 | U13: theodorus.hedwin@icmda.net | V13: 생년월일 일치, 이메일 일치, 이름 완전일치
A14: 45883.567 | B14: PETER SATHIYANATHAN MICHEAL JOHN | D14: Male | E14: 28573 | F14: MALAYSIA | G14: HEALTHCARE CHRISTIAN FELLOWSHIP MALAYSIA | H14: DOCTOR | I14: =VLOOKUP(CLEAN(F14),'World Bank Categories'!$B$4:$C$220,2,FALSE) -> Middle income | J14: doctorpeter@hotmail.com | K14: Main Congress Only | L14: July 1, July 2, July 3, July 4 | M14: IRINE AARATHANA PETER SATHIYANATHAN, FEMALE, - 12 YEARS OLD DAUGHTER , doctorpeter@hotmail.com | N14: IRINE AARATHANA PETER SATHIYANATHAN [딸, 12세] | O14: 2명/ (자녀 1명) | P14: Agree | Q14: 등록 | R14: paid | S14: PETER SATHIYANATHAN MICHEAL JOHN | T14: 28573 | U14: doctorpeter@hotmail.com | V14: 생년월일 일치, 이메일 일치, 이름 완전일치
A15: 45890.989 | B15: Alina | D15: Female | E15: 36334 | F15: Belarus | G15: Belarussian CMF | H15: Ophtalmologist | I15: =VLOOKUP(CLEAN(F15),'World Bank Categories'!$B$4:$C$220,2,FALSE) -> Middle income | J15: kurdunap@gmail.com | K15: Main Congress Only | L15: June 29, June 30, July 1, July 2, July 3, July 4 | P15: Agree | Q15: 등록 | R15: bursary | S15: Alina Kurdun
A16: 45895.305 | B16: Semby, Johan Kyung Hwa | D16: Male | E16: 24127 | F16: Sweden | G16: Linköping University/Linköping University Hospital Department of Opthalmology/ ICMDA Sweden | H16: Senior Consultant in Ophthalmology/ Leader, organizer for the delegation from ICMDA Sweden and Finland | I16: =VLOOKUP(CLEAN(F16),'World Bank Categories'!$B$4:$C$220,2,FALSE) -> High income | J16: johan.semby@gmail.com | K16: Pre-Conference + Main Congress | L16: June 29, June 30, July 1, July 2, July 3, July 4 | M16: 1, Joshua Semby, male, son, joshua.semby7@gmail.com | N16: Joshua Semby [아들] | O16: 2명/ (자녀 1명) | P16: Agree | Q16: 등록 | R16: paid | S16: Johan Kyung Hwa Semby | T16: 24492 | U16: johan.semby@gmail.com | V16: 이메일 일치, 이름 유사도 100, 이름 토큰 포함
A17: 45900.026 | B17: NURGUL MAMYROVA | D17: Female | E17: 29297 | F17: Kyrgyz Republic | G17: ICMDA | H17: Doctor | I17: =VLOOKUP(CLEAN(F17),'World Bank Categories'!$B$4:$C$220,2,FALSE) -> Middle income | J17: nurgulicmda@gmail.com | K17: Student Conference + Main Congress | L17: June 29, June 30, July 1, July 2, July 3, July 4 | M17: Yes: Simon Peter Nadeem-my husband, My Daughter-Shulmiyat Sarah Nadeem, and my son -Timothy Simon Nadeem) | N17: Simon Peter Nadeem [배우자(남편)] Shulmiyat Sarah Nadeem[딸, 18세] Timothy Simon Nadeem [아들, 13세] | O17: 4명/ (자녀 2명, 배우자 1명) | P17: Agree | Q17: 등록 | R17: paid | S17: Nurgul Mamyrova | T17: 29297 | U17: nurgulicmda@gmail.com | V17: 생년월일 일치, 이메일 일치, 이름 완전일치
A18: 45908.782 | B18: Diana | C18: Safina | D18: Female | E18: 30253 | F18: Russian Federation | G18: ICMDA | H18: Regional representative, Eurasia training administrator | I18: =VLOOKUP(CLEAN(F18),'World Bank Categories'!$B$4:$C$220,2,FALSE) -> High income | J18: diana.safina316@gmail.com | K18: Pre-Conference + Main Congress | L18: June 29, June 30, July 1, July 2, July 3, July 4 | M18: Daria Safina, female, daughter 13 years old | N18: Daria Safina [딸, 13세] | O18: 2명/ (자녀 1명) | P18: Agree | Q18: 등록 | R18: bursary | S18: Diana Safina | T18: 30253 | U18: diana.safina316@gmail.com | V18: 생년월일 일치, 이메일 일치, 이름 유사도 100
A19: 45909.696 | B19: BENJAMIN DUBE | D19: Male | E19: 35302 | F19: ZIMBABWE | G19: NATIONAL UNIVERSITY OF SCIENCE AND TECHNOLOGY, ZIMBABWE | H19: Chairperson, NUST Christian Medical Fellowship (CMF) | I19: =VLOOKUP(CLEAN(F19),'World Bank Categories'!$B$4:$C$220,2,FALSE) -> Middle income | J19: benjiedube25@gmail.com | K19: Student Conference + Main Congress | L19: June 29, June 30, July 1, July 2, July 3, July 4 | P19: Agree | Q19: 등록 | R19: bursary | S19: DUBE BENJAMIN | T19: 35302 | U19: benjiedube25@gmail.com | V19: 생년월일 일치, 이메일 일치, 이름 유사도 100, 이름 토큰 포함
A20: 45918.29 | B20: Peter Fee | D20: Male | E20: 28989 | F20: United Kingdom | G20: Royal Belfast Children's Hospital, Belfast, UK | H20: Consultant Anaesthetist | I20: =VLOOKUP(CLEAN(F20),'World Bank Categories'!$B$4:$C$220,2,FALSE) -> High income | J20: peterfee@doctors.org.uk | K20: Pre-Conference + Main Congress | L20: June 29, June 30, July 1, July 2, July 3, July 4 | M20: 4: Kerry Fee, female, wife, thefees@me.com; Grace Fee, female, daughter; Joel Fee, male, son; Toby Fee, male, son. | N20: Kerry Fee [배우자(아내)] thefees@me.com Grace Fee [딸, 12세] Joel Fee [아들, 14세] Toby Fee [아들, 10세] | O20: 5명/ (자녀 3명, 배우자 1명) | P20: Agree | Q20: 등록 | R20: paid | S20: Peter Fee | T20: 28989 | U20: peterfee@doctors.org.uk | V20: 생년월일 일치, 이메일 일치, 이름 완전일치
A21: 45918.575 | B21: Nakanjako | C21: Sharon | D21: Female | E21: 34006 | F21: Uganda | G21: Uganda Christian medical Fellowship | H21: Clinical psychologist | I21: =VLOOKUP(CLEAN(#REF!),'World Bank Categories'!$B$4:$C$220,2,FALSE) -> #REF! | J21: sharonnakanjako2023@gmail.com | K21: Pre-Conference + Main Congress | L21: June 29, June 30, July 1, July 2, July 3, July 4 | P21: Agree | Q21: 등록 | R21: bursary | S21: Sharon Nakanjako | T21: 34006 | U21: sharonnakanjako2023@gmail.com | V21: 생년월일 일치, 이메일 일치, 이름 유사도 100
A22: 45922.815 | B22: Greta Gamal Nazir Kross | D22: Female | E22: 30328 | F22: Egypt, Arab Rep. | G22: Cmf egypt | H22: Pediatric specialist (director of operations of cmf egypt) | I22: =VLOOKUP(CLEAN(F22),'World Bank Categories'!$B$4:$C$220,2,FALSE) -> Middle income | J22: gretagamal@hotmail.com | K22: Pre-Conference + Main Congress | L22: June 29, June 30, July 1, July 2, July 3, July 4 | M22: George robile,male,husband Jason george,male ,son Jenny george,female,daughter | N22: George robile [배우자(남편)] gretagamal@hotmail.com Jason george [아들, 13세] Jenny george [딸, 17세] | O22: 4명/ (자녀 2명, 배우자 1명) | P22: Agree | Q22: 등록 | R22: bursary | S22: Greta Gamal
A23: 45927.904 | B23: Christa Adeline | D23: Female | E23: 35457 | F23: Indonesia | G23: ICMDA | H23: Regional Representative for Southeast Asia | I23: =VLOOKUP(CLEAN(F23),'World Bank Categories'!$B$4:$C$220,2,FALSE) -> Middle income | J23: christa.adeline@icmda.net | K23: Pre-Conference + Main Congress | L23: June 30, July 1, July 2, July 3, July 4 | P23: Agree | Q23: 등록 | R23: paid | S23: Christa Adeline | T23: 35457 | U23: christa.adeline@icmda.net | V23: 생년월일 일치, 이메일 일치, 이름 완전일치
A24: 45927.984 | B24: Quacy Asheeke Grant | D24: Male | E24: 31257 | F24: Guyana | G24: Lausanne Movement Caribbean/ICMDA Guyana-Caribbean | H24: Regional Director (Lausanne Movement Caribbean) | I24: =VLOOKUP(CLEAN(F24),'World Bank Categories'!$B$4:$C$220,2,FALSE) -> High income | J24: qgrant@lausanne.org | K24: Main Congress Only | L24: June 29, June 30, July 1, July 2, July 3, July 4 | P24: Agree | Q24: 등록 | R24: bursary | S24: Quacy Asheeke Grant
A25: 45928.771 | B25: LOUIE BENJAMIN KWON BOU | D25: Male | E25: 38475 | F25: NEW ZEALAND | G25: University of Otago | H25: Medical Student | I25: =VLOOKUP(CLEAN(F25),'World Bank Categories'!$B$4:$C$220,2,FALSE) -> High income | J25: bklouie@outlook.com | K25: Pre-Conference + Main Congress | L25: June 29, June 30, July 1, July 2, July 3 | M25: 1, Yidao Chua, male, friend, yidaochua@gmail.com | P25: Agree | Q25: 등록 | R25: paid | S25: Benjamin Louie | T25: 38475 | U25: bklouie@outlook.com | V25: 생년월일 일치, 이메일 일치, 이름 유사도 100, 이름 토큰 포함
A26: 45929.067 | B26: Mohalenyane Matheko Mary | D26: Female | E26: 35435 | F26: Lesotho | G26: Senkatana Oncology Clinic | H26: Dr. | I26: =VLOOKUP(CLEAN(F26),'World Bank Categories'!$B$4:$C$220,2,FALSE) -> Middle income | J26: matheko.mohalenyane@gmail.com | K26: Pre-Conference + Main Congress | L26: June 29, June 30, July 1, July 2, July 3, July 4 | P26: Agree | Q26: 등록 | R26: bursary | S26: Matheko Mohalenyane | T26: 35435 | U26: matheko.mohalenyane@yahoo.com | V26: 생년월일 일치, 이름 유사도 100, 이름 토큰 포함
A27: 45930.648 | B27: Anitha David | D27: Female | E27: 25119 | F27: India | G27: Emmanuel Hospital Association | H27: Dentist | I27: =VLOOKUP(CLEAN(F27),'World Bank Categories'!$B$4:$C$220,2,FALSE) -> Middle income | J27: Anitha.David@icmda.net | K27: Pre-Conference + Main Congress | L27: June 29, June 30, July 1, July 2, July 3, July 4 | P27: Agree | Q27: 등록 | R27: bursary | S27: Anitha David | T27: 25119 | U27: Anitha.David@imcda.net
A28: 45932.036 | B28: Abiyu Tadesse Fulea | C28: Kim | D28: Male | E28: 31339 | F28: Ethiopia | G28: CMF Ethiopia | H28: CMF Ethiopia chairperson | I28: =VLOOKUP(CLEAN(F28),'World Bank Categories'!$B$4:$C$220,2,FALSE) -> Low income | J28: martabiyju@gmail.com | K28: Pre-Conference + Main Congress | L28: June 29, June 30, July 1, July 2, July 3, July 4 | P28: Agree | Q28: 등록 | R28: bursary | S28: Abiyu Tadesse Fulea | T28: 31339 | U28: martabiyju@gmail.com | V28: 생년월일 일치, 이메일 일치, 이름 완전일치
A29: 45933.674 | B29: Kezia Christina Viani Wijaya | C29: 케지아 크리스티나 비아니 위자야 | D29: Female | E29: 36659 | F29: Indonesia | G29: CMDA Indonesia | H29: Member | I29: =VLOOKUP(CLEAN(F29),'World Bank Categories'!$B$4:$C$220,2,FALSE) -> Middle income | J29: keziawij@gmail.com | K29: Main Congress Only | L29: July 1, July 2, July 3, July 4 | P29: Agree | Q29: 등록 | R29: bursary | S29: Kezia Christina Viani Wijaya | T29: 36659 | U29: keziawij@gmail.com | V29: 생년월일 일치, 이메일 일치, 이름 완전일치
A30: 45943.156 | B30: Enimil Anthony Kwame | D30: Male | E30: 26224 | F30: Ghana | G30: Kwame Nkrumah University of Science and Technology | H30: Professor/Lecturer | I30: =VLOOKUP(CLEAN(F30),'World Bank Categories'!$B$4:$C$220,2,FALSE) -> Middle income | J30: Tonash@gmail.com | K30: Pre-Conference + Main Congress | L30: June 29, June 30, July 1, July 2, July 3, July 4 | M30: Helena Enimil, Female , Spouse | P30: Agree | Q30: 등록 | R30: Paid | S30: Anthony Enimil | T30: 26224 | U30: tonash@gmail.com | V30: 생년월일 일치, 이메일 일치, 이름 유사도 100, 이름 토큰 포함
A31: 45946.597 | B31: Alina Istrati | D31: Female | E31: 37372 | F31: Romania | G31: Nicolae Testemiţanu Moldova State University of Medicine and Pharmacy | H31: Student | I31: =VLOOKUP(CLEAN(F31),'World Bank Categories'!$B$4:$C$220,2,FALSE) -> High income | J31: istratialina16@gmail.com | K31: Pre-Conference + Main Congress | L31: June 29, June 30, July 1, July 2, July 3, July 4 | P31: Agree | Q31: 등록 | R31: bursary | S31: Istrati Alina | T31: 37372 | U31: istratialina16@gmail.com | V31: 생년월일 일치, 이메일 일치, 이름 유사도 100, 이름 토큰 포함
A32: 45947.179 | B32: HERVE TISTOU HITIMANA | D32: Male | E32: 33297 | F32: Burundi | G32: BCMDA | H32: Dr | I32: =VLOOKUP(CLEAN(F32),'World Bank Categories'!$B$4:$C$220,2,FALSE) -> Low income | J32: h.tistou@gmail.com | K32: Pre-Conference + Main Congress | L32: June 29, June 30, July 1, July 2, July 3, July 4 | P32: Agree | Q32: 등록 | R32: bursary | S32: HERVE TISTOU HITIMANA | T32: 33297 | U32: h.tistou@gmail.com | V32: 생년월일 일치, 이메일 일치, 이름 완전일치
A33: 45947.313 | B33: OKONGO BERFINA | D33: Female | E33: 36417 | F33: Senegal | G33: Association des médecins et dentistes chrétiens du Sénégal | H33: Treasury | I33: =VLOOKUP(CLEAN(F33),'World Bank Categories'!$B$4:$C$220,2,FALSE) -> Middle income | J33: O.berfina1@gmail.com | K33: Pre-Conference + Main Congress | L33: June 29, June 30, July 1, July 2, July 3, July 4 | P33: Agree | Q33: 등록 | R33: bursary | S33: OKONGO Berfina | T33: 36417 | U33: O.berfina1@gmail.com | V33: 생년월일 일치, 이메일 일치, 이름 완전일치
A34: 45947.313 | B34: ADONONSI FEGNITI MAHUTON MARIELLE | D34: Female | E34: 37086 | F34: Benin | G34: Association des Médecins et Dentistes Chrétiens du Sénégal | H34: Student leader | I34: =VLOOKUP(CLEAN(F34),'World Bank Categories'!$B$4:$C$220,2,FALSE) -> Middle income | J34: mariellehy@gmail.com | K34: Pre-Conference + Main Congress | L34: June 29, June 30, July 1, July 2, July 3, July 4 | P34: Agree | Q34: 등록 | R34: bursary | S34: Marielle Adononsi | T34: 37086 | U34: mariellehy@gmail.com | V34: 생년월일 일치, 이메일 일치, 이름 유사도 100, 이름 토큰 포함
A35: 45947.313 | B35: Rebecca Biaye | D35: Female | E35: 33994 | F35: Senegal | G35: Association des médecins et dentistes chrétiens du Sénégal | H35: National president | I35: =VLOOKUP(CLEAN(F35),'World Bank Categories'!$B$4:$C$220,2,FALSE) -> Middle income | J35: rebiaye@gmail.com | K35: Pre-Conference + Main Congress | L35: June 29, June 30, July 1, July 2, July 3, July 4 | P35: Agree | Q35: 등록 | R35: bursary | S35: Rebecca Biaye | T35: 33994 | U35: rebiaye@gmail.com | V35: 생년월일 일치, 이메일 일치, 이름 완전일치
A36: 45948.297 | B36: OBO Yapo Gilles | D36: Male | E36: 34126 | F36: Côte d’Ivoire | G36: AMPCI | H36: Medical Officer | I36: =VLOOKUP(CLEAN(F36),'World Bank Categories'!$B$4:$C$220,2,FALSE) -> Middle income | J36: yapogilles@yahoo.fr | K36: Pre-Conference + Main Congress | L36: June 29, June 30, July 1, July 2, July 3, July 4 | P36: Agree | Q36: 등록 | R36: bursary | S36: OBO Yapo Gilles | T36: 34126 | U36: yapogilles@yahoo.fr | V36: 생년월일 일치, 이메일 일치, 이름 완전일치
A37: 45948.8 | B37: Nermin Botros Zakaria Gohar | C37: 네르민 | D37: Female | E37: 34099 | F37: Egypt, Arab Rep. | G37: Faculty of medicine menofia university | H37: Assistant lecturer | I37: =VLOOKUP(CLEAN(F37),'World Bank Categories'!$B$4:$C$220,2,FALSE) -> Middle income | J37: nermenbotros22@gmail.com | K37: Pre-Conference + Main Congress | L37: June 29, June 30, July 1, July 2, July 3, July 4 | P37: Agree | Q37: 등록 | R37: bursary | S37: Nermin botros zakaria | T37: 34099 | U37: nermenbotros22@gmail.com | V37: 생년월일 일치, 이메일 일치, 이름 유사도 100, 이름 토큰 포함
A38: 45949.129 | B38: Nancy Botros Zakria Gohar | D38: Female | E38: 36381 | F38: Egypt, Arab Rep. | G38: Benha university hospital | H38: Cardiothoracic surgery resident | I38: =VLOOKUP(CLEAN(F38),'World Bank Categories'!$B$4:$C$220,2,FALSE) -> Middle income | J38: nancybotros161@gmail.com | K38: Pre-Conference + Main Congress | L38: June 29, June 30, July 1, July 2, July 3, July 4 | P38: Agree | Q38: 등록 | R38: bursary | S38: Nancy Botros Zakria Gohar | T38: 36381 | U38: nancybotros161@gmail.com | V38: 생년월일 일치, 이메일 일치, 이름 완전일치
A39: 45949.232 | B39: Bodoua Adjo Anne-Mireille | D39: Female | E39: 37412 | F39: Côte d’Ivoire | G39: AMPCI | H39: Medical student | I39: =VLOOKUP(CLEAN(F39),'World Bank Categories'!$B$4:$C$220,2,FALSE) -> Middle income | J39: bodouaanno@gmail.com | K39: Pre-Conference + Main Congress | L39: June 29, June 30, July 1, July 2, July 3, July 4 | P39: Agree | Q39: 등록 | R39: bursary | S39: Bodoua Adjo Anne-Mireille | T39: 37412 | U39: bodouaanno@gmail.com | V39: 생년월일 일치, 이메일 일치, 이름 완전일치
A40: 45950.126 | B40: Kupualor David Akwafo | D40: Male | E40: 28979 | F40: Ghana | G40: University of Ghana Medical Centre/St Joseph Hospital, Koforidua | H40: Senior Specialist | I40: =VLOOKUP(CLEAN(F40),'World Bank Categories'!$B$4:$C$220,2,FALSE) -> Middle income | J40: dkupualor@yahoo.com | K40: Pre-Conference + Main Congress | L40: June 29, June 30, July 1, July 2, July 3, July 4 | M40: Mrs Sarah Kupualor, Wife, marsar.asaa@yahoo.com | P40: Agree | Q40: 등록 | R40: paid | S40: David Akwafo Kupualor | T40: 28979 | U40: dkupualor@yahoo.com | V40: 생년월일 일치, 이메일 일치, 이름 유사도 100, 이름 토큰 포함
A41: 45950.134 | B41: Uhunmwangho Courage Ukponmwan | D41: Male | E41: 27390 | F41: Nigeria | G41: ICMDA West Africa | H41: Regional Secretary | I41: =VLOOKUP(CLEAN(F41),'World Bank Categories'!$B$4:$C$220,2,FALSE) -> Middle income | J41: ucourage@yahoo.com | K41: Pre-Conference + Main Congress | L41: June 29, June 30, July 1, July 2, July 3, July 4 | P41: Agree | Q41: 등록 | R41: bursary | S41: Courage Uhunmwangho | T41: 27390 | U41: ucourage@yahoo.com | V41: 생년월일 일치, 이메일 일치, 이름 유사도 100, 이름 토큰 포함
A42: 45951.22 | B42: IKEUBA DELIGHT CHIDEBELU | C42: Delight | D42: Male | E42: 38579 | F42: Nigeria | G42: Christian Medical and Dental Association | H42: Mr. | I42: =VLOOKUP(CLEAN(F42),'World Bank Categories'!$B$4:$C$220,2,FALSE) -> Middle income | J42: delightikeuba@gmail.com | K42: Pre-Conference + Main Congress | L42: June 30, July 1, July 2, July 3, July 4 | P42: Agree | Q42: 등록 | R42: bursary | S42: IKEUBA DELIGHT CHIDEBELU | T42: 38579 | U42: delightikeuba@gmail.com | V42: 생년월일 일치, 이메일 일치, 이름 완전일치
A43: 45952.287 | B43: ABASIRA TRINITY MUNGUFENI | D43: Male | E43: 35236 | F43: Uganda | G43: KING CEASOR UNIVERSITY, UGANDA CHRISTIAN MEDICAL FELLOWSHIP | H43: STUDENT | I43: =VLOOKUP(CLEAN(F43),'World Bank Categories'!$B$4:$C$220,2,FALSE) -> Low income | J43: tabasiramungufeni22ag@student.kcu.ac.ug | K43: Pre-Conference + Main Congress | L43: June 29, June 30, July 1, July 2, July 3, July 4 | P43: Agree | Q43: 등록 | R43: bursary | S43: Abasira Trinity Mungufeni | T43: 35236 | U43: tabasiramungufeni22ag@student.kcu.ac.ug | V43: 생년월일 일치, 이메일 일치, 이름 완전일치
A44: 45952.509 | B44: KUSONGA LABAN | D44: Male | E44: 37547 | F44: Uganda | G44: Kabale University/Uganda christian medical fellowship | H44: Student | I44: =VLOOKUP(CLEAN(F44),'World Bank Categories'!$B$4:$C$220,2,FALSE) -> Low income | J44: labkusonga20@gmail.com | K44: Pre-Conference + Main Congress | L44: June 29, June 30, July 1, July 2, July 3, July 4 | P44: Agree | Q44: 등록 | R44: bursary | S44: KUSONGA LABAN | T44: 37182 | U44: labkusonga20@gmail.com | V44: 이메일 일치, 이름 완전일치
A45: 45952.557 | B45: Jenniffer Laura Daltro Monteiro da Silva Loures | D45: Female | E45: 29011 | F45: Brazil | G45: Medicos de Cristo | H45: icmda Fieldworker Brazil Colombia and Venezuela | I45: =VLOOKUP(CLEAN(F45),'World Bank Categories'!$B$4:$C$220,2,FALSE) -> Middle income | J45: jldms1@gmail.com | K45: Pre-Conference + Main Congress | L45: June 29, June 30, July 1, July 2, July 3, July 4 | M45: Felipe Aleixo Loures ( husband) | P45: Agree | Q45: 등록 | R45: bursary | S45: jenniffer laura daltro monteiro da silva loures | T45: 29011 | U45: jldms1@gmail.com | V45: 생년월일 일치, 이메일 일치, 이름 완전일치
A46: 45952.74 | B46: Elita Theofani Juliawan | D46: Female | E46: 36498 | F46: Indonesia | G46: ICMDA | H46: Training track facilitator | I46: =VLOOKUP(CLEAN(F46),'World Bank Categories'!$B$4:$C$220,2,FALSE) -> Middle income | J46: elitatheofani@yahoo.co.id | K46: Pre-Conference + Main Congress | L46: June 30, July 1, July 2, July 3, July 4 | P46: Agree | Q46: 등록 | R46: paid | S46: Elita Theofani Juliawan | T46: 36498 | U46: elitatheofani@yahoo.co.id | V46: 생년월일 일치, 이메일 일치, 이름 완전일치
A47: 45952.832 | B47: NEMBA GRACE VAIBRA | D47: Female | E47: 37163 | F47: Chad | G47: ASSOCIATION DES MEDECINS ET DENTISTES CHRETIENS DU TCHAD(AMDCT) | H47: ETUDIANT | I47: =VLOOKUP(CLEAN(F47),'World Bank Categories'!$B$4:$C$220,2,FALSE) -> Low income | J47: gracevaibra777@gmail.com | K47: Pre-Conference + Main Congress | L47: June 29, June 30, July 1, July 2, July 3, July 4 | P47: Agree | Q47: 등록 | R47: bursary | S47: Nemba Grâce Vaibra | T47: 37163 | U47: gracevaibra777@gmail.com | V47: 생년월일 일치, 이메일 일치, 이름 완전일치
A48: 45952.89 | B48: Ika Septiana Eryani | D48: Female | E48: 34219 | F48: Indonesia | G48: Ministry of Health, Indonesia | H48: Health Administrator | I48: =VLOOKUP(CLEAN(F48),'World Bank Categories'!$B$4:$C$220,2,FALSE) -> Middle income | J48: trifosa.ikaseptiana@gmail.com | K48: Main Congress Only | L48: July 2, July 3, July 4 | P48: Agree | Q48: 등록 | R48: bursary | S48: Ika Septiana Eryani | T48: 34219 | U48: trifosa.ikaseptiana@gmail.com | V48: 생년월일 일치, 이메일 일치, 이름 완전일치
A49: 45952.99 | B49: Ansino Skyleth | D49: Female | E49: 35438 | F49: Philippines | G49: Bileg Community Outreach International | H49: Resident Physician | I49: =VLOOKUP(CLEAN(F49),'World Bank Categories'!$B$4:$C$220,2,FALSE) -> Middle income | J49: skyansinophi@gmail.com | K49: Main Congress Only | L49: July 2, July 3, July 4 | P49: Agree | Q49: 등록 | R49: bursary | S49: Skyleth Ansino | T49: 35438 | U49: skyansinophi@gmail.com | V49: 생년월일 일치, 이메일 일치, 이름 유사도 100, 이름 토큰 포함
A50: 45953.025 | B50: Jo Vee Java Dignadice | D50: Female | E50: 23483 | F50: Philippines | G50: ICMDA/MCCN | H50: Global Training Track Coordinator /Director | I50: =VLOOKUP(CLEAN(F50),'World Bank Categories'!$B$4:$C$220,2,FALSE) -> Middle income | J50: jov@doctor.com | K50: Pre-Conference + Main Congress | L50: June 29, June 30, July 1, July 2, July 3, July 4 | M50: Isa Berne J. Dignadice | P50: Agree | Q50: 등록 | R50: bursary | S50: Jo Vee Dignadice | T50: 22752 | U50: jov@doctor.com | V50: 이메일 일치, 이름 유사도 100, 이름 토큰 포함
A51: 45953.92 | B51: Finish Fernando | D51: Male | E51: 31262 | F51: Indonesia | G51: Bethesda Serukam Mission Hospital | H51: Vice Director | I51: =VLOOKUP(CLEAN(F51),'World Bank Categories'!$B$4:$C$220,2,FALSE) -> Middle income | J51: finish.fernando@gmail.com | K51: Main Congress Only | L51: June 29, June 30, July 1, July 2, July 3, July 4 | P51: Agree | Q51: 등록 | R51: bursary | S51: Finish Fernando | T51: 31262 | U51: finish.fernando@gmail.com | V51: 생년월일 일치, 이메일 일치, 이름 완전일치
A52: 45954.066 | B52: Lunkuse Henriettah Dungu | D52: Female | E52: 36855 | F52: Uganda | G52: Islamic University in Uganda | H52: Medical Doctor | I52: =VLOOKUP(CLEAN(F52),'World Bank Categories'!$B$4:$C$220,2,FALSE) -> Low income | J52: henriettahdungu@gmail.com | K52: Pre-Conference + Main Congress | L52: 46203 | P52: Agree | Q52: 등록 | R52: bursary | S52: Lunkuse Henriettah Dungu | T52: 36855 | U52: henriettahdungu@gmail.com | V52: 생년월일 일치, 이메일 일치, 이름 완전일치
A53: 45955.199 | B53: Melvar Kelly | D53: Female | E53: 36376 | F53: Kenya | G53: Moi University | H53: Student | I53: =VLOOKUP(CLEAN(F53),'World Bank Categories'!$B$4:$C$220,2,FALSE) -> Middle income | J53: Kellymelvar285@gmail.com | K53: Pre-Conference + Main Congress | L53: June 29, June 30, July 1, July 2, July 3, July 4 | P53: Agree | Q53: 등록 | R53: bursary | S53: Melvar Kelly | T53: 36376 | U53: kellymelvar285@gmail.com | V53: 생년월일 일치, 이메일 일치, 이름 완전일치
A54: 45957.162 | B54: OGUNGBANGBE OLUTOLA ESTHER | D54: Female | E54: 36253 | F54: NIGERIA | G54: ABIA STATE UNIVERSITY TEACHING HOSPITAL/CMDA NIGERIA | H54: SCHOOL WELFARE DIRECTOR/ SISTER'S COORDINATOR | I54: =VLOOKUP(CLEAN(F54),'World Bank Categories'!$B$4:$C$220,2,FALSE) -> Middle income | J54: estherogungbangbe.eo@gmail.com | K54: Pre-Conference + Main Congress | L54: June 29, June 30, July 1, July 2, July 3, July 4 | P54: Agree | Q54: 등록 | R54: Paid | S54: Ogungbangbe Olutola Esther | T54: 36253 | U54: estherogungbangbe.eo@gmail.com | V54: 생년월일 일치, 이메일 일치, 이름 완전일치
A55: 45957.261 | B55: IRIA DOMINION OSAYOMORE | D55: Male | E55: 35712 | F55: Nigeria | G55: Federal Medical Centre, Owo | H55: Doctor | I55: =VLOOKUP(CLEAN(F55),'World Bank Categories'!$B$4:$C$220,2,FALSE) -> Middle income | J55: iriadominion@gmail.com | K55: Pre-Conference + Main Congress | L55: June 29, June 30, July 1, July 2, July 3, July 4 | P55: Agree | Q55: 등록 | R55: bursary | S55: Dominion Iria | T55: 35712 | U55: iriadominion@gmail.com | V55: 생년월일 일치, 이메일 일치, 이름 유사도 100, 이름 토큰 포함
A56: 45957.284 | B56: LINGA, fidelis filibus | D56: Male | E56: 30098 | F56: Nigeria | G56: Federal Teaching Hospital, Gombe Gombe state | H56: Doctor, | I56: =VLOOKUP(CLEAN(F56),'World Bank Categories'!$B$4:$C$220,2,FALSE) -> Middle income | J56: drfillinga@gmail.com | K56: Pre-Conference + Main Congress | L56: June 29, June 30, July 1, July 2, July 3, July 4 | P56: Agree | Q56: 등록 | R56: bursary | S56: LINGA, Fidelis Filibus | T56: 30098 | U56: drfillinga@gmail.com | V56: 생년월일 일치, 이메일 일치, 이름 완전일치
A57: 45957.46 | B57: Paul Mayellawos Karuwa | D57: Male | E57: 35773 | F57: Nigeria | G57: CMDA-Nigeria, Kano State Chapter | H57: Dr. | I57: =VLOOKUP(CLEAN(F57),'World Bank Categories'!$B$4:$C$220,2,FALSE) -> Middle income | J57: ataschong@gmail.com | K57: Pre-Conference + Main Congress | L57: June 29, June 30, July 1, July 2, July 3, July 4 | P57: Agree | Q57: 등록 | R57: bursary | S57: PAUL MAYELLAWOS KARUWA | T57: 35773 | U57: ataschong@gmail.com | V57: 생년월일 일치, 이메일 일치, 이름 완전일치
A58: 45958.565 | B58: Adiyana Esti Purwaningrum | D58: Female | E58: 27940 | F58: Indonesia | G58: Indonesia Christian Medical and Dental Association | H58: Mission division team work | I58: =VLOOKUP(CLEAN(F58),'World Bank Categories'!$B$4:$C$220,2,FALSE) -> Middle income | J58: adienesti@gmail.com | K58: Pre-Conference + Main Congress | L58: June 30, July 1, July 2, July 3, July 4 | P58: Agree | Q58: 등록 | R58: bursary | S58: Adiyana Esti Purwaningrum | T58: 27940 | U58: adienesti@gmail.com | V58: 생년월일 일치, 이메일 일치, 이름 완전일치
A59: 45958.777 | B59: Etubi Alexander Ibrahim | D59: Male | E59: 31409 | F59: Nigeria | G59: University of Abuja Teaching Hospital/CMDA Nigeria | H59: Dr/ICMDA Regional Representative Anglophone west Africa/Deputy CEO 2 CMDA Nigeria | I59: =VLOOKUP(CLEAN(F59),'World Bank Categories'!$B$4:$C$220,2,FALSE) -> Middle income | J59: alexetubi28@gmail.com | K59: Pre-Conference + Main Congress | L59: June 29, June 30, July 1, July 2, July 3, July 4 | P59: Agree | Q59: 등록 | R59: bursary | S59: Etubi Alexander Ibrahim | T59: 31409 | U59: alexetubi28@gmail.com | V59: 생년월일 일치, 이메일 일치, 이름 완전일치
A60: 45958.989 | B60: LINDAEL GEOFREY MLAY | D60: Female | E60: 34612 | F60: Tanzania | G60: SANYA JUU LUTHERAN HEALTH CENTRE | H60: MEDICAL OFFICER IN CHARGE | I60: =VLOOKUP(CLEAN(F60),'World Bank Categories'!$B$4:$C$220,2,FALSE) -> Middle income | J60: mlaylinda4@gmail.com | K60: Pre-Conference + Main Congress | L60: 46202 | P60: Agree | Q60: 등록 | R60: bursary | S60: LINDAEL G MLAY | T60: 34612 | U60: mlaylinda4@gmail.com | V60: 생년월일 일치, 이메일 일치, 이름 유사도 92
A61: 45961.094 | B61: Cornel Martin Angolile | D61: Male | E61: 36016 | F61: Tanzania | G61: London School of Hygiene & Tropical Medicine | H61: Dr | I61: =VLOOKUP(CLEAN(F61),'World Bank Categories'!$B$4:$C$220,2,FALSE) -> Middle income | J61: cornelangolile@gmail.com | K61: Pre-Conference + Main Congress | L61: June 29, June 30, July 1, July 2, July 3, July 4 | P61: Agree | Q61: 등록 | R61: bursary | S61: Cornel Martin Angolile | T61: 36016 | U61: cornelangolile@gmail.com | V61: 생년월일 일치, 이메일 일치, 이름 완전일치
A62: 45962.907 | B62: Eric Kiprotich Langat | D62: Male | E62: 32013 | F62: Kenya | G62: Tenwek Mission Hospital | H62: Dr | I62: =VLOOKUP(CLEAN(F62),'World Bank Categories'!$B$4:$C$220,2,FALSE) -> Middle income | J62: ericlangat77@gmail.com | K62: Pre-Conference + Main Congress | L62: June 29, June 30, July 1, July 2, July 3, July 4 | P62: Agree | Q62: 등록 | R62: bursary | S62: Eric Kiprotich Langat
A63: 45964.77 | B63: Biira Eunice | D63: Female | E63: 37380 | F63: Uganda | G63: Kampala international university | H63: Student | I63: =VLOOKUP(CLEAN(F63),'World Bank Categories'!$B$4:$C$220,2,FALSE) -> Low income | J63: eunycebiira@gmail.com | K63: Pre-Conference + Main Congress | L63: June 29, June 30, July 1, July 2, July 3, July 4 | P63: Agree | Q63: 등록 | R63: bursary | S63: Biira Eunice | T63: 45781 | U63: eunycebiira@gmail.com | V63: 이메일 일치, 이름 완전일치
A64: 45965.191 | B64: Yao Mawuena DANSOU | D64: Male | E64: 28467 | F64: TOGO | G64: ICMDA | H64: Dr | I64: =VLOOKUP(CLEAN(F64),'World Bank Categories'!$B$4:$C$220,2,FALSE) -> Low income | J64: dansouyaomawuena@gmail.com | K64: Pre-Conference + Main Congress | L64: June 29, June 30, July 1, July 2, July 3, July 4 | P64: Agree | Q64: 등록 | R64: bursary | S64: Yao Mawuena DANSOU | T64: 28467 | U64: dansouyaomawuena@gmail.com | V64: 생년월일 일치, 이메일 일치, 이름 완전일치
A65: 45965.232 | B65: KADZAHLO KOMLA DOVENE | D65: Male | E65: 32128 | F65: TOGO | G65: National malaria control program of Togo | H65: Public health specialist | I65: =VLOOKUP(CLEAN(F65),'World Bank Categories'!$B$4:$C$220,2,FALSE) -> Low income | J65: tdkadzahlo@gmail.com | K65: Pre-Conference + Main Congress | L65: June 29, June 30, July 1, July 2, July 3, July 4 | P65: Agree | Q65: 등록 | R65: bursary | S65: Kadzahlo Komla Dovenè | T65: 32128 | U65: tdkadzahlo@gmail.com | V65: 생년월일 일치, 이메일 일치, 이름 완전일치
A66: 45965.377 | B66: SEKO Kudzovi Mario | D66: Male | E66: 34722 | F66: TOGO | G66: AMCT | H66: Doctor | I66: =VLOOKUP(CLEAN(F66),'World Bank Categories'!$B$4:$C$220,2,FALSE) -> Low income | J66: kudzovimarioseko@gmail.com | K66: Pre-Conference + Main Congress | L66: June 29, June 30, July 1, July 2, July 3, July 4 | P66: Agree | Q66: 등록 | R66: bursary | S66: SEKO Kudzovi Mario | T66: 34722 | U66: kudzovimarioseko@gmail.com | V66: 생년월일 일치, 이메일 일치, 이름 완전일치
A67: 45966.822 | B67: Frisyeni Amanda Mangule | D67: Female | E67: 38402 | F67: Indonesia | G67: Udayana Univercity | H67: Student | I67: =VLOOKUP(CLEAN(F67),'World Bank Categories'!$B$4:$C$220,2,FALSE) -> Middle income | J67: amandamangule05@gmail.com | K67: Pre-Conference + Main Congress | L67: June 29, June 30, July 1, July 2, July 3, July 4 | P67: Agree | Q67: 등록 | R67: bursary | S67: Frisyeni Amanda Mangule | T67: 38402 | U67: amandamangule05@gmail.com | V67: 생년월일 일치, 이메일 일치, 이름 완전일치
A68: 45969.15 | B68: BIGOGO HERBERT CHARLES | D68: Male | E68: 35695 | F68: Uganda | G68: UGANDA CHRISTIAN MEDICAL FELLOWSHIP (UCMF) | H68: NATIONAL EXECUTIVE- UCMF STUDENTS LIAISON SECRETARY | I68: =VLOOKUP(CLEAN(F68),'World Bank Categories'!$B$4:$C$220,2,FALSE) -> Low income | J68: herbertbigogo@gmail.com | K68: Pre-Conference + Main Congress | L68: June 29, June 30, July 1, July 2, July 3, July 4 | P68: Agree | Q68: 등록 | R68: bursary | S68: BIGOGO HERBERT CHARLES | T68: 35695 | U68: herbertbigogo@gmail.com | V68: 생년월일 일치, 이메일 일치, 이름 완전일치
A69: 45970.186 | B69: Kyabu Kapijimpanga | D69: Female | E69: 37575 | F69: Zambia | G69: Muğla Sıtkı Koçman University | H69: Medical student | I69: =VLOOKUP(CLEAN(F69),'World Bank Categories'!$B$4:$C$220,2,FALSE) -> Middle income | J69: Kyabukapiji4@gmail.com | K69: Pre-Conference + Main Congress | L69: June 29, June 30, July 1, July 2, July 3, July 4 | P69: Agree | Q69: 등록 | R69: bursary | S69: Kyabu Kapijimpanga | T69: 37575 | U69: Kyabukapiji4@gmail.com | V69: 생년월일 일치, 이메일 일치, 이름 완전일치
A70: 45971.841 | B70: ANDRIA BURI ANAK IBRAHIM | D70: Male | E70: 37385 | F70: MALAYSIA | G70: UNIVERSITY OF MALAYSIA, SARAWAK | H70: MEDICAL STUDENT | I70: =VLOOKUP(CLEAN(F70),'World Bank Categories'!$B$4:$C$220,2,FALSE) -> Middle income | J70: andriaburiibrahim@gmail.com | K70: Pre-Conference + Main Congress | L70: June 29, June 30, July 1, July 2, July 3, July 4 | P70: Agree | Q70: 등록 | R70: bursary | S70: Andria Buri anak Ibrahim
A71: 45972.18 | B71: ZOTCHI Komi | D71: Male | E71: 34699 | F71: TOGO | G71: AMCT (Togo) | H71: Docteur | I71: =VLOOKUP(CLEAN(F71),'World Bank Categories'!$B$4:$C$220,2,FALSE) -> Low income | J71: kzotchi94@gmail.com | K71: Pre-Conference + Main Congress | L71: June 29, June 30, July 1, July 2, July 3, July 4 | P71: Agree | Q71: 등록 | R71: bursary | S71: ZOTCHI Paulin | T71: 34699 | U71: kzotchi94@gmail.com | V71: 생년월일 일치, 이메일 일치
A72: 45975.852 | B72: ADAMU ADDISSIE NURAMO | D72: Male | E72: 26816 | F72: Ethiopia | G72: ADDIS ABABA UNIVERSITY and CMDDF-Ethiopia | H72: MD MPH | I72: =VLOOKUP(CLEAN(F72),'World Bank Categories'!$B$4:$C$220,2,FALSE) -> Low income | J72: adamu.addissie@aaau.edu.et | K72: Pre-Conference + Main Congress | L72: June 29, June 30, July 1, July 2, July 3, July 4 | P72: Agree | Q72: 등록 | R72: bursary | S72: ADAMU ADDISSIE NURAMO | T72: 26816 | U72: adamu.addissie@aau.edu.et | V72: 생년월일 일치, 이름 완전일치
A73: 45976.196 | B73: Samuel Subba | D73: Male | E73: 36840 | F73: Nepal | G73: Norvic International Hospital | H73: Medical Officer (House Officer) | I73: =VLOOKUP(CLEAN(F73),'World Bank Categories'!$B$4:$C$220,2,FALSE) -> Middle income | J73: samuelsubba@daum.net | K73: Pre-Conference + Main Congress | L73: June 29, June 30, July 1, July 2, July 3, July 4 | P73: Agree | Q73: 등록 | R73: bursary | S73: Samuel Subba
A74: 45979.593 | B74: Augustine Max Lyamarungu | D74: Male | E74: 35122 | F74: Tanzania | G74: CMDA Tanzania chapter | H74: Medical officer (MD) | I74: =VLOOKUP(CLEAN(F74),'World Bank Categories'!$B$4:$C$220,2,FALSE) -> Middle income | J74: agogomax.am@gmail.com | K74: Pre-Conference + Main Congress | L74: June 29, June 30, July 1, July 2, July 3, July 4 | P74: Agree | Q74: 등록 | R74: bursary | S74: Augustine Max Lyamarungu | T74: 35122 | U74: agogomax.am@gmail.com | V74: 생년월일 일치, 이메일 일치, 이름 완전일치
A75: 45981.656 | B75: Irakoze Christian | D75: Male | E75: 32586 | F75: Burundi | G75: Burundi Christian Medical and Dental Association | H75: Advisor, National Committee | I75: =VLOOKUP(CLEAN(F75),'World Bank Categories'!$B$4:$C$220,2,FALSE) -> Low income | J75: ichris255@gmail.com | K75: Pre-Conference + Main Congress | L75: June 29, June 30, July 1, July 2, July 3, July 4 | P75: Agree | Q75: 등록 | R75: bursary | S75: Christian Irakoze | T75: 32586 | U75: ichris255@gmail.com | V75: 생년월일 일치, 이메일 일치, 이름 유사도 100, 이름 토큰 포함
A76: 45982.754 | B76: Priyani Nelum Weerakoon | D76: Female | E76: 32684 | F76: Sri Lanka | G76: ICMDA | H76: Registered Nurse | I76: =VLOOKUP(CLEAN(F76),'World Bank Categories'!$B$4:$C$220,2,FALSE) -> Middle income | J76: 715nelumweerakoon@gmail.com | K76: Main Congress Only | L76: June 30, July 1, July 2, July 3, July 4 | P76: Agree | Q76: 등록 | R76: bursary | S76: Nelum Weerakoon | T76: 32684 | U76: 715nelumweerakoon@gmail.com | V76: 생년월일 일치, 이메일 일치, 이름 유사도 100, 이름 토큰 포함
A77: 45984.227 | B77: MALEKA Justice Illustre | C77: MALEKA Justice Illustre | D77: Male | E77: 33434 | F77: Congo,Rep. | G77: Medicals Sciences Superior Institute | H77: Doctor | I77: =VLOOKUP(CLEAN(F77),'World Bank Categories'!$B$4:$C$220,2,FALSE) -> Middle income | J77: justiceillustre@gmail.com | K77: Pre-Conference + Main Congress | L77: 46202 | P77: Agree | Q77: 등록 | R77: bursary | S77: MALEKA Justice Illustre | T77: 33434 | U77: justiceillustre@gmail.com | V77: 생년월일 일치, 이메일 일치, 이름 완전일치
A78: 45984.625 | B78: Alabi Favour Wealth | D78: Female | E78: 37776 | F78: Nigeria | G78: Bingham University Teaching Hospital, Jos | H78: School Academic Secretary of CMDA student arm BHUTH Chapter | I78: =VLOOKUP(CLEAN(F78),'World Bank Categories'!$B$4:$C$220,2,FALSE) -> Middle income | J78: Favouralabiwealth@gmail.com | K78: Pre-Conference + Main Congress | L78: June 29, June 30, July 1, July 2, July 3, July 4 | P78: Agree | Q78: 등록 | R78: Paid | S78: Alabi Favour | T78: 38142 | U78: Favouralabiwealth@gmail.com | V78: 이메일 일치, 이름 유사도 100, 이름 토큰 포함
A79: 45984.987 | B79: MASRA NGARMBAYE | D79: Male | E79: 31065 | F79: Chad | G79: ASSOCIATION DES MEDECINS ET DENTISTES CHRETIENS DU TCHAD- AMDCT | H79: DOCTOR MEMBER | I79: =VLOOKUP(CLEAN(F79),'World Bank Categories'!$B$4:$C$220,2,FALSE) -> Low income | J79: nmasra@yahoo.com | K79: Pre-Conference + Main Congress | L79: June 29, June 30, July 1, July 2, July 3, July 4 | M79: 1, Edith Dekoum Nelembaye, female, Wife, nmasra@yahoo.com 2, Manaseth Toulaboua Ngarmbaye, male, Son, nmasra@yahoo.com | N79: Edith Dekoum Nelembaye [배우자(아내)] Manaseth Toulaboua Ngarmbaye [아들, 2세] | O79: 3명/ (자녀 1명, 배우자 1명) | P79: Agree | Q79: 등록 | R79: bursary | S79: MASRA NGARMBAYE | T79: 31065 | U79: nmasra@yahoo.com | V79: 생년월일 일치, 이메일 일치, 이름 완전일치
A80: 45985.777 | B80: Moussa Oumarou | C80: Yacouba | D80: Male | E80: 36793 | F80: Nigeria | G80: AMPCN | H80: Leader Étudiant | I80: =VLOOKUP(CLEAN(F80),'World Bank Categories'!$B$4:$C$220,2,FALSE) -> Middle income | J80: yacouboum33@gmail.com | K80: Pre-Conference + Main Congress | L80: June 29, June 30, July 1, July 2, July 3, July 4 | P80: Agree | Q80: 등록 | R80: bursary | S80: Moussa Oumarou | T80: 36793 | U80: yacouboum33@gmail.com | V80: 생년월일 일치, 이메일 일치, 이름 완전일치
A81: 45985.853 | B81: MUPFASONI BELYSE | C81: MUPFASONI BELYSE | D81: Female | E81: 33868 | F81: Burundi | G81: UNIVERSITY OF NGOZI | H81: DR | I81: =VLOOKUP(CLEAN(F81),'World Bank Categories'!$B$4:$C$220,2,FALSE) -> Low income | J81: mupfasonib1@gmail.com | K81: Pre-Conference + Main Congress | L81: June 29, June 30, July 1, July 2, July 3, July 4 | P81: Agree | Q81: 등록 | R81: bursary | S81: MUPFASONI BELYSE | T81: 33868 | U81: mupfasonib1@gmail.com | V81: 생년월일 일치, 이메일 일치, 이름 완전일치
A82: 45988.082 | B82: Iryna Hushcha | D82: Female | E82: 33908 | F82: Belarus | G82: ICMDA | H82: Fieldworker | I82: =VLOOKUP(CLEAN(F82),'World Bank Categories'!$B$4:$C$220,2,FALSE) -> Middle income | J82: hushchairyna@gmail.com | K82: Main Congress Only | L82: june 30, July 1, July 2, July 3, July 4 | P82: Agree | Q82: 등록 | R82: bursary | S82: Iryna Hushcha | T82: 33908 | U82: hushchairyna@gmail.com | V82: 생년월일 일치, 이메일 일치, 이름 완전일치
A83: 45988.222 | B83: Timothy Tam | D83: Male | E83: 17098 | F83: Canada | G83: Christian Medical Dental association Canada | H83: Treasurer | I83: =VLOOKUP(CLEAN(F83),'World Bank Categories'!$B$4:$C$220,2,FALSE) -> High income | J83: timtamdmd@gmail.com | K83: Pre-Conference + Main Congress | L83: June 29, June 30, July 1, July 2, July 3, July 4 | M83: Remy Tam female and wife | P83: Agree | Q83: 등록 | R83: paid | S83: Timothy Tam | T83: 17098 | U83: timtamdmd@gmail.com | V83: 생년월일 일치, 이메일 일치, 이름 완전일치
A84: 45988.603 | B84: Mathew Santhosh Thomas | D84: Male | E84: 22235 | F84: India | G84: ICMDA | H84: Training in Charge | I84: =VLOOKUP(CLEAN(F84),'World Bank Categories'!$B$4:$C$220,2,FALSE) -> Middle income | J84: santhosh.mathew@icmda.net | K84: Pre-Conference + Main Congress | L84: June 29, June 30, July 1, July 2, July 3, July 4 | M84: 1 Saira Paulose, wife | P84: Agree | Q84: 등록 | R84: bursary | S84: Mathew Santhosh Thomas | T84: 22235 | U84: santhosh.mathew@icmda.net | V84: 생년월일 일치, 이메일 일치, 이름 완전일치
A85: 45989.19 | B85: Sofako Améganvi EGLOH | D85: Male | E85: 29659 | F85: TOGO | G85: CMF TOGO | H85: Doctor | I85: =VLOOKUP(CLEAN(F85),'World Bank Categories'!$B$4:$C$220,2,FALSE) -> Low income | J85: esofak81@gmail.com | K85: Pre-Conference + Main Congress | L85: June 29, June 30, July 1, July 2, July 3, July 4 | M85: 1, Afi Kafui BANIBA ATOKO Epse EGLOH, Female, Spouse, kbaniba@gmail.com 2, Betsaleel Ewousika Améganvi EGLOH, Male, Child, esofak81@gmail.com | N85: Afi Kafui BANIBA ATOKO Epse EGLOH [배우자(아내)] Betsaleel Ewousika Améganvi EGLOH [자녀, 3세] | O85: 3명/ (자녀 1명, 배우자 1명) | P85: Agree | Q85: 등록 | R85: bursary | S85: Améganvi Sofako EGLOH | T85: 29659 | U85: esofak81@gmail.com | V85: 생년월일 일치, 이메일 일치, 이름 유사도 100, 이름 토큰 포함
A86: 45989.837 | B86: Lucky Sarjono Buranda | D86: Male | E86: 33593 | F86: Indonesia | G86: Indonesia CMDF | H86: MD / Department of Mission | I86: =VLOOKUP(CLEAN(F86),'World Bank Categories'!$B$4:$C$220,2,FALSE) -> Middle income | J86: mdburanda@gmail.com | K86: Pre-Conference + Main Congress | L86: June 29, June 30, July 1, July 2, July 3, July 4 | P86: Agree | Q86: 등록 | R86: bursary | S86: Lucky Sarjono Buranda | T86: 33593 | U86: mdburanda@gmail.com | V86: 생년월일 일치, 이메일 일치, 이름 완전일치
A87: 45989.918 | B87: LAY LINHHAK | D87: Male | E87: 37852 | F87: Cambodia | G87: University Of Health Sciences | H87: Medical Student | I87: =VLOOKUP(CLEAN(F87),'World Bank Categories'!$B$4:$C$220,2,FALSE) -> Middle income | J87: linhhak213@gmail.com | K87: Main Congress Only | L87: July 1, July 2, July 3, July 4 | M87: Naro Sodavid, Male, Friend, narodavidktc@gmail.com | P87: Agree | Q87: 등록 | R87: bursary | S87: LAY LINHHAK | T87: 37852 | U87: linhhak213@gmail.com | V87: 생년월일 일치, 이메일 일치, 이름 완전일치
A88: 45989.92 | B88: Naro Sodavid | D88: Male | E88: 37875 | F88: Cambodia | G88: University of Health Sciences | H88: Medical student | I88: =VLOOKUP(CLEAN(F88),'World Bank Categories'!$B$4:$C$220,2,FALSE) -> Middle income | J88: narodavidktc@gmail.com | K88: Main Congress Only | L88: July 1, July 2, July 3, July 4 | M88: Lay Linhhak ,male,friend, linhhak213@gmail.com | P88: Agree | Q88: 등록 | R88: bursary | S88: NARO SODAVID | T88: 37875 | U88: narodavidktc@gmail.com | V88: 생년월일 일치, 이메일 일치, 이름 완전일치
A89: 45989.953 | B89: CHHANGSOUR YMEY | D89: Male | E89: 38368 | F89: Cambodia | G89: University of health and sciences | H89: Medical students | I89: =VLOOKUP(CLEAN(F89),'World Bank Categories'!$B$4:$C$220,2,FALSE) -> Middle income | J89: meyboy77@gmail.com | K89: Main Congress Only | L89: July 1, July 2, July 3, July 4 | P89: Agree | Q89: 등록 | R89: bursary | S89: ChhangSour Ymey | T89: 38368 | U89: meyboy77@gmail.com | V89: 생년월일 일치, 이메일 일치, 이름 완전일치
A90: 45989.954 | B90: TOUCH KEOMONEY | D90: Female | E90: 37925 | F90: Cambodia | G90: University of Health and Sciences | H90: Student | I90: =VLOOKUP(CLEAN(F90),'World Bank Categories'!$B$4:$C$220,2,FALSE) -> Middle income | J90: keomonyclever@gmail.com | K90: Main Congress Only | L90: July 1, July 2, July 3, July 4 | P90: Agree | Q90: 등록 | R90: bursary | S90: KEOMONEY TOUCH | T90: 37925 | U90: keomonyclever@gmail.com | V90: 생년월일 일치, 이메일 일치, 이름 유사도 100, 이름 토큰 포함
A91: 45989.995 | B91: CHHORM SOVANROZA | D91: Male | E91: 36466 | F91: Cambodia | G91: University of health sciences | H91: Medical student | I91: =VLOOKUP(CLEAN(F91),'World Bank Categories'!$B$4:$C$220,2,FALSE) -> Middle income | J91: thomasroza66@gmail.com | K91: Main Congress Only | L91: July 2, July 3, July 4 | P91: Agree | Q91: 등록 | R91: bursary | S91: CHHORM Sovanroza | T91: 36466 | U91: thomasroza66@gmail.com | V91: 생년월일 일치, 이메일 일치, 이름 완전일치
A92: 45990.019 | B92: Socheata Sokun | D92: Female | E92: 37495 | F92: Cambodia | G92: University of Health Sciences | H92: Medical Student | I92: =VLOOKUP(CLEAN(F92),'World Bank Categories'!$B$4:$C$220,2,FALSE) -> Middle income | J92: socheatasokun08@gmail.com | K92: Main Congress Only | L92: July 2, July 3, July 4 | P92: Agree | Q92: 등록 | R92: bursary | S92: Socheata Sokun | T92: 37495 | U92: socheatasokun08@gmail.com | V92: 생년월일 일치, 이메일 일치, 이름 완전일치
A93: 45990.201 | B93: Mario botross zakaria gohar | D93: Male | E93: 32844 | F93: Egypt, Arab Rep. | G93: Quesna central hospital. | H93: Pharmacist | I93: =VLOOKUP(CLEAN(F93),'World Bank Categories'!$B$4:$C$220,2,FALSE) -> Middle income | J93: Mariobotross2@ gmail.com | K93: Pre-Conference + Main Congress | L93: June 29, June 30, July 1, July 2, July 3, July 4 | P93: Agree | Q93: 등록 | R93: bursary(신규) | S93: Mario Botros Zakaria | T93: 32844 | U93: Mariobotross2@Gmail.com | V93: 생년월일 일치, 이름 유사도 85
A94: 45991.081 | B94: SOKUN VANNYLA | D94: Female | E94: 38619 | F94: Cambodia | G94: International University | H94: Pharmacist Student | I94: =VLOOKUP(CLEAN(F94),'World Bank Categories'!$B$4:$C$220,2,FALSE) -> Middle income | J94: vanilapipi2@gmail.com | K94: Main Congress Only | L94: July 2, July 3, July 4 | M94: SOKUN SOCHEATA | P94: Agree | Q94: 등록 | R94: bursary | S94: Sokun Vannyla | T94: 38619 | U94: vanilapipi2@gmail.com | V94: 생년월일 일치, 이메일 일치, 이름 완전일치
A95: 45991.88 | B95: Hannah Meas | C95: 미어 한나 | D95: Female | E95: 38139 | F95: Cambodia | G95: International University (IU) | H95: Student | I95: =VLOOKUP(CLEAN(F95),'World Bank Categories'!$B$4:$C$220,2,FALSE) -> Middle income | J95: meashannah0106@gmail.com | K95: Main Congress Only | L95: July 1, July 2, July 3, July 4 | M95: I don’t bring any family members but i have my friends, her name is Vannila and Money | P95: Agree | Q95: 등록 | R95: bursary | S95: MEAS HANNAH | T95: 38139 | U95: meashannah0106@gmail.com | V95: 생년월일 일치, 이메일 일치, 이름 유사도 100, 이름 토큰 포함
A96: 45992.336 | B96: DAYANE GONÇALVES DA SILVA | C96: 다야네 | D96: Female | E96: 35248 | F96: Brazil | G96: MÉDICOS DE CRISTO | H96: REPRESENTANTE MISSÕES GRUPO LOCAL MDC BH | I96: =VLOOKUP(CLEAN(F96),'World Bank Categories'!$B$4:$C$220,2,FALSE) -> Middle income | J96: dayanew17@gmail.com | K96: Pre-Conference + Main Congress | L96: June 29, June 30, July 1, July 2, July 3, July 4 | P96: Agree | Q96: 등록 | R96: bursary | S96: DAYANE GONÇALVES DA SILVA | T96: 35248 | U96: dayanew17@gmail.com | V96: 생년월일 일치, 이메일 일치, 이름 완전일치
A97: 45993.612 | B97: BUDHA MANI DUNGANA | D97: Male | E97: 24838 | F97: Bhutan | G97: GREAT COMMISSION PROJECT | H97: COMMISSSIONER | I97: =VLOOKUP(CLEAN(F97),'World Bank Categories'!$B$4:$C$220,2,FALSE) -> Middle income | J97: benjiruth1968@gmail.com | K97: Pre-Conference Only | L97: June 30, July 1, July 2, July 3, July 4 | P97: Agree | Q97: 등록 | R97: bursary | S97: BUDHA MANI DUNGANA | T97: 24838 | U97: benjiruth1968@gmail.com | V97: 생년월일 일치, 이메일 일치, 이름 완전일치
A98: 45993.841 | B98: Tania Gahama Ineza | D98: Female | E98: 34383 | F98: Burundi | G98: Burundi Christian Medical and Dental Association | H98: Secretary | I98: =VLOOKUP(CLEAN(F98),'World Bank Categories'!$B$4:$C$220,2,FALSE) -> Low income | J98: gahamatania@gmail.com | K98: Pre-Conference + Main Congress | L98: June 29, June 30, July 1, July 2, July 3, July 4 | P98: Agree | Q98: 등록 | R98: bursary | S98: Tania Gahama Ineza | T98: 34383 | U98: gahamatania@gmail.com | V98: 생년월일 일치, 이메일 일치, 이름 완전일치
A99: 45994.137 | B99: KIM KYUNGJOONG | C99: 김경중 | D99: Male | E99: 30184 | F99: Korea, Rep. | G99: Mercy Medical Center Cambodia / OMF, CMF | H99: Gastroenterologist / Missionary | I99: =VLOOKUP(CLEAN(F99),'World Bank Categories'!$B$4:$C$220,2,FALSE) -> High income | J99: jabezkj@gmail.com | K99: Main Congress Only | L99: July 2, July 3, July 4 | P99: Agree | Q99: 등록 | R99: bursary | S99: KYUNGJOONG KIM | T99: 30184 | U99: jabezkj@gmail.com | V99: 생년월일 일치, 이메일 일치, 이름 유사도 100, 이름 토큰 포함
A100: 45994.547 | B100: Gerelmaa Jargalsaikhan | D100: Female | E100: 32386 | F100: Mongolia | G100: Agape Christian Hospital of Mongolia | H100: Dr / Surgeon | I100: =VLOOKUP(CLEAN(F100),'World Bank Categories'!$B$4:$C$220,2,FALSE) -> Middle income | J100: drgerelmaa@ubach.org | K100: Pre-Conference + Main Congress | L100: June 30, July 1, July 2, July 3, July 4 | P100: Agree | Q100: 등록 | R100: bursary | S100: Gerelmaa Jargalsaikhan | T100: 32386 | U100: drgerelmaa@ubach.org | V100: 생년월일 일치, 이메일 일치, 이름 완전일치
A101: 45994.894 | B101: Yameen Khan Younatan | D101: Male | E101: 35708 | F101: Pakistan | G101: Christian Medical Fellowship, Pakistan | H101: Coordinator | I101: =VLOOKUP(CLEAN(F101),'World Bank Categories'!$B$4:$C$220,2,FALSE) -> Middle income | J101: yameen.k1997@gmail.com | K101: Main Congress Only | L101: June 29, June 30, July 1, July 2, July 3, July 4 | P101: Agree | Q101: 등록 | R101: bursary | S101: Yameen Khan Younatan | T101: 35708 | U101: yameen.k1997@gmail.com | V101: 생년월일 일치, 이메일 일치, 이름 완전일치
A102: 45994.995 | B102: Ean Meylik | D102: Female | E102: 38389 | F102: Cambodia | G102: Norton University | H102: Student | I102: =VLOOKUP(CLEAN(F102),'World Bank Categories'!$B$4:$C$220,2,FALSE) -> Middle income | J102: meyli0602@gmail.com | K102: Main Congress Only | L102: July 1, July 2, July 3, July 4 | P102: Agree | Q102: 등록 | R102: bursary | S102: Ean Meylik | T102: 38389 | U102: meyli0602@gmail.com | V102: 생년월일 일치, 이메일 일치, 이름 완전일치
...

Sheet 가족단위명단
A2: 2인 가족 | B2: 3인 가족 | C2: 4인 가족 | D2: 5인 가족 | E2: 6인 가족 | F2: 합계
A3: =A4/2 -> 11 | B3: =B4/3 -> 7 | C3: =C4/4 -> 7 | D3: =D4/5 -> 1 | E3: =E4/6 -> 1 | F3: =SUM(A3:E3) -> 27 | G3: 가족 총 팀 수
A4: =SUMIF(P8:P1000,2) -> 22 | B4: =SUMIF(P8:P1000,3) -> 21 | C4: =SUMIF(P8:P1000,4) -> 28 | D4: =SUMIF(P8:P1000,5) -> 5 | E4: =SUMIF(P8:P1000,6) -> 6 | F4: =SUM(A4:E4) -> 82 | G4: 가족 총 인원 수
A6: =F4 -> 82
A8: Timestamp | B8: 1. Name As it appears on your passport | C8: 2. Name (Korean): | D8: 3. Gender: | E8: 4. Date of Birth: (MM-DD-YYYY) | F8: 5. Nationality As it appears on your passport | G8: 6. Affiliation School/Institution/Organization Name | H8: 7. Title/Position | I8: 8. World Bank Category Found on your Registration Tab | J8: 9. Email Address Must be the same email used for registration | K8: 10. ICMDA Event You Plan to Attend | L8: 11. Free Accommodation Request Dates | M8: 12. Accompanying Family Member(s)(Name/Gender/Relationship): Are you bringing family member(s)? If yes, please indicate how many will accompany you and provide their name, gender, and relationship (ex: 1, John Doe, male, husband, John_D@gmail.com) | N8: 동반자 전체 요악 | O8: 본인 포함 총 인원(가족 단위 경우만) | P8: 인원명 | Q8: 13. Consent for Personal Information Use I hereby consent to the collection and use of the personal information provided above for the purpose of evaluating my application for ICMDA free accommodation and for related communications. | R8: 등록판정 | S8: Paid | T8: 매칭된 godsends 이름 | U8: 매칭된 godsends 생년월일 | V8: 매칭된 godsends 이메일 | W8: 판정 근거 | X8: Column 1
A9: 45843.795 | B9: NZAME Yolande | D9: Female | E9: 21016 | F9: Gabon | G9: Gabon Medical Chrétien | H9: Membre | I9: =VLOOKUP(CLEAN(F9),'World Bank Categories'!$B$4:$C$220,2,FALSE) -> Middle income | J9: yolandenzame@gmail.com | K9: Main Congress Only | L9: June 29, June 30, July 1, July 2, July 3, July 4 | M9: Rebecca, féminin, fille, vierin.rebecca@hotmail.fr | N9: Rebecca [딸] | O9: 2명/ (자녀 1명) | P9: =VALUE(LEFT(O9,1)) -> 2 | Q9: Agree | R9: 등록 | S9: paid | T9: NZAME Yolande
A10: 45871.236 | B10: PAUL STEPHEN ATARO AYELLA | D10: Male | E10: 28186 | F10: Uganda | G10: ICMDA | H10: REGIONAL REPRESENTATIVE EAST AFRICA | I10: =VLOOKUP(CLEAN(F10),'World Bank Categories'!$B$4:$C$220,2,FALSE) -> Low income | J10: ATARODRPAPA@GMAIL.COM | K10: Student Conference + Main Congress | L10: June 29, June 30, July 1, July 2, July 3, July 4 | M10: ATARO JANE KARINA, FEMALE. ATARO NEEMA ANGIOLETTA, FEMALE DAUGHTERS | N10: ATARO JANE KARINA, FEMALE. ATARO NEEMA ANGIOLETTA, FEMALE DAUGHTERS 딸 2명 | O10: 3명/ (자녀 2명) | P10: =VALUE(LEFT(O10,1)) -> 3 | Q10: Agree | R10: 등록 | S10: bursary | T10: Paul Stephen Ataro Ayella | U10: 28186 | V10: atarodrpapa@gmail.com | W10: 생년월일 일치, 이메일 일치, 이름 완전일치
A11: 45883.567 | B11: PETER SATHIYANATHAN MICHEAL JOHN | D11: Male | E11: 28573 | F11: MALAYSIA | G11: HEALTHCARE CHRISTIAN FELLOWSHIP MALAYSIA | H11: DOCTOR | I11: =VLOOKUP(CLEAN(F11),'World Bank Categories'!$B$4:$C$220,2,FALSE) -> Middle income | J11: doctorpeter@hotmail.com | K11: Main Congress Only | L11: July 1, July 2, July 3, July 4 | M11: IRINE AARATHANA PETER SATHIYANATHAN, FEMALE, - 12 YEARS OLD DAUGHTER , doctorpeter@hotmail.com | N11: IRINE AARATHANA PETER SATHIYANATHAN [딸, 12세] | O11: 2명/ (자녀 1명) | P11: =VALUE(LEFT(O11,1)) -> 2 | Q11: Agree | R11: 등록 | S11: paid | T11: PETER SATHIYANATHAN MICHEAL JOHN | U11: 28573 | V11: doctorpeter@hotmail.com | W11: 생년월일 일치, 이메일 일치, 이름 완전일치
A12: 45895.305 | B12: Semby, Johan Kyung Hwa | D12: Male | E12: 24127 | F12: Sweden | G12: Linköping University/Linköping University Hospital Department of Opthalmology/ ICMDA Sweden | H12: Senior Consultant in Ophthalmology/ Leader, organizer for the delegation from ICMDA Sweden and Finland | I12: =VLOOKUP(CLEAN(F12),'World Bank Categories'!$B$4:$C$220,2,FALSE) -> High income | J12: johan.semby@gmail.com | K12: Pre-Conference + Main Congress | L12: June 29, June 30, July 1, July 2, July 3, July 4 | M12: 1, Joshua Semby, male, son, joshua.semby7@gmail.com | N12: Joshua Semby [아들] | O12: 2명/ (자녀 1명) | P12: =VALUE(LEFT(O12,1)) -> 2 | Q12: Agree | R12: 등록 | S12: paid | T12: Johan Kyung Hwa Semby | U12: 24492 | V12: johan.semby@gmail.com | W12: 이메일 일치, 이름 유사도 100, 이름 토큰 포함
A13: 45900.026 | B13: NURGUL MAMYROVA | D13: Female | E13: 29297 | F13: Kyrgyz Republic | G13: ICMDA | H13: Doctor | I13: =VLOOKUP(CLEAN(F13),'World Bank Categories'!$B$4:$C$220,2,FALSE) -> Middle income | J13: nurgulicmda@gmail.com | K13: Student Conference + Main Congress | L13: June 29, June 30, July 1, July 2, July 3, July 4 | M13: Yes: Simon Peter Nadeem-my husband, My Daughter-Shulmiyat Sarah Nadeem, and my son -Timothy Simon Nadeem) | N13: Simon Peter Nadeem [배우자(남편)] Shulmiyat Sarah Nadeem[딸, 18세] Timothy Simon Nadeem [아들, 13세] | O13: 4명/ (자녀 2명, 배우자 1명) | P13: =VALUE(LEFT(O13,1)) -> 4 | Q13: Agree | R13: 등록 | S13: paid | T13: Nurgul Mamyrova | U13: 29297 | V13: nurgulicmda@gmail.com | W13: 생년월일 일치, 이메일 일치, 이름 완전일치
A14: 45908.782 | B14: Diana | C14: Safina | D14: Female | E14: 30253 | F14: Russian Federation | G14: ICMDA | H14: Regional representative, Eurasia training administrator | I14: =VLOOKUP(CLEAN(F14),'World Bank Categories'!$B$4:$C$220,2,FALSE) -> High income | J14: diana.safina316@gmail.com | K14: Pre-Conference + Main Congress | L14: June 29, June 30, July 1, July 2, July 3, July 4 | M14: Daria Safina, female, daughter 13 years old | N14: Daria Safina [딸, 13세] | O14: 2명/ (자녀 1명) | P14: =VALUE(LEFT(O14,1)) -> 2 | Q14: Agree | R14: 등록 | S14: bursary | T14: Diana Safina | U14: 30253 | V14: diana.safina316@gmail.com | W14: 생년월일 일치, 이메일 일치, 이름 유사도 100
A15: 45918.29 | B15: Peter Fee | D15: Male | E15: 28989 | F15: United Kingdom | G15: Royal Belfast Children's Hospital, Belfast, UK | H15: Consultant Anaesthetist | I15: =VLOOKUP(CLEAN(F15),'World Bank Categories'!$B$4:$C$220,2,FALSE) -> High income | J15: peterfee@doctors.org.uk | K15: Pre-Conference + Main Congress | L15: June 29, June 30, July 1, July 2, July 3, July 4 | M15: 4: Kerry Fee, female, wife, thefees@me.com; Grace Fee, female, daughter; Joel Fee, male, son; Toby Fee, male, son. | N15: Kerry Fee [배우자(아내)] thefees@me.com Grace Fee [딸, 12세] Joel Fee [아들, 14세] Toby Fee [아들, 10세] | O15: 5명/ (자녀 3명, 배우자 1명) | P15: =VALUE(LEFT(O15,1)) -> 5 | Q15: Agree | R15: 등록 | S15: paid | T15: Peter Fee | U15: 28989 | V15: peterfee@doctors.org.uk | W15: 생년월일 일치, 이메일 일치, 이름 완전일치
A16: 45922.815 | B16: Greta Gamal Nazir Kross | D16: Female | E16: 30328 | F16: Egypt, Arab Rep. | G16: Cmf egypt | H16: Pediatric specialist (director of operations of cmf egypt) | I16: =VLOOKUP(CLEAN(F16),'World Bank Categories'!$B$4:$C$220,2,FALSE) -> Middle income | J16: gretagamal@hotmail.com | K16: Pre-Conference + Main Congress | L16: June 29, June 30, July 1, July 2, July 3, July 4 | M16: George robile,male,husband Jason george,male ,son Jenny george,female,daughter | N16: George robile [배우자(남편)] gretagamal@hotmail.com Jason george [아들, 13세] Jenny george [딸, 17세] | O16: 4명/ (자녀 2명, 배우자 1명) | P16: =VALUE(LEFT(O16,1)) -> 4 | Q16: Agree | R16: 등록 | S16: bursary | T16: Greta Gamal
A17: 45984.987 | B17: MASRA NGARMBAYE | D17: Male | E17: 31065 | F17: Chad | G17: ASSOCIATION DES MEDECINS ET DENTISTES CHRETIENS DU TCHAD- AMDCT | H17: DOCTOR MEMBER | I17: =VLOOKUP(CLEAN(F17),'World Bank Categories'!$B$4:$C$220,2,FALSE) -> Low income | J17: nmasra@yahoo.com | K17: Pre-Conference + Main Congress | L17: June 29, June 30, July 1, July 2, July 3, July 4 | M17: 1, Edith Dekoum Nelembaye, female, Wife, nmasra@yahoo.com 2, Manaseth Toulaboua Ngarmbaye, male, Son, nmasra@yahoo.com | N17: Edith Dekoum Nelembaye [배우자(아내)] Manaseth Toulaboua Ngarmbaye [아들, 2세] | O17: 3명/ (자녀 1명, 배우자 1명) | P17: =VALUE(LEFT(O17,1)) -> 3 | Q17: Agree | R17: 등록 | S17: bursary | T17: MASRA NGARMBAYE | U17: 31065 | V17: nmasra@yahoo.com | W17: 생년월일 일치, 이메일 일치, 이름 완전일치
A18: 45989.19 | B18: Sofako Améganvi EGLOH | D18: Male | E18: 29659 | F18: TOGO | G18: CMF TOGO | H18: Doctor | I18: =VLOOKUP(CLEAN(F18),'World Bank Categories'!$B$4:$C$220,2,FALSE) -> Low income | J18: esofak81@gmail.com | K18: Pre-Conference + Main Congress | L18: June 29, June 30, July 1, July 2, July 3, July 4 | M18: 1, Afi Kafui BANIBA ATOKO Epse EGLOH, Female, Spouse, kbaniba@gmail.com 2, Betsaleel Ewousika Améganvi EGLOH, Male, Child, esofak81@gmail.com | N18: Afi Kafui BANIBA ATOKO Epse EGLOH [배우자(아내)] Betsaleel Ewousika Améganvi EGLOH [자녀, 3세] | O18: 3명/ (자녀 1명, 배우자 1명) | P18: =VALUE(LEFT(O18,1)) -> 3 | Q18: Agree | R18: 등록 | S18: bursary | T18: Améganvi Sofako EGLOH | U18: 29659 | V18: esofak81@gmail.com | W18: 생년월일 일치, 이메일 일치, 이름 유사도 100, 이름 토큰 포함
A19: 45996.041 | B19: TRAY CHEAVKUN | D19: Male | E19: 32733 | F19: Cambodia | G19: Cambodian Christian Medical Fellowship | H19: Member | I19: =VLOOKUP(CLEAN(F19),'World Bank Categories'!$B$4:$C$220,2,FALSE) -> Middle income | J19: traykun@live.com | K19: Main Congress Only | L19: July 2, July 3, July 4 | M19: Yes my family, ANG SREYNIN, Female, wife, angsreynin@gmail.com and one daughter 3years old female. | N19: ANG SREYNIN [배우자(아내)] one daughter [딸, 3세] | O19: 3명/ (자녀 1명, 배우자 1명) | P19: =VALUE(LEFT(O19,1)) -> 3 | Q19: Agree | R19: 등록 | S19: bursary | T19: TRAY CHEAVKUN | U19: 32733 | V19: traykun@live.com | W19: 생년월일 일치, 이메일 일치, 이름 완전일치
A20: 46012.652 | B20: Gena kerollos dawood gerges | D20: Female | E20: 32980 | F20: Egypt, Arab Rep. | G20: CMF | H20: ENT specialist | I20: =VLOOKUP(CLEAN(F20),'World Bank Categories'!$B$4:$C$220,2,FALSE) -> Middle income | J20: genakerollos@gmail.com | K20: Pre-Conference + Main Congress | L20: June 29, June 30, July 1, July 2, July 3, July 4 | M20: Ramy nabil, male , husband, ramyzakharious@gmail.com + holy ramy, female , daughter, 11 years old + heaven ramy, female, daughter, 6 years old | N20: Ramy nabil [배우자(남편)] holy ramy [딸, 11세] heaven ramy [딸, 6세] | O20: 4명/ (자녀 2명, 배우자 1명) | P20: =VALUE(LEFT(O20,1)) -> 4 | Q20: Agree | R20: 등록 | S20: bursary | T20: Gena kerollos dawood gerges | U20: 32980 | V20: genakerollos@gmail.com | W20: 생년월일 일치, 이메일 일치, 이름 완전일치
A21: 46013.749 | B21: Donald Kafa | D21: Male | E21: 28068 | F21: Solomon Islands | G21: Oceania ICMDA | H21: Medical Doctor | I21: =VLOOKUP(CLEAN(F21),'World Bank Categories'!$B$4:$C$220,2,FALSE) -> Middle income | J21: kafadonald@gmail.com | K21: Pre-Conference + Main Congress | L21: June 29, June 30, July 1 | M21: Elnisha Donald Kafa, 13 year old Son, email: kafadonald@gmail.com | N21: Elnisha Donald Kafa [아들, 13세] | O21: 2명/ (자녀 1명) | P21: =VALUE(LEFT(O21,1)) -> 2 | Q21: Agree | R21: 등록 | S21: bursary | T21: Donald Kafa | U21: 28068 | V21: kafadonald@gmail.com | W21: 생년월일 일치, 이메일 일치, 이름 완전일치
A22: 46021.99 | B22: Priscilia Pratami Intan | D22: Female | E22: 33794 | F22: Indonesia | G22: CMDFI | H22: Saline Process Teamwork | I22: =VLOOKUP(CLEAN(F22),'World Bank Categories'!$B$4:$C$220,2,FALSE) -> Middle income | J22: priscilia.pratami.intan@gmail.com | K22: Pre-Conference + Main Congress | L22: June 29, June 30, July 1, July 2, July 3, July 4 | M22: 3, Rudy. S, male, husband, rudisetiawan883@gmail.com; Kara Jessica Joetan, female, daughter, priscilia.pratami.intan@gmail.com; Anya Kirana Joetan, female, daughter, priscilia.pratami.intan@gmail.com | N22: Rudy.S [배우자(남편)] Kara Jessica Joetan [딸, 3세] Anya Kirana Joetan [딸] | O22: 4명/ (자녀 2명, 배우자 1명) | P22: =VALUE(LEFT(O22,1)) -> 4 | Q22: Agree | R22: 등록 | S22: bursary | T22: Priscilia Pratami Intan | U22: 33794 | V22: priscilia.pratami.intan@gmail.com | W22: 생년월일 일치, 이메일 일치, 이름 완전일치
A23: 46022.752 | B23: PHOEM | C23: CHANTHEN | D23: Female | E23: 33802 | F23: Cambodia | G23: Cambodian Chrsitian Medical Fellowship | H23: Key Volunteer | I23: =VLOOKUP(CLEAN(F23),'World Bank Categories'!$B$4:$C$220,2,FALSE) -> Middle income | J23: drsam0701@gmail.com | K23: Main Congress Only | L23: July 1, July 2, July 3, July 4 | M23: yes, Limeng Lichi, female, Daughter, drsam0701@gmail.com | N23: Limeng Lichi [딸, 16세] | O23: 2명/ (자녀 1명) | P23: =VALUE(LEFT(O23,1)) -> 2 | Q23: Agree | R23: 등록 | S23: bursary | T23: Phoem Chanthen | U23: 33802 | V23: drsam0701@gmail.com | W23: 생년월일 일치, 이메일 일치, 이름 유사도 100
A24: 46023.099 | B24: Rani Dwi Cahyaniputri | D24: Female | E24: 31644 | F24: Indonesia | G24: Simore Ministry | H24: Director | I24: =VLOOKUP(CLEAN(F24),'World Bank Categories'!$B$4:$C$220,2,FALSE) -> Middle income | J24: rk.tulung@gmail.com | K24: Main Congress Only | L24: June 29, June 30, July 1, July 2, July 3, July 4 | M24: 2, Augustine Elizabeth Pattipeilohy/female/mother, Danzel Bezalel Tulung/male/son (8 months old baby) | N24: Augustine Elizabeth Pattipeilohy [모] Danzel Bezalel Tulung[아들, 0세] | O24: 3명/ (자녀 1명, 동반자 1명) | P24: =VALUE(LEFT(O24,1)) -> 3 | Q24: Agree | R24: 등록 | S24: bursary | T24: Rani Dwi Cahyaniputri | U24: 31644 | V24: rk.tulung@gmail.com | W24: 생년월일 일치, 이메일 일치, 이름 완전일치
A25: 46048.143 | B25: Jodi Wiles | D25: Female | E25: 29327 | F25: South Africa | G25: Christian Medical Fellowship South Africa | H25: National Executive Committee member | I25: =VLOOKUP(CLEAN(F25),'World Bank Categories'!$B$4:$C$220,2,FALSE) -> Middle income | J25: jodiwiles@gmail.com | K25: Main Congress Only | L25: July 1, July 2, July 3, July 4 | M25: 3: Michael Wiles, male, husband, michaelwiles@gmail.com; Amia Wiles, female, daughter (12 years old), jodiandmichaelwiles@gmail.com; Cayla Wiles, female, daughter (10 years old), jodiandmichaelwiles@gmail.com | N25: Michael Wiles [배우자(남편)] Amia Wiles [딸, 12세] Cayla Wiles [딸, 10세] | O25: 4명/ (자녀 2명, 배우자 1명) | P25: =VALUE(LEFT(O25,1)) -> 4 | Q25: Agree | R25: 등록 | S25: paid | T25: Jodi Wiles
A26: 46048.749 | B26: Phon Sophai | D26: Male | E26: 31397 | F26: Cambodia | G26: CCMF | H26: Medical doctor | I26: =VLOOKUP(CLEAN(F26),'World Bank Categories'!$B$4:$C$220,2,FALSE) -> Middle income | J26: uhs.sophai@gmail.com | K26: Main Congress Only | L26: July 1, July 2, July 3, July 4 | M26: 1, Dy Dalen, Female, Wife, 2, Phay Rattanak, Female, daughter. | N26: Dy Dalen [배우자(아내)] Phay Rattanak [딸, 7세] | O26: 3명/ (자녀 1명, 배우자 1명) | P26: =VALUE(LEFT(O26,1)) -> 3 | Q26: Agree | R26: 등록 | S26: bursary | T26: Phon Sophai | U26: 31397 | V26: uhs.sophai@gmail.com | W26: 생년월일 일치, 이메일 일치, 이름 완전일치
A27: 46052.179 | B27: Sybrand Johannes de Vaal | D27: Male | E27: 29271 | F27: South Africa | G27: CMF South Africa | H27: Dr | I27: =VLOOKUP(CLEAN(F27),'World Bank Categories'!$B$4:$C$220,2,FALSE) -> Middle income | J27: sjdevaal@gmail.com | K27: Pre-Conference + Main Congress | L27: June 30, July 1, July 2, July 3, July 4 | M27: 1, Celeste de Vaal, female, wife, celestedevaal@uct.ac.za 2, Nienke de Vaal, female, daughter, sjdevaal@gmail.com 3, Lira de Vaal, female, daughter, sjdevaal@gmail.com 4, Thandi de Vaal, daughter, sjdevaal@gmail.com 5, Ariana de Vaal, daughter, sjdevaal@gmail.com | N27: Celeste de Vaal [배우자(아내)] Nienke de Vaal [딸] Lira de Vaal [딸] Thandi de Vaal [딸] Ariana de Vaal [딸] | O27: 6명/ (자녀 5명, 배우자 1명) | P27: =VALUE(LEFT(O27,1)) -> 6 | Q27: Agree | R27: 등록 | S27: paid | T27: Sybrand Johannes de Vaal
A28: 46053.822 | B28: PHAM THI HUYEN | D28: Female | E28: 31669 | F28: Vietnam | G28: Hong phuc general hospital, Hai Phong, Vietnam | H28: Pharmacist | I28: =VLOOKUP(CLEAN(F28),'World Bank Categories'!$B$4:$C$220,2,FALSE) -> Middle income | J28: huyentrangshaloms@gmail.com | K28: Main Congress Only | L28: July 2, July 3, July 4 | M28: Nguyen Pham Viet An, son, huyentrangshaloms@gmail.com | N28: Nguyen Pham Viet An [아들] | O28: 2명/ (자녀 1명) | P28: =VALUE(LEFT(O28,1)) -> 2 | Q28: Agree | R28: 등록 | S28: bursary | T28: pham thi huyen | U28: 31669 | V28: huyentrangshaloms@gmail.com | W28: 생년월일 일치, 이메일 일치, 이름 완전일치
A29: 46090.384 | B29: Hamado | C29: Sawadogo | D29: Male | E29: 32873 | F29: Burkina Faso | G29: ICMDA | H29: Family Physician /RR | I29: =VLOOKUP(CLEAN(F29),'World Bank Categories'!$B$4:$C$220,2,FALSE) -> Low income | J29: hamadodavidsawadogo@gmail.com | K29: Pre-Conference + Main Congress | L29: June 29, June 30, July 1, July 2, July 3, July 4 | M29: May be my daughter Sawadogo Deogracias W. 5 year old Female | N29: Sawadogo Deogracias W [딸, 5세] | O29: 2명/ (자녀 1명) | P29: =VALUE(LEFT(O29,1)) -> 2 | Q29: Agree | R29: 등록 | S29: bursary | T29: HAMADO SAWADOGO | U29: 32873 | V29: hamadodavidsawadogo@gmail.com | W29: 생년월일 일치, 이메일 일치, 이름 유사도 100
A30: 46107.134 | B30: Jodi Isaacs Wiles | D30: Female | E30: 29327 | F30: South Africa | G30: UKZN/Queen Nandi Regional Hospital/CMF South Africa executive committee member | H30: Dr | I30: =VLOOKUP(CLEAN(F30),'World Bank Categories'!$B$4:$C$220,2,FALSE) -> Middle income | J30: jodiandmichaelwiles@gmail.com | K30: Main Congress Only | L30: July 2, July 3, July 4 | M30: 1, Michael Wiles, male, husband, jodiandmichaelwiles@gmail.com. 2. Amia Wiles, female, daughter, jodiandmichaelwiles@gmail.com, Cayla Wiles, female, daughter, jodiandmichaelwiles@gmail.com | N30: Amia Wiles (딸, 11세) Cayla Wiles (딸, 9세) | O30: 3명/ (자녀 2명) | P30: =VALUE(LEFT(O30,1)) -> 3 | Q30: Agree | R30: 등록 | S30: paid | T30: Jodi Wiles | U30: 29327 | V30: jodiwiles@gmail.com | W30: 생년월일 일치, 이름 일치
A31: 46122.73 | B31: KYUNGMIN JANG | C31: 장경민 | D31: Male | E31: 31381 | F31: Korea, Rep. | G31: His Hands On Africa (Rwanda) | H31: Dental Mission Director and Dental Surgeon | I31: =VLOOKUP(CLEAN(F31),'World Bank Categories'!$B$4:$C$220,2,FALSE) -> High income | J31: jang@hishandsonafrica.org | K31: Main Congress Only | L31: July 1, July 2, July 3, July 4 | M31: 3, MINHEE KIM(김민희), Female, Wife / CELINE JANG 장세린 (1 daughter, 7yrs) / Arin JANG 장아린 (2 daughter, 4 yrs) | N31: 김민희 (배우자) 장세린 (딸, 7세) 장하린(딸, 2세) | O31: 4명 / (자녀 2명, 배우자 1명) | P31: =VALUE(LEFT(O31,1)) -> 4 | Q31: Agree | R31: 등록 | S31: paid | T31: KYUNGMIN JANG | U31: 31117 | V31: jang@hishandsonafrica.org | W31: *갓샌즈 국가 Rwanda, 생년월일 불일치
A32: 46136.529 | B32: CHI MA | C32: N/A | D32: Female | E32: 31597 | F32: CHINA | G32: Peniel Church Muzha | H32: Doctor | I32: =VLOOKUP(CLEAN(F32),'World Bank Categories'!$B$4:$C$220,2,FALSE) -> Middle income | J32: mamachi07@gmail.com edgarwu@msn.com | K32: Pre-Conference + Main Congress | L32: June 29, June 30, July 1, July 2, July 3, July 4 | M32: PIN-HSIEN WU, male, husband, wu.edgar@gmail.com; EN-JIE WU, female, daughter, wu.edgar@gmail.com; EN-QI WU, male, son, wu.edgar@gmail.com | N32: PIN-HSIEN WU(배우자,남편) EN-JIE WU(딸) EN-QI WU(아들) | O32: 4명/ 자녀 2명, 배우자 1명 | P32: =VALUE(LEFT(O32,1)) -> 4 | Q32: Agree | R32: 등록 | S32: paid
A33: 46147.178 | B33: Helena Gomes | D33: Female | E33: 16387 | F33: Brazil | G33: CMF Brazil | H33: Mother accompanying applicant (Mireille Gomes) | I33: =VLOOKUP(CLEAN(F33),'World Bank Categories'!$B$4:$C$220,2,FALSE) -> Middle income | J33: gomesmibr@gmail.com | K33: Pre-Conference + Main Congress | L33: June 29, June 30, July 1, July 2, July 3, July 4 | M33: Mireille Gomes / Female / Daughter | N33: Mireille Gomes(딸) | O33: 2명(딸 1명) | P33: =VALUE(LEFT(O33,1)) -> 2 | Q33: Agree | R33: 등록 | S33: paid | T33: Helena Maria Freyesleben Silva de Miranda Gomes | U33: 16387 | V33: gomesmibr@gmail.com | W33: 이메일 일치; 이름 유사도 0.41; 생년월일 일치; Godsends row 1627; Payment Status=Paid; Amount=0 | X33: 720843
A34: 46163.633 | B34: MANOLITA JUNASA | D34: Female | E34: 21916 | F34: Philippines | G34: KAVOD Center for Special Persons | H34: Founder, Executive Director | I34: =VLOOKUP(CLEAN(F34),'World Bank Categories'!$B$4:$C$220,2,FALSE) -> Middle income | J34: mallette.p@gmail.com | K34: Main Congress Only | L34: June 29, June 30, July 1, July 2, July 3, July 4 | M34: 1, KYLE DAVID JUNASA, male, son, KyleDPJ518@gmail.com | N34: KYLE DAVID JUNASA(아들) | O34: 2명(아들 1명) | P34: =VALUE(LEFT(O34,1)) -> 2 | Q34: Agree | R34: 등록 | S34: paid | T34: MANOLITA JUNASA | U34: 21916 | V34: mallette.p@gmail.com | W34: 이메일 일치; 이름 유사도 1.00; 생년월일 일치; Godsends row 2459; Payment Status=Paid; Amount=1505 | X34: 725030
A35: 46163.637 | B35: KYLE DAVID JUNASA | D35: Male | E35: 34837 | F35: Philippines | G35: KAVOD Center for Special Persons | H35: Co-founder, Coach | I35: =VLOOKUP(CLEAN(F35),'World Bank Categories'!$B$4:$C$220,2,FALSE) -> Middle income | J35: mallette.p@gmail.com | K35: Main Congress Only | L35: June 29, June 30, July 1, July 2, July 3, July 4 | M35: 1, MANOLITA JUNASA, female, mother, mallette.p@gmail.com | N35: MANOLITA JUNASA(엄마) | O35: 2명(엄마 1명) | P35: =VALUE(LEFT(O35,1)) -> 2 | Q35: Agree | R35: 등록 | S35: paid | T35: MANOLITA JUNASA | U35: 21916 | V35: mallette.p@gmail.com | W35: 이메일 일치; 이름 유사도 0.56; 생년월일 불일치/없음; Godsends row 2459; Payment Status=Paid; Amount=1505 | X35: 725030

Sheet 개인 단위 명단
A2: =COUNTA(B5:B14621) -> 550 | B2: 자원봉사자, 지원팀, 중국팀 등은 포함 안 된 인원 | C2: Godsends 등록자 수 | D2: =COUNTIF(Q5:Q685,"등록") -> 550 | F2: Godsends 미등록자 수 | G2: =COUNTIF(Q5:Q2621,"미등록") -> 0 | I2: paid 완료 | J2: =COUNTA(R5:R14621) -> 550
A4: Timestamp | B4: 1. Name As it appears on your passport | C4: 2. Name (Korean): | D4: 3. Gender: | E4: 4. Date of Birth: (MM-DD-YYYY) | F4: 5. Nationality As it appears on your passport | G4: 6. Affiliation School/Institution/Organization Name | H4: 7. Title/Position | I4: 8. World Bank Category Found on your Registration Tab | J4: 9. Email Address Must be the same email used for registration | K4: 10. ICMDA Event You Plan to Attend | L4: 11. Free Accommodation Request Dates | M4: 12. Accompanying Family Member(s)(Name/Gender/Relationship): Are you bringing family member(s)? If yes, please indicate how many will accompany you and provide their name, gender, and relationship (ex: 1, John Doe, male, husband, John_D@gmail.com) | N4: 동반자 전체 요악 | O4: 본인 포함 총 인원(가족 단위 경우만) | P4: 13. Consent for Personal Information Use I hereby consent to the collection and use of the personal information provided above for the purpose of evaluating my application for ICMDA free accommodation and for related communications. | Q4: 등록판정 | R4: Paid | S4: 매칭된 godsends 이름 | T4: 매칭된 godsends 생년월일 | U4: 매칭된 godsends 이메일 | V4: 판정 근거 | W4: Column 1
A5: 45841.453 | B5: Elisa Mabel Galeano Gamarra | D5: Female | E5: 35614 | F5: Paraguay | G5: in the process of having an association in Paraguay | H5: doctor | I5: =VLOOKUP(CLEAN(F5),'World Bank Categories'!$B$4:$C$220,2,FALSE) -> Middle income | J5: elisamedoficial@gmail.com | K5: Pre-Conference + Main Congress | L5: June 29, June 30, July 1, July 2, July 3, July 4 | P5: Agree | Q5: 등록 | R5: bursary | S5: Elisa Mabel Galeano Gamarra
A6: 45853.25 | B6: Blessings Dendere | D6: Female | E6: 36458 | F6: Zimbabwe | G6: Christian Medical Fellowship | H6: Doctor | I6: =VLOOKUP(CLEAN(F6),'World Bank Categories'!$B$4:$C$220,2,FALSE) -> Middle income | J6: blessingszd@gmail.com | K6: Pre-Conference + Main Congress | L6: June 29, June 30, July 1, July 2, July 3, July 4 | P6: Agree | Q6: 등록 | R6: bursary | S6: Blessings Dendere
A7: 45859.287 | B7: Muhumuza Ndamage Stephen | C7: Not Korean | D7: Male | E7: 29178 | F7: Rwanda | G7: Rwanda Christian Medical and Dental Organization | H7: Head of Rwanda Christian Medical and a Dental Organization | I7: =VLOOKUP(CLEAN(F7),'World Bank Categories'!$B$4:$C$220,2,FALSE) -> Low income | J7: stephen20130@gmail.com | K7: Student Conference + Main Congress | L7: 46207 | P7: Agree | Q7: 등록 | R7: bursary | S7: Muhumuza Ndamage Stephen | T7: 29178 | U7: stephen20130@gmail.com | V7: 생년월일 일치, 이메일 일치, 이름 완전일치
A8: 45865.165 | B8: KILACH CAROLE JESANG | D8: Female | E8: 32229 | F8: Kenya | G8: CHRISTIAN MEDICAL FELLOWSHIP- KENYA | H8: Dr/Miss/ Regional Leader | I8: =VLOOKUP(CLEAN(F8),'World Bank Categories'!$B$4:$C$220,2,FALSE) -> Middle income | J8: carolejesang@gmail.com | K8: Pre-Conference + Main Congress | L8: June 29, June 30, July 1, July 2, July 3, July 4 | P8: Agree | Q8: 등록 | R8: paid | S8: KILACH CAROLE JESANG | T8: 32229 | U8: carolejesang@gmail.com | V8: 생년월일 일치, 이메일 일치, 이름 완전일치
A9: 45870.142 | B9: Aline Garcia Pereira | C9: Aline Garcia Pereira | D9: Female | E9: 32847 | F9: Brazil | G9: Uniasselvi (University)/ MDC -Medicos de Cristo | H9: I am student of Health Management (graduation). But I am also PHD | I9: =VLOOKUP(CLEAN(F9),'World Bank Categories'!$B$4:$C$220,2,FALSE) -> Middle income | J9: alinegpereira1@gmail.com | K9: Student Conference + Main Congress | L9: June 29, June 30, July 1, July 2, July 3, July 4 | P9: Agree | Q9: 등록 | R9: paid | S9: Aline Garcia Pereira | T9: 32847 | U9: alinegpereira1@gmail.com | V9: 생년월일 일치, 이메일 일치, 이름 완전일치
A10: 45874.23 | B10: Mugaba Proscovia Mujeere | D10: Female | E10: 28943 | F10: Uganda | G10: Uganda Christian Medical Fellowship (UCMF) | H10: Chairperson of UCMF National Executive Committee | I10: =VLOOKUP(CLEAN(F10),'World Bank Categories'!$B$4:$C$220,2,FALSE) -> Low income | J10: drprosiemm@gmail.com | K10: Main Congress Only | L10: June 30, July 1, July 2, July 3, July 4 | P10: Agree | Q10: 등록 | R10: bursary | S10: Proscovia Mujeere Mugaba
A11: 45875.633 | B11: Theodorus Hedwin Kadrianto | D11: Male | E11: 32327 | F11: Indonesia | G11: ICMDA | H11: AEO for East Asia, Southeast Asia, Oceania | I11: =VLOOKUP(CLEAN(F11),'World Bank Categories'!$B$4:$C$220,2,FALSE) -> Middle income | J11: theodorus.hedwin@icmda.net | K11: Pre-Conference + Main Congress | L11: June 29, June 30, July 1, July 2, July 3, July 4 | P11: Agree | Q11: 등록 | R11: paid | S11: Theodorus Hedwin Kadrianto | T11: 32327 | U11: theodorus.hedwin@icmda.net | V11: 생년월일 일치, 이메일 일치, 이름 완전일치
A12: 45890.989 | B12: Alina | D12: Female | E12: 36334 | F12: Belarus | G12: Belarussian CMF | H12: Ophtalmologist | I12: =VLOOKUP(CLEAN(F12),'World Bank Categories'!$B$4:$C$220,2,FALSE) -> Middle income | J12: kurdunap@gmail.com | K12: Main Congress Only | L12: June 29, June 30, July 1, July 2, July 3, July 4 | P12: Agree | Q12: 등록 | R12: bursary | S12: Alina Kurdun
A13: 45909.696 | B13: BENJAMIN DUBE | D13: Male | E13: 35302 | F13: ZIMBABWE | G13: NATIONAL UNIVERSITY OF SCIENCE AND TECHNOLOGY, ZIMBABWE | H13: Chairperson, NUST Christian Medical Fellowship (CMF) | I13: =VLOOKUP(CLEAN(F13),'World Bank Categories'!$B$4:$C$220,2,FALSE) -> Middle income | J13: benjiedube25@gmail.com | K13: Student Conference + Main Congress | L13: June 29, June 30, July 1, July 2, July 3, July 4 | P13: Agree | Q13: 등록 | R13: bursary | S13: DUBE BENJAMIN | T13: 35302 | U13: benjiedube25@gmail.com | V13: 생년월일 일치, 이메일 일치, 이름 유사도 100, 이름 토큰 포함
A14: 45918.575 | B14: Nakanjako | C14: Sharon | D14: Female | E14: 34006 | F14: Uganda | G14: Uganda Christian medical Fellowship | H14: Clinical psychologist | I14: =VLOOKUP(CLEAN(#REF!),'World Bank Categories'!$B$4:$C$220,2,FALSE) -> #REF! | J14: sharonnakanjako2023@gmail.com | K14: Pre-Conference + Main Congress | L14: June 29, June 30, July 1, July 2, July 3, July 4 | P14: Agree | Q14: 등록 | R14: bursary | S14: Sharon Nakanjako | T14: 34006 | U14: sharonnakanjako2023@gmail.com | V14: 생년월일 일치, 이메일 일치, 이름 유사도 100
A15: 45927.904 | B15: Christa Adeline | D15: Female | E15: 35457 | F15: Indonesia | G15: ICMDA | H15: Regional Representative for Southeast Asia | I15: =VLOOKUP(CLEAN(F15),'World Bank Categories'!$B$4:$C$220,2,FALSE) -> Middle income | J15: christa.adeline@icmda.net | K15: Pre-Conference + Main Congress | L15: June 30, July 1, July 2, July 3, July 4 | P15: Agree | Q15: 등록 | R15: paid | S15: Christa Adeline | T15: 35457 | U15: christa.adeline@icmda.net | V15: 생년월일 일치, 이메일 일치, 이름 완전일치
A16: 45927.984 | B16: Quacy Asheeke Grant | D16: Male | E16: 31257 | F16: Guyana | G16: Lausanne Movement Caribbean/ICMDA Guyana-Caribbean | H16: Regional Director (Lausanne Movement Caribbean) | I16: =VLOOKUP(CLEAN(F16),'World Bank Categories'!$B$4:$C$220,2,FALSE) -> High income | J16: qgrant@lausanne.org | K16: Main Congress Only | L16: June 29, June 30, July 1, July 2, July 3, July 4 | P16: Agree | Q16: 등록 | R16: bursary | S16: Quacy Asheeke Grant
A17: 45928.771 | B17: LOUIE BENJAMIN KWON BOU | D17: Male | E17: 38475 | F17: NEW ZEALAND | G17: University of Otago | H17: Medical Student | I17: =VLOOKUP(CLEAN(F17),'World Bank Categories'!$B$4:$C$220,2,FALSE) -> High income | J17: bklouie@outlook.com | K17: Pre-Conference + Main Congress | L17: June 29, June 30, July 1, July 2, July 3 | M17: 1, Yidao Chua, male, friend, yidaochua@gmail.com | P17: Agree | Q17: 등록 | R17: paid | S17: Benjamin Louie | T17: 38475 | U17: bklouie@outlook.com | V17: 생년월일 일치, 이메일 일치, 이름 유사도 100, 이름 토큰 포함
A18: 45929.067 | B18: Mohalenyane Matheko Mary | D18: Female | E18: 35435 | F18: Lesotho | G18: Senkatana Oncology Clinic | H18: Dr. | I18: =VLOOKUP(CLEAN(F18),'World Bank Categories'!$B$4:$C$220,2,FALSE) -> Middle income | J18: matheko.mohalenyane@gmail.com | K18: Pre-Conference + Main Congress | L18: June 29, June 30, July 1, July 2, July 3, July 4 | P18: Agree | Q18: 등록 | R18: bursary | S18: Matheko Mohalenyane | T18: 35435 | U18: matheko.mohalenyane@yahoo.com | V18: 생년월일 일치, 이름 유사도 100, 이름 토큰 포함
A19: 45930.648 | B19: Anitha David | D19: Female | E19: 25119 | F19: India | G19: Emmanuel Hospital Association | H19: Dentist | I19: =VLOOKUP(CLEAN(F19),'World Bank Categories'!$B$4:$C$220,2,FALSE) -> Middle income | J19: Anitha.David@icmda.net | K19: Pre-Conference + Main Congress | L19: June 29, June 30, July 1, July 2, July 3, July 4 | P19: Agree | Q19: 등록 | R19: bursary | S19: Anitha David | T19: 25119 | U19: Anitha.David@imcda.net
A20: 45932.036 | B20: Abiyu Tadesse Fulea | C20: Kim | D20: Male | E20: 31339 | F20: Ethiopia | G20: CMF Ethiopia | H20: CMF Ethiopia chairperson | I20: =VLOOKUP(CLEAN(F20),'World Bank Categories'!$B$4:$C$220,2,FALSE) -> Low income | J20: martabiyju@gmail.com | K20: Pre-Conference + Main Congress | L20: June 29, June 30, July 1, July 2, July 3, July 4 | P20: Agree | Q20: 등록 | R20: bursary | S20: Abiyu Tadesse Fulea | T20: 31339 | U20: martabiyju@gmail.com | V20: 생년월일 일치, 이메일 일치, 이름 완전일치
A21: 45933.674 | B21: Kezia Christina Viani Wijaya | C21: 케지아 크리스티나 비아니 위자야 | D21: Female | E21: 36659 | F21: Indonesia | G21: CMDA Indonesia | H21: Member | I21: =VLOOKUP(CLEAN(F21),'World Bank Categories'!$B$4:$C$220,2,FALSE) -> Middle income | J21: keziawij@gmail.com | K21: Main Congress Only | L21: July 1, July 2, July 3, July 4 | P21: Agree | Q21: 등록 | R21: bursary | S21: Kezia Christina Viani Wijaya | T21: 36659 | U21: keziawij@gmail.com | V21: 생년월일 일치, 이메일 일치, 이름 완전일치
A22: 45943.156 | B22: Enimil Anthony Kwame | D22: Male | E22: 26224 | F22: Ghana | G22: Kwame Nkrumah University of Science and Technology | H22: Professor/Lecturer | I22: =VLOOKUP(CLEAN(F22),'World Bank Categories'!$B$4:$C$220,2,FALSE) -> Middle income | J22: Tonash@gmail.com | K22: Pre-Conference + Main Congress | L22: June 29, June 30, July 1, July 2, July 3, July 4 | M22: Helena Enimil, Female , Spouse | P22: Agree | Q22: 등록 | R22: Paid | S22: Anthony Enimil | T22: 26224 | U22: tonash@gmail.com | V22: 생년월일 일치, 이메일 일치, 이름 유사도 100, 이름 토큰 포함
A23: 45946.597 | B23: Alina Istrati | D23: Female | E23: 37372 | F23: Romania | G23: Nicolae Testemiţanu Moldova State University of Medicine and Pharmacy | H23: Student | I23: =VLOOKUP(CLEAN(F23),'World Bank Categories'!$B$4:$C$220,2,FALSE) -> High income | J23: istratialina16@gmail.com | K23: Pre-Conference + Main Congress | L23: June 29, June 30, July 1, July 2, July 3, July 4 | P23: Agree | Q23: 등록 | R23: bursary | S23: Istrati Alina | T23: 37372 | U23: istratialina16@gmail.com | V23: 생년월일 일치, 이메일 일치, 이름 유사도 100, 이름 토큰 포함
A24: 45947.179 | B24: HERVE TISTOU HITIMANA | D24: Male | E24: 33297 | F24: Burundi | G24: BCMDA | H24: Dr | I24: =VLOOKUP(CLEAN(F24),'World Bank Categories'!$B$4:$C$220,2,FALSE) -> Low income | J24: h.tistou@gmail.com | K24: Pre-Conference + Main Congress | L24: June 29, June 30, July 1, July 2, July 3, July 4 | P24: Agree | Q24: 등록 | R24: bursary | S24: HERVE TISTOU HITIMANA | T24: 33297 | U24: h.tistou@gmail.com | V24: 생년월일 일치, 이메일 일치, 이름 완전일치
A25: 45947.313 | B25: OKONGO BERFINA | D25: Female | E25: 36417 | F25: Senegal | G25: Association des médecins et dentistes chrétiens du Sénégal | H25: Treasury | I25: =VLOOKUP(CLEAN(F25),'World Bank Categories'!$B$4:$C$220,2,FALSE) -> Middle income | J25: O.berfina1@gmail.com | K25: Pre-Conference + Main Congress | L25: June 29, June 30, July 1, July 2, July 3, July 4 | P25: Agree | Q25: 등록 | R25: bursary | S25: OKONGO Berfina | T25: 36417 | U25: O.berfina1@gmail.com | V25: 생년월일 일치, 이메일 일치, 이름 완전일치
A26: 45947.313 | B26: ADONONSI FEGNITI MAHUTON MARIELLE | D26: Female | E26: 37086 | F26: Benin | G26: Association des Médecins et Dentistes Chrétiens du Sénégal | H26: Student leader | I26: =VLOOKUP(CLEAN(F26),'World Bank Categories'!$B$4:$C$220,2,FALSE) -> Middle income | J26: mariellehy@gmail.com | K26: Pre-Conference + Main Congress | L26: June 29, June 30, July 1, July 2, July 3, July 4 | P26: Agree | Q26: 등록 | R26: bursary | S26: Marielle Adononsi | T26: 37086 | U26: mariellehy@gmail.com | V26: 생년월일 일치, 이메일 일치, 이름 유사도 100, 이름 토큰 포함
A27: 45947.313 | B27: Rebecca Biaye | D27: Female | E27: 33994 | F27: Senegal | G27: Association des médecins et dentistes chrétiens du Sénégal | H27: National president | I27: =VLOOKUP(CLEAN(F27),'World Bank Categories'!$B$4:$C$220,2,FALSE) -> Middle income | J27: rebiaye@gmail.com | K27: Pre-Conference + Main Congress | L27: June 29, June 30, July 1, July 2, July 3, July 4 | P27: Agree | Q27: 등록 | R27: bursary | S27: Rebecca Biaye | T27: 33994 | U27: rebiaye@gmail.com | V27: 생년월일 일치, 이메일 일치, 이름 완전일치
A28: 45948.297 | B28: OBO Yapo Gilles | D28: Male | E28: 34126 | F28: Côte d’Ivoire | G28: AMPCI | H28: Medical Officer | I28: =VLOOKUP(CLEAN(F28),'World Bank Categories'!$B$4:$C$220,2,FALSE) -> Middle income | J28: yapogilles@yahoo.fr | K28: Pre-Conference + Main Congress | L28: June 29, June 30, July 1, July 2, July 3, July 4 | P28: Agree | Q28: 등록 | R28: bursary | S28: OBO Yapo Gilles | T28: 34126 | U28: yapogilles@yahoo.fr | V28: 생년월일 일치, 이메일 일치, 이름 완전일치
A29: 45948.8 | B29: Nermin Botros Zakaria Gohar | C29: 네르민 | D29: Female | E29: 34099 | F29: Egypt, Arab Rep. | G29: Faculty of medicine menofia university | H29: Assistant lecturer | I29: =VLOOKUP(CLEAN(F29),'World Bank Categories'!$B$4:$C$220,2,FALSE) -> Middle income | J29: nermenbotros22@gmail.com | K29: Pre-Conference + Main Congress | L29: June 29, June 30, July 1, July 2, July 3, July 4 | P29: Agree | Q29: 등록 | R29: bursary | S29: Nermin botros zakaria | T29: 34099 | U29: nermenbotros22@gmail.com | V29: 생년월일 일치, 이메일 일치, 이름 유사도 100, 이름 토큰 포함
A30: 45949.129 | B30: Nancy Botros Zakria Gohar | D30: Female | E30: 36381 | F30: Egypt, Arab Rep. | G30: Benha university hospital | H30: Cardiothoracic surgery resident | I30: =VLOOKUP(CLEAN(F30),'World Bank Categories'!$B$4:$C$220,2,FALSE) -> Middle income | J30: nancybotros161@gmail.com | K30: Pre-Conference + Main Congress | L30: June 29, June 30, July 1, July 2, July 3, July 4 | P30: Agree | Q30: 등록 | R30: bursary | S30: Nancy Botros Zakria Gohar | T30: 36381 | U30: nancybotros161@gmail.com | V30: 생년월일 일치, 이메일 일치, 이름 완전일치
A31: 45949.232 | B31: Bodoua Adjo Anne-Mireille | D31: Female | E31: 37412 | F31: Côte d’Ivoire | G31: AMPCI | H31: Medical student | I31: =VLOOKUP(CLEAN(F31),'World Bank Categories'!$B$4:$C$220,2,FALSE) -> Middle income | J31: bodouaanno@gmail.com | K31: Pre-Conference + Main Congress | L31: June 29, June 30, July 1, July 2, July 3, July 4 | P31: Agree | Q31: 등록 | R31: bursary | S31: Bodoua Adjo Anne-Mireille | T31: 37412 | U31: bodouaanno@gmail.com | V31: 생년월일 일치, 이메일 일치, 이름 완전일치
A32: 45950.126 | B32: Kupualor David Akwafo | D32: Male | E32: 28979 | F32: Ghana | G32: University of Ghana Medical Centre/St Joseph Hospital, Koforidua | H32: Senior Specialist | I32: =VLOOKUP(CLEAN(F32),'World Bank Categories'!$B$4:$C$220,2,FALSE) -> Middle income | J32: dkupualor@yahoo.com | K32: Pre-Conference + Main Congress | L32: June 29, June 30, July 1, July 2, July 3, July 4 | M32: Mrs Sarah Kupualor, Wife, marsar.asaa@yahoo.com | P32: Agree | Q32: 등록 | R32: paid | S32: David Akwafo Kupualor | T32: 28979 | U32: dkupualor@yahoo.com | V32: 생년월일 일치, 이메일 일치, 이름 유사도 100, 이름 토큰 포함
A33: 45950.134 | B33: Uhunmwangho Courage Ukponmwan | D33: Male | E33: 27390 | F33: Nigeria | G33: ICMDA West Africa | H33: Regional Secretary | I33: =VLOOKUP(CLEAN(F33),'World Bank Categories'!$B$4:$C$220,2,FALSE) -> Middle income | J33: ucourage@yahoo.com | K33: Pre-Conference + Main Congress | L33: June 29, June 30, July 1, July 2, July 3, July 4 | P33: Agree | Q33: 등록 | R33: bursary | S33: Courage Uhunmwangho | T33: 27390 | U33: ucourage@yahoo.com | V33: 생년월일 일치, 이메일 일치, 이름 유사도 100, 이름 토큰 포함
A34: 45951.22 | B34: IKEUBA DELIGHT CHIDEBELU | C34: Delight | D34: Male | E34: 38579 | F34: Nigeria | G34: Christian Medical and Dental Association | H34: Mr. | I34: =VLOOKUP(CLEAN(F34),'World Bank Categories'!$B$4:$C$220,2,FALSE) -> Middle income | J34: delightikeuba@gmail.com | K34: Pre-Conference + Main Congress | L34: June 30, July 1, July 2, July 3, July 4 | P34: Agree | Q34: 등록 | R34: bursary | S34: IKEUBA DELIGHT CHIDEBELU | T34: 38579 | U34: delightikeuba@gmail.com | V34: 생년월일 일치, 이메일 일치, 이름 완전일치
A35: 45952.287 | B35: ABASIRA TRINITY MUNGUFENI | D35: Male | E35: 35236 | F35: Uganda | G35: KING CEASOR UNIVERSITY, UGANDA CHRISTIAN MEDICAL FELLOWSHIP | H35: STUDENT | I35: =VLOOKUP(CLEAN(F35),'World Bank Categories'!$B$4:$C$220,2,FALSE) -> Low income | J35: tabasiramungufeni22ag@student.kcu.ac.ug | K35: Pre-Conference + Main Congress | L35: June 29, June 30, July 1, July 2, July 3, July 4 | P35: Agree | Q35: 등록 | R35: bursary | S35: Abasira Trinity Mungufeni | T35: 35236 | U35: tabasiramungufeni22ag@student.kcu.ac.ug | V35: 생년월일 일치, 이메일 일치, 이름 완전일치
A36: 45952.509 | B36: KUSONGA LABAN | D36: Male | E36: 37547 | F36: Uganda | G36: Kabale University/Uganda christian medical fellowship | H36: Student | I36: =VLOOKUP(CLEAN(F36),'World Bank Categories'!$B$4:$C$220,2,FALSE) -> Low income | J36: labkusonga20@gmail.com | K36: Pre-Conference + Main Congress | L36: June 29, June 30, July 1, July 2, July 3, July 4 | P36: Agree | Q36: 등록 | R36: bursary | S36: KUSONGA LABAN | T36: 37182 | U36: labkusonga20@gmail.com | V36: 이메일 일치, 이름 완전일치
A37: 45952.557 | B37: Jenniffer Laura Daltro Monteiro da Silva Loures | D37: Female | E37: 29011 | F37: Brazil | G37: Medicos de Cristo | H37: icmda Fieldworker Brazil Colombia and Venezuela | I37: =VLOOKUP(CLEAN(F37),'World Bank Categories'!$B$4:$C$220,2,FALSE) -> Middle income | J37: jldms1@gmail.com | K37: Pre-Conference + Main Congress | L37: June 29, June 30, July 1, July 2, July 3, July 4 | M37: Felipe Aleixo Loures ( husband) | P37: Agree | Q37: 등록 | R37: bursary | S37: jenniffer laura daltro monteiro da silva loures | T37: 29011 | U37: jldms1@gmail.com | V37: 생년월일 일치, 이메일 일치, 이름 완전일치
A38: 45952.74 | B38: Elita Theofani Juliawan | D38: Female | E38: 36498 | F38: Indonesia | G38: ICMDA | H38: Training track facilitator | I38: =VLOOKUP(CLEAN(F38),'World Bank Categories'!$B$4:$C$220,2,FALSE) -> Middle income | J38: elitatheofani@yahoo.co.id | K38: Pre-Conference + Main Congress | L38: June 30, July 1, July 2, July 3, July 4 | P38: Agree | Q38: 등록 | R38: paid | S38: Elita Theofani Juliawan | T38: 36498 | U38: elitatheofani@yahoo.co.id | V38: 생년월일 일치, 이메일 일치, 이름 완전일치
A39: 45952.832 | B39: NEMBA GRACE VAIBRA | D39: Female | E39: 37163 | F39: Chad | G39: ASSOCIATION DES MEDECINS ET DENTISTES CHRETIENS DU TCHAD(AMDCT) | H39: ETUDIANT | I39: =VLOOKUP(CLEAN(F39),'World Bank Categories'!$B$4:$C$220,2,FALSE) -> Low income | J39: gracevaibra777@gmail.com | K39: Pre-Conference + Main Congress | L39: June 29, June 30, July 1, July 2, July 3, July 4 | P39: Agree | Q39: 등록 | R39: bursary | S39: Nemba Grâce Vaibra | T39: 37163 | U39: gracevaibra777@gmail.com | V39: 생년월일 일치, 이메일 일치, 이름 완전일치
A40: 45952.89 | B40: Ika Septiana Eryani | D40: Female | E40: 34219 | F40: Indonesia | G40: Ministry of Health, Indonesia | H40: Health Administrator | I40: =VLOOKUP(CLEAN(F40),'World Bank Categories'!$B$4:$C$220,2,FALSE) -> Middle income | J40: trifosa.ikaseptiana@gmail.com | K40: Main Congress Only | L40: July 2, July 3, July 4 | P40: Agree | Q40: 등록 | R40: bursary | S40: Ika Septiana Eryani | T40: 34219 | U40: trifosa.ikaseptiana@gmail.com | V40: 생년월일 일치, 이메일 일치, 이름 완전일치
A41: 45952.99 | B41: Ansino Skyleth | D41: Female | E41: 35438 | F41: Philippines | G41: Bileg Community Outreach International | H41: Resident Physician | I41: =VLOOKUP(CLEAN(F41),'World Bank Categories'!$B$4:$C$220,2,FALSE) -> Middle income | J41: skyansinophi@gmail.com | K41: Main Congress Only | L41: July 2, July 3, July 4 | P41: Agree | Q41: 등록 | R41: bursary | S41: Skyleth Ansino | T41: 35438 | U41: skyansinophi@gmail.com | V41: 생년월일 일치, 이메일 일치, 이름 유사도 100, 이름 토큰 포함
A42: 45953.025 | B42: Jo Vee Java Dignadice | D42: Female | E42: 23483 | F42: Philippines | G42: ICMDA/MCCN | H42: Global Training Track Coordinator /Director | I42: =VLOOKUP(CLEAN(F42),'World Bank Categories'!$B$4:$C$220,2,FALSE) -> Middle income | J42: jov@doctor.com | K42: Pre-Conference + Main Congress | L42: June 29, June 30, July 1, July 2, July 3, July 4 | M42: Isa Berne J. Dignadice | P42: Agree | Q42: 등록 | R42: bursary | S42: Jo Vee Dignadice | T42: 22752 | U42: jov@doctor.com | V42: 이메일 일치, 이름 유사도 100, 이름 토큰 포함
A43: 45953.92 | B43: Finish Fernando | D43: Male | E43: 31262 | F43: Indonesia | G43: Bethesda Serukam Mission Hospital | H43: Vice Director | I43: =VLOOKUP(CLEAN(F43),'World Bank Categories'!$B$4:$C$220,2,FALSE) -> Middle income | J43: finish.fernando@gmail.com | K43: Main Congress Only | L43: June 29, June 30, July 1, July 2, July 3, July 4 | P43: Agree | Q43: 등록 | R43: bursary | S43: Finish Fernando | T43: 31262 | U43: finish.fernando@gmail.com | V43: 생년월일 일치, 이메일 일치, 이름 완전일치
A44: 45954.066 | B44: Lunkuse Henriettah Dungu | D44: Female | E44: 36855 | F44: Uganda | G44: Islamic University in Uganda | H44: Medical Doctor | I44: =VLOOKUP(CLEAN(F44),'World Bank Categories'!$B$4:$C$220,2,FALSE) -> Low income | J44: henriettahdungu@gmail.com | K44: Pre-Conference + Main Congress | L44: 46203 | P44: Agree | Q44: 등록 | R44: bursary | S44: Lunkuse Henriettah Dungu | T44: 36855 | U44: henriettahdungu@gmail.com | V44: 생년월일 일치, 이메일 일치, 이름 완전일치
A45: 45955.199 | B45: Melvar Kelly | D45: Female | E45: 36376 | F45: Kenya | G45: Moi University | H45: Student | I45: =VLOOKUP(CLEAN(F45),'World Bank Categories'!$B$4:$C$220,2,FALSE) -> Middle income | J45: Kellymelvar285@gmail.com | K45: Pre-Conference + Main Congress | L45: June 29, June 30, July 1, July 2, July 3, July 4 | P45: Agree | Q45: 등록 | R45: bursary | S45: Melvar Kelly | T45: 36376 | U45: kellymelvar285@gmail.com | V45: 생년월일 일치, 이메일 일치, 이름 완전일치
A46: 45957.162 | B46: OGUNGBANGBE OLUTOLA ESTHER | D46: Female | E46: 36253 | F46: NIGERIA | G46: ABIA STATE UNIVERSITY TEACHING HOSPITAL/CMDA NIGERIA | H46: SCHOOL WELFARE DIRECTOR/ SISTER'S COORDINATOR | I46: =VLOOKUP(CLEAN(F46),'World Bank Categories'!$B$4:$C$220,2,FALSE) -> Middle income | J46: estherogungbangbe.eo@gmail.com | K46: Pre-Conference + Main Congress | L46: June 29, June 30, July 1, July 2, July 3, July 4 | P46: Agree | Q46: 등록 | R46: Paid | S46: Ogungbangbe Olutola Esther | T46: 36253 | U46: estherogungbangbe.eo@gmail.com | V46: 생년월일 일치, 이메일 일치, 이름 완전일치
A47: 45957.261 | B47: IRIA DOMINION OSAYOMORE | D47: Male | E47: 35712 | F47: Nigeria | G47: Federal Medical Centre, Owo | H47: Doctor | I47: =VLOOKUP(CLEAN(F47),'World Bank Categories'!$B$4:$C$220,2,FALSE) -> Middle income | J47: iriadominion@gmail.com | K47: Pre-Conference + Main Congress | L47: June 29, June 30, July 1, July 2, July 3, July 4 | P47: Agree | Q47: 등록 | R47: bursary | S47: Dominion Iria | T47: 35712 | U47: iriadominion@gmail.com | V47: 생년월일 일치, 이메일 일치, 이름 유사도 100, 이름 토큰 포함
A48: 45957.284 | B48: LINGA, fidelis filibus | D48: Male | E48: 30098 | F48: Nigeria | G48: Federal Teaching Hospital, Gombe Gombe state | H48: Doctor, | I48: =VLOOKUP(CLEAN(F48),'World Bank Categories'!$B$4:$C$220,2,FALSE) -> Middle income | J48: drfillinga@gmail.com | K48: Pre-Conference + Main Congress | L48: June 29, June 30, July 1, July 2, July 3, July 4 | P48: Agree | Q48: 등록 | R48: bursary | S48: LINGA, Fidelis Filibus | T48: 30098 | U48: drfillinga@gmail.com | V48: 생년월일 일치, 이메일 일치, 이름 완전일치
A49: 45957.46 | B49: Paul Mayellawos Karuwa | D49: Male | E49: 35773 | F49: Nigeria | G49: CMDA-Nigeria, Kano State Chapter | H49: Dr. | I49: =VLOOKUP(CLEAN(F49),'World Bank Categories'!$B$4:$C$220,2,FALSE) -> Middle income | J49: ataschong@gmail.com | K49: Pre-Conference + Main Congress | L49: June 29, June 30, July 1, July 2, July 3, July 4 | P49: Agree | Q49: 등록 | R49: bursary | S49: PAUL MAYELLAWOS KARUWA | T49: 35773 | U49: ataschong@gmail.com | V49: 생년월일 일치, 이메일 일치, 이름 완전일치
A50: 45958.565 | B50: Adiyana Esti Purwaningrum | D50: Female | E50: 27940 | F50: Indonesia | G50: Indonesia Christian Medical and Dental Association | H50: Mission division team work | I50: =VLOOKUP(CLEAN(F50),'World Bank Categories'!$B$4:$C$220,2,FALSE) -> Middle income | J50: adienesti@gmail.com | K50: Pre-Conference + Main Congress | L50: June 30, July 1, July 2, July 3, July 4 | P50: Agree | Q50: 등록 | R50: bursary | S50: Adiyana Esti Purwaningrum | T50: 27940 | U50: adienesti@gmail.com | V50: 생년월일 일치, 이메일 일치, 이름 완전일치
A51: 45958.777 | B51: Etubi Alexander Ibrahim | D51: Male | E51: 31409 | F51: Nigeria | G51: University of Abuja Teaching Hospital/CMDA Nigeria | H51: Dr/ICMDA Regional Representative Anglophone west Africa/Deputy CEO 2 CMDA Nigeria | I51: =VLOOKUP(CLEAN(F51),'World Bank Categories'!$B$4:$C$220,2,FALSE) -> Middle income | J51: alexetubi28@gmail.com | K51: Pre-Conference + Main Congress | L51: June 29, June 30, July 1, July 2, July 3, July 4 | P51: Agree | Q51: 등록 | R51: bursary | S51: Etubi Alexander Ibrahim | T51: 31409 | U51: alexetubi28@gmail.com | V51: 생년월일 일치, 이메일 일치, 이름 완전일치
A52: 45958.989 | B52: LINDAEL GEOFREY MLAY | D52: Female | E52: 34612 | F52: Tanzania | G52: SANYA JUU LUTHERAN HEALTH CENTRE | H52: MEDICAL OFFICER IN CHARGE | I52: =VLOOKUP(CLEAN(F52),'World Bank Categories'!$B$4:$C$220,2,FALSE) -> Middle income | J52: mlaylinda4@gmail.com | K52: Pre-Conference + Main Congress | L52: 46202 | P52: Agree | Q52: 등록 | R52: bursary | S52: LINDAEL G MLAY | T52: 34612 | U52: mlaylinda4@gmail.com | V52: 생년월일 일치, 이메일 일치, 이름 유사도 92
A53: 45961.094 | B53: Cornel Martin Angolile | D53: Male | E53: 36016 | F53: Tanzania | G53: London School of Hygiene & Tropical Medicine | H53: Dr | I53: =VLOOKUP(CLEAN(F53),'World Bank Categories'!$B$4:$C$220,2,FALSE) -> Middle income | J53: cornelangolile@gmail.com | K53: Pre-Conference + Main Congress | L53: June 29, June 30, July 1, July 2, July 3, July 4 | P53: Agree | Q53: 등록 | R53: bursary | S53: Cornel Martin Angolile | T53: 36016 | U53: cornelangolile@gmail.com | V53: 생년월일 일치, 이메일 일치, 이름 완전일치
A54: 45962.907 | B54: Eric Kiprotich Langat | D54: Male | E54: 32013 | F54: Kenya | G54: Tenwek Mission Hospital | H54: Dr | I54: =VLOOKUP(CLEAN(F54),'World Bank Categories'!$B$4:$C$220,2,FALSE) -> Middle income | J54: ericlangat77@gmail.com | K54: Pre-Conference + Main Congress | L54: June 29, June 30, July 1, July 2, July 3, July 4 | P54: Agree | Q54: 등록 | R54: bursary | S54: Eric Kiprotich Langat
A55: 45964.77 | B55: Biira Eunice | D55: Female | E55: 37380 | F55: Uganda | G55: Kampala international university | H55: Student | I55: =VLOOKUP(CLEAN(F55),'World Bank Categories'!$B$4:$C$220,2,FALSE) -> Low income | J55: eunycebiira@gmail.com | K55: Pre-Conference + Main Congress | L55: June 29, June 30, July 1, July 2, July 3, July 4 | P55: Agree | Q55: 등록 | R55: bursary | S55: Biira Eunice | T55: 45781 | U55: eunycebiira@gmail.com | V55: 이메일 일치, 이름 완전일치
A56: 45965.191 | B56: Yao Mawuena DANSOU | D56: Male | E56: 28467 | F56: TOGO | G56: ICMDA | H56: Dr | I56: =VLOOKUP(CLEAN(F56),'World Bank Categories'!$B$4:$C$220,2,FALSE) -> Low income | J56: dansouyaomawuena@gmail.com | K56: Pre-Conference + Main Congress | L56: June 29, June 30, July 1, July 2, July 3, July 4 | P56: Agree | Q56: 등록 | R56: bursary | S56: Yao Mawuena DANSOU | T56: 28467 | U56: dansouyaomawuena@gmail.com | V56: 생년월일 일치, 이메일 일치, 이름 완전일치
A57: 45965.232 | B57: KADZAHLO KOMLA DOVENE | D57: Male | E57: 32128 | F57: TOGO | G57: National malaria control program of Togo | H57: Public health specialist | I57: =VLOOKUP(CLEAN(F57),'World Bank Categories'!$B$4:$C$220,2,FALSE) -> Low income | J57: tdkadzahlo@gmail.com | K57: Pre-Conference + Main Congress | L57: June 29, June 30, July 1, July 2, July 3, July 4 | P57: Agree | Q57: 등록 | R57: bursary | S57: Kadzahlo Komla Dovenè | T57: 32128 | U57: tdkadzahlo@gmail.com | V57: 생년월일 일치, 이메일 일치, 이름 완전일치
A58: 45965.377 | B58: SEKO Kudzovi Mario | D58: Male | E58: 34722 | F58: TOGO | G58: AMCT | H58: Doctor | I58: =VLOOKUP(CLEAN(F58),'World Bank Categories'!$B$4:$C$220,2,FALSE) -> Low income | J58: kudzovimarioseko@gmail.com | K58: Pre-Conference + Main Congress | L58: June 29, June 30, July 1, July 2, July 3, July 4 | P58: Agree | Q58: 등록 | R58: bursary | S58: SEKO Kudzovi Mario | T58: 34722 | U58: kudzovimarioseko@gmail.com | V58: 생년월일 일치, 이메일 일치, 이름 완전일치
A59: 45966.822 | B59: Frisyeni Amanda Mangule | D59: Female | E59: 38402 | F59: Indonesia | G59: Udayana Univercity | H59: Student | I59: =VLOOKUP(CLEAN(F59),'World Bank Categories'!$B$4:$C$220,2,FALSE) -> Middle income | J59: amandamangule05@gmail.com | K59: Pre-Conference + Main Congress | L59: June 29, June 30, July 1, July 2, July 3, July 4 | P59: Agree | Q59: 등록 | R59: bursary | S59: Frisyeni Amanda Mangule | T59: 38402 | U59: amandamangule05@gmail.com | V59: 생년월일 일치, 이메일 일치, 이름 완전일치
A60: 45969.15 | B60: BIGOGO HERBERT CHARLES | D60: Male | E60: 35695 | F60: Uganda | G60: UGANDA CHRISTIAN MEDICAL FELLOWSHIP (UCMF) | H60: NATIONAL EXECUTIVE- UCMF STUDENTS LIAISON SECRETARY | I60: =VLOOKUP(CLEAN(F60),'World Bank Categories'!$B$4:$C$220,2,FALSE) -> Low income | J60: herbertbigogo@gmail.com | K60: Pre-Conference + Main Congress | L60: June 29, June 30, July 1, July 2, July 3, July 4 | P60: Agree | Q60: 등록 | R60: bursary | S60: BIGOGO HERBERT CHARLES | T60: 35695 | U60: herbertbigogo@gmail.com | V60: 생년월일 일치, 이메일 일치, 이름 완전일치
A61: 45970.186 | B61: Kyabu Kapijimpanga | D61: Female | E61: 37575 | F61: Zambia | G61: Muğla Sıtkı Koçman University | H61: Medical student | I61: =VLOOKUP(CLEAN(F61),'World Bank Categories'!$B$4:$C$220,2,FALSE) -> Middle income | J61: Kyabukapiji4@gmail.com | K61: Pre-Conference + Main Congress | L61: June 29, June 30, July 1, July 2, July 3, July 4 | P61: Agree | Q61: 등록 | R61: bursary | S61: Kyabu Kapijimpanga | T61: 37575 | U61: Kyabukapiji4@gmail.com | V61: 생년월일 일치, 이메일 일치, 이름 완전일치
A62: 45971.841 | B62: ANDRIA BURI ANAK IBRAHIM | D62: Male | E62: 37385 | F62: MALAYSIA | G62: UNIVERSITY OF MALAYSIA, SARAWAK | H62: MEDICAL STUDENT | I62: =VLOOKUP(CLEAN(F62),'World Bank Categories'!$B$4:$C$220,2,FALSE) -> Middle income | J62: andriaburiibrahim@gmail.com | K62: Pre-Conference + Main Congress | L62: June 29, June 30, July 1, July 2, July 3, July 4 | P62: Agree | Q62: 등록 | R62: bursary | S62: Andria Buri anak Ibrahim
A63: 45972.18 | B63: ZOTCHI Komi | D63: Male | E63: 34699 | F63: TOGO | G63: AMCT (Togo) | H63: Docteur | I63: =VLOOKUP(CLEAN(F63),'World Bank Categories'!$B$4:$C$220,2,FALSE) -> Low income | J63: kzotchi94@gmail.com | K63: Pre-Conference + Main Congress | L63: June 29, June 30, July 1, July 2, July 3, July 4 | P63: Agree | Q63: 등록 | R63: bursary | S63: ZOTCHI Paulin | T63: 34699 | U63: kzotchi94@gmail.com | V63: 생년월일 일치, 이메일 일치
A64: 45975.852 | B64: ADAMU ADDISSIE NURAMO | D64: Male | E64: 26816 | F64: Ethiopia | G64: ADDIS ABABA UNIVERSITY and CMDDF-Ethiopia | H64: MD MPH | I64: =VLOOKUP(CLEAN(F64),'World Bank Categories'!$B$4:$C$220,2,FALSE) -> Low income | J64: adamu.addissie@aaau.edu.et | K64: Pre-Conference + Main Congress | L64: June 29, June 30, July 1, July 2, July 3, July 4 | P64: Agree | Q64: 등록 | R64: bursary | S64: ADAMU ADDISSIE NURAMO | T64: 26816 | U64: adamu.addissie@aau.edu.et | V64: 생년월일 일치, 이름 완전일치
A65: 45976.196 | B65: Samuel Subba | D65: Male | E65: 36840 | F65: Nepal | G65: Norvic International Hospital | H65: Medical Officer (House Officer) | I65: =VLOOKUP(CLEAN(F65),'World Bank Categories'!$B$4:$C$220,2,FALSE) -> Middle income | J65: samuelsubba@daum.net | K65: Pre-Conference + Main Congress | L65: June 29, June 30, July 1, July 2, July 3, July 4 | P65: Agree | Q65: 등록 | R65: bursary | S65: Samuel Subba
A66: 45979.593 | B66: Augustine Max Lyamarungu | D66: Male | E66: 35122 | F66: Tanzania | G66: CMDA Tanzania chapter | H66: Medical officer (MD) | I66: =VLOOKUP(CLEAN(F66),'World Bank Categories'!$B$4:$C$220,2,FALSE) -> Middle income | J66: agogomax.am@gmail.com | K66: Pre-Conference + Main Congress | L66: June 29, June 30, July 1, July 2, July 3, July 4 | P66: Agree | Q66: 등록 | R66: bursary | S66: Augustine Max Lyamarungu | T66: 35122 | U66: agogomax.am@gmail.com | V66: 생년월일 일치, 이메일 일치, 이름 완전일치
A67: 45981.656 | B67: Irakoze Christian | D67: Male | E67: 32586 | F67: Burundi | G67: Burundi Christian Medical and Dental Association | H67: Advisor, National Committee | I67: =VLOOKUP(CLEAN(F67),'World Bank Categories'!$B$4:$C$220,2,FALSE) -> Low income | J67: ichris255@gmail.com | K67: Pre-Conference + Main Congress | L67: June 29, June 30, July 1, July 2, July 3, July 4 | P67: Agree | Q67: 등록 | R67: bursary | S67: Christian Irakoze | T67: 32586 | U67: ichris255@gmail.com | V67: 생년월일 일치, 이메일 일치, 이름 유사도 100, 이름 토큰 포함
A68: 45982.754 | B68: Priyani Nelum Weerakoon | D68: Female | E68: 32684 | F68: Sri Lanka | G68: ICMDA | H68: Registered Nurse | I68: =VLOOKUP(CLEAN(F68),'World Bank Categories'!$B$4:$C$220,2,FALSE) -> Middle income | J68: 715nelumweerakoon@gmail.com | K68: Main Congress Only | L68: June 30, July 1, July 2, July 3, July 4 | P68: Agree | Q68: 등록 | R68: bursary | S68: Nelum Weerakoon | T68: 32684 | U68: 715nelumweerakoon@gmail.com | V68: 생년월일 일치, 이메일 일치, 이름 유사도 100, 이름 토큰 포함
A69: 45984.227 | B69: MALEKA Justice Illustre | C69: MALEKA Justice Illustre | D69: Male | E69: 33434 | F69: Congo,Rep. | G69: Medicals Sciences Superior Institute | H69: Doctor | I69: =VLOOKUP(CLEAN(F69),'World Bank Categories'!$B$4:$C$220,2,FALSE) -> Middle income | J69: justiceillustre@gmail.com | K69: Pre-Conference + Main Congress | L69: 46202 | P69: Agree | Q69: 등록 | R69: bursary | S69: MALEKA Justice Illustre | T69: 33434 | U69: justiceillustre@gmail.com | V69: 생년월일 일치, 이메일 일치, 이름 완전일치
A70: 45984.625 | B70: Alabi Favour Wealth | D70: Female | E70: 37776 | F70: Nigeria | G70: Bingham University Teaching Hospital, Jos | H70: School Academic Secretary of CMDA student arm BHUTH Chapter | I70: =VLOOKUP(CLEAN(F70),'World Bank Categories'!$B$4:$C$220,2,FALSE) -> Middle income | J70: Favouralabiwealth@gmail.com | K70: Pre-Conference + Main Congress | L70: June 29, June 30, July 1, July 2, July 3, July 4 | P70: Agree | Q70: 등록 | R70: Paid | S70: Alabi Favour | T70: 38142 | U70: Favouralabiwealth@gmail.com | V70: 이메일 일치, 이름 유사도 100, 이름 토큰 포함
A71: 45985.777 | B71: Moussa Oumarou | C71: Yacouba | D71: Male | E71: 36793 | F71: Nigeria | G71: AMPCN | H71: Leader Étudiant | I71: =VLOOKUP(CLEAN(F71),'World Bank Categories'!$B$4:$C$220,2,FALSE) -> Middle income | J71: yacouboum33@gmail.com | K71: Pre-Conference + Main Congress | L71: June 29, June 30, July 1, July 2, July 3, July 4 | P71: Agree | Q71: 등록 | R71: bursary | S71: Moussa Oumarou | T71: 36793 | U71: yacouboum33@gmail.com | V71: 생년월일 일치, 이메일 일치, 이름 완전일치
A72: 45985.853 | B72: MUPFASONI BELYSE | C72: MUPFASONI BELYSE | D72: Female | E72: 33868 | F72: Burundi | G72: UNIVERSITY OF NGOZI | H72: DR | I72: =VLOOKUP(CLEAN(F72),'World Bank Categories'!$B$4:$C$220,2,FALSE) -> Low income | J72: mupfasonib1@gmail.com | K72: Pre-Conference + Main Congress | L72: June 29, June 30, July 1, July 2, July 3, July 4 | P72: Agree | Q72: 등록 | R72: bursary | S72: MUPFASONI BELYSE | T72: 33868 | U72: mupfasonib1@gmail.com | V72: 생년월일 일치, 이메일 일치, 이름 완전일치
A73: 45988.082 | B73: Iryna Hushcha | D73: Female | E73: 33908 | F73: Belarus | G73: ICMDA | H73: Fieldworker | I73: =VLOOKUP(CLEAN(F73),'World Bank Categories'!$B$4:$C$220,2,FALSE) -> Middle income | J73: hushchairyna@gmail.com | K73: Main Congress Only | L73: june 30, July 1, July 2, July 3, July 4 | P73: Agree | Q73: 등록 | R73: bursary | S73: Iryna Hushcha | T73: 33908 | U73: hushchairyna@gmail.com | V73: 생년월일 일치, 이메일 일치, 이름 완전일치
A74: 45988.222 | B74: Timothy Tam | D74: Male | E74: 17098 | F74: Canada | G74: Christian Medical Dental association Canada | H74: Treasurer | I74: =VLOOKUP(CLEAN(F74),'World Bank Categories'!$B$4:$C$220,2,FALSE) -> High income | J74: timtamdmd@gmail.com | K74: Pre-Conference + Main Congress | L74: June 29, June 30, July 1, July 2, July 3, July 4 | M74: Remy Tam female and wife | P74: Agree | Q74: 등록 | R74: paid | S74: Timothy Tam | T74: 17098 | U74: timtamdmd@gmail.com | V74: 생년월일 일치, 이메일 일치, 이름 완전일치
A75: 45988.603 | B75: Mathew Santhosh Thomas | D75: Male | E75: 22235 | F75: India | G75: ICMDA | H75: Training in Charge | I75: =VLOOKUP(CLEAN(F75),'World Bank Categories'!$B$4:$C$220,2,FALSE) -> Middle income | J75: santhosh.mathew@icmda.net | K75: Pre-Conference + Main Congress | L75: June 29, June 30, July 1, July 2, July 3, July 4 | M75: 1 Saira Paulose, wife | P75: Agree | Q75: 등록 | R75: bursary | S75: Mathew Santhosh Thomas | T75: 22235 | U75: santhosh.mathew@icmda.net | V75: 생년월일 일치, 이메일 일치, 이름 완전일치
A76: 45989.837 | B76: Lucky Sarjono Buranda | D76: Male | E76: 33593 | F76: Indonesia | G76: Indonesia CMDF | H76: MD / Department of Mission | I76: =VLOOKUP(CLEAN(F76),'World Bank Categories'!$B$4:$C$220,2,FALSE) -> Middle income | J76: mdburanda@gmail.com | K76: Pre-Conference + Main Congress | L76: June 29, June 30, July 1, July 2, July 3, July 4 | P76: Agree | Q76: 등록 | R76: bursary | S76: Lucky Sarjono Buranda | T76: 33593 | U76: mdburanda@gmail.com | V76: 생년월일 일치, 이메일 일치, 이름 완전일치
A77: 45989.918 | B77: LAY LINHHAK | D77: Male | E77: 37852 | F77: Cambodia | G77: University Of Health Sciences | H77: Medical Student | I77: =VLOOKUP(CLEAN(F77),'World Bank Categories'!$B$4:$C$220,2,FALSE) -> Middle income | J77: linhhak213@gmail.com | K77: Main Congress Only | L77: July 1, July 2, July 3, July 4 | M77: Naro Sodavid, Male, Friend, narodavidktc@gmail.com | P77: Agree | Q77: 등록 | R77: bursary | S77: LAY LINHHAK | T77: 37852 | U77: linhhak213@gmail.com | V77: 생년월일 일치, 이메일 일치, 이름 완전일치
A78: 45989.92 | B78: Naro Sodavid | D78: Male | E78: 37875 | F78: Cambodia | G78: University of Health Sciences | H78: Medical student | I78: =VLOOKUP(CLEAN(F78),'World Bank Categories'!$B$4:$C$220,2,FALSE) -> Middle income | J78: narodavidktc@gmail.com | K78: Main Congress Only | L78: July 1, July 2, July 3, July 4 | M78: Lay Linhhak ,male,friend, linhhak213@gmail.com | P78: Agree | Q78: 등록 | R78: bursary | S78: NARO SODAVID | T78: 37875 | U78: narodavidktc@gmail.com | V78: 생년월일 일치, 이메일 일치, 이름 완전일치
A79: 45989.953 | B79: CHHANGSOUR YMEY | D79: Male | E79: 38368 | F79: Cambodia | G79: University of health and sciences | H79: Medical students | I79: =VLOOKUP(CLEAN(F79),'World Bank Categories'!$B$4:$C$220,2,FALSE) -> Middle income | J79: meyboy77@gmail.com | K79: Main Congress Only | L79: July 1, July 2, July 3, July 4 | P79: Agree | Q79: 등록 | R79: bursary | S79: ChhangSour Ymey | T79: 38368 | U79: meyboy77@gmail.com | V79: 생년월일 일치, 이메일 일치, 이름 완전일치
A80: 45989.954 | B80: TOUCH KEOMONEY | D80: Female | E80: 37925 | F80: Cambodia | G80: University of Health and Sciences | H80: Student | I80: =VLOOKUP(CLEAN(F80),'World Bank Categories'!$B$4:$C$220,2,FALSE) -> Middle income | J80: keomonyclever@gmail.com | K80: Main Congress Only | L80: July 1, July 2, July 3, July 4 | P80: Agree | Q80: 등록 | R80: bursary | S80: KEOMONEY TOUCH | T80: 37925 | U80: keomonyclever@gmail.com | V80: 생년월일 일치, 이메일 일치, 이름 유사도 100, 이름 토큰 포함
A81: 45989.995 | B81: CHHORM SOVANROZA | D81: Male | E81: 36466 | F81: Cambodia | G81: University of health sciences | H81: Medical student | I81: =VLOOKUP(CLEAN(F81),'World Bank Categories'!$B$4:$C$220,2,FALSE) -> Middle income | J81: thomasroza66@gmail.com | K81: Main Congress Only | L81: July 2, July 3, July 4 | P81: Agree | Q81: 등록 | R81: bursary | S81: CHHORM Sovanroza | T81: 36466 | U81: thomasroza66@gmail.com | V81: 생년월일 일치, 이메일 일치, 이름 완전일치
A82: 45990.019 | B82: Socheata Sokun | D82: Female | E82: 37495 | F82: Cambodia | G82: University of Health Sciences | H82: Medical Student | I82: =VLOOKUP(CLEAN(F82),'World Bank Categories'!$B$4:$C$220,2,FALSE) -> Middle income | J82: socheatasokun08@gmail.com | K82: Main Congress Only | L82: July 2, July 3, July 4 | P82: Agree | Q82: 등록 | R82: bursary | S82: Socheata Sokun | T82: 37495 | U82: socheatasokun08@gmail.com | V82: 생년월일 일치, 이메일 일치, 이름 완전일치
A83: 45990.201 | B83: Mario botross zakaria gohar | D83: Male | E83: 32844 | F83: Egypt, Arab Rep. | G83: Quesna central hospital. | H83: Pharmacist | I83: =VLOOKUP(CLEAN(F83),'World Bank Categories'!$B$4:$C$220,2,FALSE) -> Middle income | J83: Mariobotross2@ gmail.com | K83: Pre-Conference + Main Congress | L83: June 29, June 30, July 1, July 2, July 3, July 4 | P83: Agree | Q83: 등록 | R83: bursary(신규) | S83: Mario Botros Zakaria | T83: 32844 | U83: Mariobotross2@Gmail.com | V83: 생년월일 일치, 이름 유사도 85
A84: 45991.081 | B84: SOKUN VANNYLA | D84: Female | E84: 38619 | F84: Cambodia | G84: International University | H84: Pharmacist Student | I84: =VLOOKUP(CLEAN(F84),'World Bank Categories'!$B$4:$C$220,2,FALSE) -> Middle income | J84: vanilapipi2@gmail.com | K84: Main Congress Only | L84: July 2, July 3, July 4 | M84: SOKUN SOCHEATA | P84: Agree | Q84: 등록 | R84: bursary | S84: Sokun Vannyla | T84: 38619 | U84: vanilapipi2@gmail.com | V84: 생년월일 일치, 이메일 일치, 이름 완전일치
A85: 45991.88 | B85: Hannah Meas | C85: 미어 한나 | D85: Female | E85: 38139 | F85: Cambodia | G85: International University (IU) | H85: Student | I85: =VLOOKUP(CLEAN(F85),'World Bank Categories'!$B$4:$C$220,2,FALSE) -> Middle income | J85: meashannah0106@gmail.com | K85: Main Congress Only | L85: July 1, July 2, July 3, July 4 | M85: I don’t bring any family members but i have my friends, her name is Vannila and Money | P85: Agree | Q85: 등록 | R85: bursary | S85: MEAS HANNAH | T85: 38139 | U85: meashannah0106@gmail.com | V85: 생년월일 일치, 이메일 일치, 이름 유사도 100, 이름 토큰 포함
A86: 45992.336 | B86: DAYANE GONÇALVES DA SILVA | C86: 다야네 | D86: Female | E86: 35248 | F86: Brazil | G86: MÉDICOS DE CRISTO | H86: REPRESENTANTE MISSÕES GRUPO LOCAL MDC BH | I86: =VLOOKUP(CLEAN(F86),'World Bank Categories'!$B$4:$C$220,2,FALSE) -> Middle income | J86: dayanew17@gmail.com | K86: Pre-Conference + Main Congress | L86: June 29, June 30, July 1, July 2, July 3, July 4 | P86: Agree | Q86: 등록 | R86: bursary | S86: DAYANE GONÇALVES DA SILVA | T86: 35248 | U86: dayanew17@gmail.com | V86: 생년월일 일치, 이메일 일치, 이름 완전일치
A87: 45993.612 | B87: BUDHA MANI DUNGANA | D87: Male | E87: 24838 | F87: Bhutan | G87: GREAT COMMISSION PROJECT | H87: COMMISSSIONER | I87: =VLOOKUP(CLEAN(F87),'World Bank Categories'!$B$4:$C$220,2,FALSE) -> Middle income | J87: benjiruth1968@gmail.com | K87: Pre-Conference Only | L87: June 30, July 1, July 2, July 3, July 4 | P87: Agree | Q87: 등록 | R87: bursary | S87: BUDHA MANI DUNGANA | T87: 24838 | U87: benjiruth1968@gmail.com | V87: 생년월일 일치, 이메일 일치, 이름 완전일치
A88: 45993.841 | B88: Tania Gahama Ineza | D88: Female | E88: 34383 | F88: Burundi | G88: Burundi Christian Medical and Dental Association | H88: Secretary | I88: =VLOOKUP(CLEAN(F88),'World Bank Categories'!$B$4:$C$220,2,FALSE) -> Low income | J88: gahamatania@gmail.com | K88: Pre-Conference + Main Congress | L88: June 29, June 30, July 1, July 2, July 3, July 4 | P88: Agree | Q88: 등록 | R88: bursary | S88: Tania Gahama Ineza | T88: 34383 | U88: gahamatania@gmail.com | V88: 생년월일 일치, 이메일 일치, 이름 완전일치
A89: 45994.137 | B89: KIM KYUNGJOONG | C89: 김경중 | D89: Male | E89: 30184 | F89: Korea, Rep. | G89: Mercy Medical Center Cambodia / OMF, CMF | H89: Gastroenterologist / Missionary | I89: =VLOOKUP(CLEAN(F89),'World Bank Categories'!$B$4:$C$220,2,FALSE) -> High income | J89: jabezkj@gmail.com | K89: Main Congress Only | L89: July 2, July 3, July 4 | P89: Agree | Q89: 등록 | R89: bursary | S89: KYUNGJOONG KIM | T89: 30184 | U89: jabezkj@gmail.com | V89: 생년월일 일치, 이메일 일치, 이름 유사도 100, 이름 토큰 포함
A90: 45994.547 | B90: Gerelmaa Jargalsaikhan | D90: Female | E90: 32386 | F90: Mongolia | G90: Agape Christian Hospital of Mongolia | H90: Dr / Surgeon | I90: =VLOOKUP(CLEAN(F90),'World Bank Categories'!$B$4:$C$220,2,FALSE) -> Middle income | J90: drgerelmaa@ubach.org | K90: Pre-Conference + Main Congress | L90: June 30, July 1, July 2, July 3, July 4 | P90: Agree | Q90: 등록 | R90: bursary | S90: Gerelmaa Jargalsaikhan | T90: 32386 | U90: drgerelmaa@ubach.org | V90: 생년월일 일치, 이메일 일치, 이름 완전일치
A91: 45994.894 | B91: Yameen Khan Younatan | D91: Male | E91: 35708 | F91: Pakistan | G91: Christian Medical Fellowship, Pakistan | H91: Coordinator | I91: =VLOOKUP(CLEAN(F91),'World Bank Categories'!$B$4:$C$220,2,FALSE) -> Middle income | J91: yameen.k1997@gmail.com | K91: Main Congress Only | L91: June 29, June 30, July 1, July 2, July 3, July 4 | P91: Agree | Q91: 등록 | R91: bursary | S91: Yameen Khan Younatan | T91: 35708 | U91: yameen.k1997@gmail.com | V91: 생년월일 일치, 이메일 일치, 이름 완전일치
A92: 45994.995 | B92: Ean Meylik | D92: Female | E92: 38389 | F92: Cambodia | G92: Norton University | H92: Student | I92: =VLOOKUP(CLEAN(F92),'World Bank Categories'!$B$4:$C$220,2,FALSE) -> Middle income | J92: meyli0602@gmail.com | K92: Main Congress Only | L92: July 1, July 2, July 3, July 4 | P92: Agree | Q92: 등록 | R92: bursary | S92: Ean Meylik | T92: 38389 | U92: meyli0602@gmail.com | V92: 생년월일 일치, 이메일 일치, 이름 완전일치
A93: 45994.998 | B93: Eat Rithratana | D93: Male | E93: 38977 | F93: Cambodia | G93: Health Science Institute Of RCAF | H93: Student | I93: =VLOOKUP(CLEAN(F93),'World Bank Categories'!$B$4:$C$220,2,FALSE) -> Middle income | J93: ratanaeat270@gmail.com | K93: Main Congress Only | L93: July 1, July 2, July 3, July 4 | P93: Agree | Q93: 등록 | R93: bursary
A94: 45995.008 | B94: Sak Lyza | D94: Female | E94: 38508 | F94: Cambodia | G94: Norton University | H94: Student | I94: =VLOOKUP(CLEAN(F94),'World Bank Categories'!$B$4:$C$220,2,FALSE) -> Middle income | J94: saklyza970@gmail.com | K94: Main Congress Only | L94: July 1, July 2, July 3, July 4 | P94: Agree | Q94: 등록 | R94: bursary | S94: Sak Lyza | T94: 38508 | U94: saklyza970@gmail.com | V94: 생년월일 일치, 이메일 일치, 이름 완전일치
A95: 45997.913 | B95: Kpoughor Watchman | D95: Male | E95: 36956 | F95: Nigeria | G95: Jos University Teaching Hospital, Lamingo, Jos, Plateau State, Nigeria | H95: Mr | I95: =VLOOKUP(CLEAN(F95),'World Bank Categories'!$B$4:$C$220,2,FALSE) -> Middle income | J95: kpoughorw@gmail.com | K95: Pre-Conference + Main Congress | L95: June 29, June 30, July 1, July 2, July 3, July 4 | P95: Agree | Q95: 등록 | R95: bursary | S95: Kpoughor Watchman | T95: 36956 | U95: kpoughorw@gmail.com | V95: 생년월일 일치, 이메일 일치, 이름 완전일치
A96: 45999.921 | B96: Iveeltsetseg Gelegjamts | C96: 이웰체첵 | D96: Female | E96: 37314 | F96: Mongolia | G96: Ach medical university | H96: medical student | I96: =VLOOKUP(CLEAN(F96),'World Bank Categories'!$B$4:$C$220,2,FALSE) -> Middle income | J96: iveelxo@gmail.com | K96: Pre-Conference + Main Congress | L96: June 29, June 30, July 1, July 2, July 3, July 4 | P96: Agree | Q96: 등록 | R96: bursary | S96: Iveeltsetseg Gelegjamts | T96: 37314 | U96: iveelxo@gmail.com | V96: 생년월일 일치, 이메일 일치, 이름 완전일치
A97: 46001.294 | B97: Grishenok Alena | D97: Female | E97: 34048 | F97: Russian Federation | G97: ICMDA | H97: ICMDA Eurasia fieldworker (Russia) | I97: =VLOOKUP(CLEAN(F97),'World Bank Categories'!$B$4:$C$220,2,FALSE) -> High income | J97: alenamely@gmail.com | K97: Pre-Conference + Main Congress | L97: June 29, June 30, July 1, July 2, July 3, July 4 | P97: Agree | Q97: 등록 | R97: bursary | S97: Grishenok Alena
A98: 46001.703 | B98: NAOMI BATWEL LOTTO | C98: No | D98: Female | E98: 36638 | F98: Tanzania | G98: KCMC | H98: Laboratory Scientist | I98: =VLOOKUP(CLEAN(F98),'World Bank Categories'!$B$4:$C$220,2,FALSE) -> Middle income | J98: naomylotto2@gmail.com | K98: Pre-Conference + Main Congress | L98: June 29, June 30, July 1, July 2, July 3, July 4 | P98: Agree | Q98: 등록 | R98: bursary | S98: NAOMI BATWEL LOTTO | T98: 36638 | U98: naomylotto2@gmail.com | V98: 생년월일 일치, 이메일 일치, 이름 완전일치
A99: 46002.06 | B99: Dyhia ALLACHE | D99: Female | E99: 34207 | F99: Algeria | G99: Eph azazga maghnem lounis | H99: General practitioner | I99: =VLOOKUP(CLEAN(F99),'World Bank Categories'!$B$4:$C$220,2,FALSE) -> Middle income | J99: dy.allache@gmail.com | K99: Pre-Conference + Main Congress | L99: June 29, June 30, July 1, July 2, July 3, July 4 | P99: Agree | Q99: 등록 | R99: bursary | S99: Dyhia ALLACHE | T99: 34207 | U99: dy.allache@gmail.com | V99: 생년월일 일치, 이메일 일치, 이름 완전일치
A100: 46002.06 | B100: Jeremiah Abdul Akim Jalloh | D100: Male | E100: 36040 | F100: Sierra Leone | G100: Mohamed V University - Rabat, Morcco. | H100: Medical Intern | I100: =VLOOKUP(CLEAN(F100),'World Bank Categories'!$B$4:$C$220,2,FALSE) -> Low income | J100: jallohjeremiah@gmail.com | K100: Pre-Conference + Main Congress | L100: June 29, June 30, July 1, July 2, July 3, July 4 | P100: Agree | Q100: 등록 | R100: bursary | S100: Jeremiah Abdul Akim Jalloh | T100: 35835 | U100: jallohjeremiah@gmail.com | V100: 이메일 일치, 이름 완전일치
A101: 46006.693 | B101: Timothy Anton Anavhe Okhai | D101: Male | E101: 25932 | F101: South Africa | G101: Healthcare Christian Fellowship International | H101: Global Saline Coordinator | I101: =VLOOKUP(CLEAN(F101),'World Bank Categories'!$B$4:$C$220,2,FALSE) -> Middle income | J101: timokhai@yahoo.co.uk | K101: Pre-Conference + Main Congress | L101: June 29, June 30, July 1, July 2, July 3, July 4 | P101: Agree | Q101: 등록 | R101: bursary | S101: Timothy Anton Okhai | T101: 25932 | U101: timokhai@yahoo.co.uk | V101: 생년월일 일치, 이메일 일치, 이름 유사도 100, 이름 토큰 포함
A102: 46007.604 | B102: Kesanta Gift James | D102: Female | E102: 36554 | F102: Tanzania | G102: ICMDA Tanzanian chapter | H102: Active member | I102: =VLOOKUP(CLEAN(F102),'World Bank Categories'!$B$4:$C$220,2,FALSE) -> Middle income | J102: giftjkesa@gmail.com | K102: Pre-Conference + Main Congress | L102: June 29, June 30, July 1, July 2, July 3, July 4 | P102: Agree | Q102: 등록 | R102: bursary | S102: Gift Kesanta | T102: 36554 | U102: giftjkesa@gmail.com | V102: 생년월일 일치, 이메일 일치, 이름 유사도 100, 이름 토큰 포함
...

Sheet 노랑은 지난확정
A1: Timestamp | B1: 1. Name As it appears on your passport | C1: 2. Name (Korean): | D1: 3. Gender: | E1: 4. Date of Birth: (MM-DD-YYYY) | F1: 5. Nationality As it appears on your passport | G1: 6. Affiliation School/Institution/Organization Name | H1: 7. Title/Position | I1: 8. World Bank Category Found on your Registration Tab | J1: 9. Email Address Must be the same email used for registration | K1: 10. ICMDA Event You Plan to Attend | L1: 11. Free Accommodation Request Dates | M1: 12. Accompanying Family Member(s)(Name/Gender/Relationship): Are you bringing family member(s)? If yes, please indicate how many will accompany you and provide their name, gender, and relationship (ex: 1, John Doe, male, husband, John_D@gmail.com) | N1: 동반자 전체 요악 | O1: 본인 포함 총 인원(가족 단위 경우만) | P1: 13. Consent for Personal Information Use I hereby consent to the collection and use of the personal information provided above for the purpose of evaluating my application for ICMDA free accommodation and for related communications. | Q1: 등록판정 | R1: Paid | S1: 매칭된 godsends 이름 | T1: 매칭된 godsends 생년월일 | U1: 매칭된 godsends 이메일 | V1: 판정 근거 | W1: Column 1
A2: 45841.453 | B2: Elisa Mabel Galeano Gamarra | D2: Female | E2: 35614 | F2: Paraguay | G2: in the process of having an association in Paraguay | H2: doctor | I2: Middle income | J2: elisamedoficial@gmail.com | K2: Pre-Conference + Main Congress | L2: June 29, June 30, July 1, July 2, July 3, July 4 | P2: Agree | Q2: 등록 | R2: bursary | S2: Elisa Mabel Galeano Gamarra
A3: 45843.795 | B3: NZAME Yolande | D3: Female | E3: 21016 | F3: Gabon | G3: Gabon Medical Chrétien | H3: Membre | I3: Middle income | J3: yolandenzame@gmail.com | K3: Main Congress Only | L3: June 29, June 30, July 1, July 2, July 3, July 4 | M3: Rebecca, féminin, fille, vierin.rebecca@hotmail.fr | N3: Rebecca [딸] | O3: 2명/ (자녀 1명) | P3: Agree | Q3: 등록 | R3: paid | S3: NZAME Yolande
A4: 45846.76 | B4: KALIBBALA EMMANUEL | D4: Male | E4: 36912 | F4: UGANDA | G4: Gulu University | H4: Mr. | I4: Low income | J4: kalex122001@gmail.com | K4: Main Congress Only | L4: June 29, June 30, July 1, July 2, July 3, July 4 | P4: Agree | Q4: 등록 | S4: KALIBBALA EMMANUEL
A5: 45849.777 | B5: Edwin Njore Irungu | D5: Male | E5: 32541 | F5: Kenya | G5: PCEA Kikuyu Hospital | H5: Mr | I5: Middle income | J5: irunguedwin8@gmail.com | K5: Main Congress Only | L5: June 29, June 30, July 1, July 2, July 3, July 4 | P5: Agree | Q5: 미등록
A6: 45853.25 | B6: Blessings Dendere | D6: Female | E6: 36458 | F6: Zimbabwe | G6: Christian Medical Fellowship | H6: Doctor | I6: Middle income | J6: blessingszd@gmail.com | K6: Pre-Conference + Main Congress | L6: June 29, June 30, July 1, July 2, July 3, July 4 | P6: Agree | Q6: 등록 | R6: bursary | S6: Blessings Dendere
A7: 45856.25 | B7: Ilivieda Omamezi Annah | D7: Female | E7: 38134 | F7: Nigeria | G7: University of Ilorin | H7: Student | I7: Middle income | J7: omasax94@gmail.com | K7: Student Conference + Main Congress | L7: June 29, June 30, July 1, July 2, July 3, July 4 | P7: Agree | Q7: 미등록
A8: 45856.751 | B8: AGNESS SAIMON KASWAGA | D8: Female | E8: 37063 | F8: Tanzania | G8: KCMC | H8: MEDICAL DOCTOR | I8: Middle income | J8: Saimonagness58@gmail.com | K8: Main Congress Only | L8: June 29, June 30, July 1, July 2, July 3, July 4 | P8: Agree | Q8: 등록 | S8: AGNESS S KASWAGA | T8: 36698 | U8: Saimonagness58@gmail.com | V8: 이메일 일치, 이름 유사도 93
A9: 45857.619 | B9: Virginia Baraza Dangi | D9: Female | E9: 38314 | F9: Tanzania | G9: KCMC University | H9: Student | I9: Middle income | J9: vibaseche23@gmail.com | K9: Pre-Conference + Main Congress | L9: June 29, June 30, July 1, July 2, July 3, July 4 | P9: Agree | Q9: 등록 | S9: Virginia Baraza Dangi | T9: 38314 | U9: Vibaseche23@gmail.com | V9: 생년월일 일치, 이메일 일치, 이름 완전일치
A10: 45859.287 | B10: Muhumuza Ndamage Stephen | C10: Not Korean | D10: Male | E10: 29178 | F10: Rwanda | G10: Rwanda Christian Medical and Dental Organization | H10: Head of Rwanda Christian Medical and a Dental Organization | I10: Low income | J10: stephen20130@gmail.com | K10: Student Conference + Main Congress | L10: 46207 | P10: Agree | Q10: 등록 | R10: bursary | S10: Muhumuza Ndamage Stephen | T10: 29178 | U10: stephen20130@gmail.com | V10: 생년월일 일치, 이메일 일치, 이름 완전일치
A11: 45859.316 | B11: Modestin Nahimana | D11: Male | E11: 36278 | F11: Burundi | G11: Christian Medical Student Fellowship in Rwanda | H11: Member | I11: Low income | J11: modestin.nahimana@gmail.com | K11: Student Conference + Main Congress | L11: June 29, June 30, July 1, July 2, July 3, July 4 | P11: Agree | Q11: 미등록
A12: 45859.598 | B12: UWIMANA Kevine | D12: Female | E12: 37368 | F12: Rwanda | G12: Rwanda Christian medical and dental organization | H12: Student | I12: Low income | J12: kevineuwimana01@gmail.com | K12: Student Conference + Main Congress | L12: 46207 | Q12: 등록 | S12: Uwimana Kevine | T12: 37368 | U12: kevineuwimana01@gmail.com | V12: 생년월일 일치, 이메일 일치, 이름 완전일치
A13: 45859.6 | B13: Munezero Noella | D13: Female | E13: 35424 | F13: Rwanda | G13: Rwanda christian medical and dental organization | H13: Medical Doctor | I13: Low income | J13: Munono 25@gmail.com | K13: Pre-Conference + Main Congress | L13: June 29, June 30, July 1, July 2, July 3, July 4 | P13: Agree | Q13: 등록 | S13: Munezero Noella | T13: 35424 | U13: Munono25@gmail.com | V13: 생년월일 일치, 이름 완전일치
A14: 45859.616 | B14: Uwizeyimana Marie Grace | D14: Female | E14: 37239 | F14: Rwanda | G14: Rwanda Christian medical and dental organization | H14: Student | I14: Low income | J14: Umg | K14: Pre-Conference + Main Congress | L14: June 29, June 30, July 1, July 2, July 3, July 4 | P14: Agree | Q14: 미등록
A15: 45859.617 | B15: NIYOKWIZERWA Moise | D15: Male | E15: 37362 | F15: Rwanda | G15: Rwanda christian medical and dental organisation | H15: Student leader | I15: Low income | J15: niyokwizerwamoise910@gmail.com | K15: Pre-Conference + Main Congress | L15: 46207 | P15: Agree | Q15: 등록 | S15: Niyokwizerwa Moise | T15: 37362 | U15: niyokwizerwamoise910@gmail.com | V15: 생년월일 일치, 이메일 일치, 이름 완전일치
A16: 45859.624 | B16: NIYIREMA Olive | D16: Female | E16: 35154 | F16: Rwanda | G16: Affiliation is RWanda Christian Medical and Dental Organization Not CMSF RWanda Christian Medical and Dental Organization | H16: Doctor | I16: Low income | J16: olivenini2020@gmail.com | K16: Pre-Conference + Main Congress | L16: June 29, June 30, July 1, July 2, July 3, July 4 | P16: Agree | Q16: 등록 | S16: Olive NIYIREMA | T16: 35632 | U16: olivenini2020@gmail.com | V16: 이메일 일치, 이름 유사도 100, 이름 토큰 포함
A17: 45859.629 | B17: Tusahirwa innocent | D17: Male | E17: 37457 | F17: Rwanda | G17: Rwanda chritian medical and dental organisation | H17: Student's leader | I17: Low income | J17: tuzahirwainnocent@gmail.com | K17: Student Conference + Main Congress | L17: June 29, June 30, July 1, July 2, July 3, July 4 | P17: Agree | Q17: 미등록
A18: 45859.641 | B18: ISHIMWE Jacques | C18: ISHIMWE Jacques | D18: Male | E18: 37622 | F18: Rwanda | G18: Rwanda Christian Medical and Dental organization | H18: Student | I18: Low income | J18: asinathamukakarera@gmail.com | K18: Pre-Conference + Main Congress | L18: 46207 | P18: Agree | Q18: 등록 | S18: ISHIMWE Jacques | T18: 37622 | U18: asinathamukakarera@gmail.com | V18: 생년월일 일치, 이메일 일치, 이름 완전일치
A19: 45859.642 | B19: Uwingabire Marie Solange | D19: Female | E19: 38330 | F19: Rwanda | G19: University of Rwanda | H19: Student | I19: Low income | J19: uwingabiresolange19@gmail.com | K19: Student Conference + Main Congress | L19: June 29, June 30, July 1, July 2, July 3, July 4 | P19: Agree | Q19: 미등록
A20: 45859.646 | B20: Tobi Joyce Omonefe | D20: Female | E20: 37760 | F20: Nigeria | G20: Rwanda Christian Medical and Dental Organization | H20: Student | I20: Middle income | J20: joycie1619@gmail.com | K20: Pre-Conference + Main Congress | L20: 46207 | P20: Agree | Q20: 등록 | S20: Joyce Tobi | T20: 37760 | U20: joycie2124@gmail.com | V20: 생년월일 일치, 이름 유사도 100, 이름 토큰 포함
A21: 45859.655 | B21: Patrick GISUBIZO | D21: Male | E21: 37756 | F21: Rwanda | G21: University of Rwanda | H21: Mr. | I21: Low income | J21: gisubizopatrick095@gmail.com | K21: Student Conference + Main Congress | L21: June 29, June 30, July 1, July 2, July 3, July 4 | P21: Agree | Q21: 미등록
A22: 45859.657 | B22: ABAYISENGA Stella | D22: Female | E22: 38183 | F22: Rwanda | G22: University of Rwanda | H22: Student | I22: Low income | J22: stellabayisenga@gmail.com | K22: Student Conference + Main Congress | L22: June 29, June 30, July 1, July 2, July 3, July 4 | M22: 9, Stella,female, children, stellabayisenga@gmail.com | N22: Stella [자녀] | O22: 2명/ (자녀 1명) | P22: Agree | Q22: 미등록
A23: 45859.675 | B23: NGABOYUMWAMI Jean Paul | C23: Rwandan ID | D23: Male | E23: 37594 | F23: Rwanda | G23: University of Rwanda | H23: Medical Student | I23: Low income | J23: jeanpaulngaboyumwami@gmail.com | K23: Student Conference + Main Congress | L23: June 29, June 30, July 1, July 2, July 3, July 4 | P23: Agree | Q23: 등록 | S23: NGABOYUMWAMI Jean Paul | T23: 45762 | U23: jeanpaulngaboyumwami@gmail.com | V23: 이메일 일치
A24: 45859.792 | B24: Mbonimpa James | D24: Male | E24: 37455 | F24: Rwanda | G24: RCMDO ( Rwanda Christian Medical and Dental Organisation | H24: Medical Student | I24: Low income | J24: jamesmbonimpa904@gmail.com | K24: Pre-Conference + Main Congress | L24: June 29, June 30, July 1, July 2, July 3, July 4 | P24: Agree | Q24: 미등록
A25: 45860.185 | B25: Nsanzimfura Pacifique | C25: Nsanzimfura Pacifique | D25: Male | E25: 38109 | F25: Rwanda | G25: University of Rwanda | H25: Mr | I25: Low income | J25: nsanzimfurapacifique@gmail.com | K25: Student Conference + Main Congress | L25: June 29, June 30, July 1, July 2, July 3, July 4 | P25: Agree | Q25: 등록 | S25: Nsanzimfura Pacifique | T25: 38109 | U25: nsanzimfurapacifique@gmail.com | V25: 생년월일 일치, 이메일 일치, 이름 완전일치
A26: 45860.593 | B26: Jean d'Amour HABINSHUTI | D26: Male | E26: 34335 | F26: Rwanda | G26: Rwanda Christian Medical and Dental Organization | H26: Student | I26: Low income | J26: jdhabinshuti@gmail.com | K26: Pre-Conference + Main Congress | L26: 46207 | P26: Agree | Q26: 미등록
A27: 45860.797 | B27: Umuhoza Marie Claire | D27: Female | E27: 35013 | F27: Rwanda | G27: Public Hospital | H27: Junior Doctor | I27: Low income | J27: umumariec1@gmail.com | K27: Main Congress Only | L27: July 1, July 2, July 3, July 4 | P27: Agree | Q27: 등록 | S27: Marie Claire Umuhoza | T27: 35013 | U27: umumariec1@gmail.com | V27: 생년월일 일치, 이메일 일치, 이름 유사도 100, 이름 토큰 포함
A28: 45860.808 | B28: MAOMBI Melanie | D28: Female | E28: 35285 | F28: Rwanda | G28: University of Rwanda | H28: Resident | I28: Low income | J28: melaniemaombi@gmail.com | K28: Pre-Conference + Main Congress | L28: June 29, June 30, July 1, July 2, July 3, July 4 | M28: 1, BITEGETSIMANA GEDEON, male, husband | P28: Agree | Q28: 미등록
A29: 45860.823 | B29: Donath SINABUBARAGA | D29: Male | E29: 36362 | F29: Rwanda | G29: Rwanda Christian Medical and Dental Organization | H29: student | I29: Low income | J29: dosinabubaraga@gmail.com | K29: Pre-Conference + Main Congress | L29: June 30, July 1, July 2, July 3, July 4 | P29: Agree | Q29: 미등록
A30: 45860.982 | B30: Ruvimbo Mutize | D30: Female | E30: 37253 | F30: Zimbabwe | G30: National University of Science and Technology (NUST) | H30: Student | I30: Middle income | J30: mutizer28@gmail.com | K30: Main Congress Only | L30: June 30, July 1, July 2, July 3, July 4 | P30: Agree | Q30: 등록 | S30: Ruvimbo Mutize
A31: 45861.652 | B31: INGABIRE Emeline | D31: Female | E31: 36721 | F31: Rwanda | G31: Rwanda Christian Medical and Dental Organisation | H31: Student | I31: Low income | J31: emelinerda@gmail.com | K31: Student Conference + Main Congress | L31: June 29, June 30, July 1, July 2, July 3, July 4 | P31: Agree | Q31: 미등록
A32: 45862.865 | B32: Unkwiye hertier | D32: Male | E32: 36536 | F32: Rwanda | G32: Rwanda Christian Medical and Dental Organization (RCMDO) | H32: President of Chritian medical student fellowship -Remera chapter | I32: Low income | J32: hertierunkwiye1@gmail.com | K32: Main Congress Only | L32: June 30, July 1, July 2, July 3, July 4 | P32: Agree | Q32: 미등록
A33: 45862.937 | B33: BANA Keys Pamela | C33: Pamla Keys BANA | D33: Female | E33: 38542 | F33: Rwanda | G33: Rwanda Christian Medical and dental Organization | H33: Student | I33: Low income | J33: kpamela210@gmail.com | K33: Student Conference + Main Congress | L33: June 29, June 30, July 1, July 2, July 3, July 4 | P33: Agree | Q33: 미등록
A34: 45865.161 | B34: MUTABARUKA John | D34: Male | E34: 45908 | F34: Rwanda | G34: Rwanda Christian Medical and Dental Organization. | H34: Student Leader | I34: Low income | J34: mutabarukajohn250@gmail.com | K34: Pre-Conference + Main Congress | L34: June 29, June 30, July 1, July 2, July 3, July 4 | P34: Agree | Q34: 미등록
A35: 45865.165 | B35: KILACH CAROLE JESANG | D35: Female | E35: 32229 | F35: Kenya | G35: CHRISTIAN MEDICAL FELLOWSHIP- KENYA | H35: Dr/Miss/ Regional Leader | I35: Middle income | J35: carolejesang@gmail.com | K35: Pre-Conference + Main Congress | L35: June 29, June 30, July 1, July 2, July 3, July 4 | P35: Agree | Q35: 등록 | R35: paid | S35: KILACH CAROLE JESANG | T35: 32229 | U35: carolejesang@gmail.com | V35: 생년월일 일치, 이메일 일치, 이름 완전일치
A36: 45865.819 | B36: Mugeni Adeline | D36: Female | E36: 28995 | F36: Rwanda | G36: Rwanda Christian Medical and Dental Organisation | H36: Dr | I36: Low income | J36: mugenia23@gmail.com | K36: Pre-Conference + Main Congress | L36: June 29, June 30, July 1, July 2, July 3, July 4 | P36: Agree | Q36: 등록 | S36: Adeline Mugeni | T36: 28995 | U36: mugenia23@gmail.com | V36: 생년월일 일치, 이메일 일치, 이름 유사도 100, 이름 토큰 포함
A37: 45865.819 | B37: KANANGA Wilson | D37: Male | E37: 35647 | F37: Rwanda | G37: Nyamata level two Teaching Hospital | H37: Intern Doctor | I37: Low income | J37: kanawilson01@gmail.com | K37: Pre-Conference + Main Congress | L37: June 30, July 1, July 2, July 3, July 4 | P37: Agree | Q37: 미등록
A38: 45866.256 | B38: BUTOYI Alphonse | C38: BUTOYI Alphonse | D38: Male | E38: 26966 | F38: Rwanda | G38: Legacy Clinics | H38: Senior consultant Obstetrician &Gyneacologist | I38: Low income | J38: alphonse.butoyi@doctor.com | K38: Main Congress Only | L38: July 1, July 2, July 3, July 4 | P38: Agree | Q38: 미등록
A39: 45870.142 | B39: Aline Garcia Pereira | C39: Aline Garcia Pereira | D39: Female | E39: 32847 | F39: Brazil | G39: Uniasselvi (University)/ MDC -Medicos de Cristo | H39: I am student of Health Management (graduation). But I am also PHD | I39: Middle income | J39: alinegpereira1@gmail.com | K39: Student Conference + Main Congress | L39: June 29, June 30, July 1, July 2, July 3, July 4 | P39: Agree | Q39: 등록 | R39: paid | S39: Aline Garcia Pereira | T39: 32847 | U39: alinegpereira1@gmail.com | V39: 생년월일 일치, 이메일 일치, 이름 완전일치
A40: 45871.144 | B40: Aida Olinda Lizano Alarcón | D40: Female | E40: 31443 | F40: Peru | G40: Asociacion Cristiana de Profesionales de la Salud del Perú | H40: Medico Internista | I40: Middle income | J40: aida.lizanoo@gmail.com | K40: Main Congress Only | L40: June 29, June 30, July 1, July 2, July 3, July 4 | P40: Agree | Q40: 미등록
A41: 45871.236 | B41: PAUL STEPHEN ATARO AYELLA | D41: Male | E41: 28186 | F41: Uganda | G41: ICMDA | H41: REGIONAL REPRESENTATIVE EAST AFRICA | I41: Low income | J41: ATARODRPAPA@GMAIL.COM | K41: Student Conference + Main Congress | L41: June 29, June 30, July 1, July 2, July 3, July 4 | M41: ATARO JANE KARINA, FEMALE. ATARO NEEMA ANGIOLETTA, FEMALE DAUGHTERS | N41: ATARO JANE KARINA, FEMALE. 딸 2명 ATARO NEEMA ANGIOLETTA, FEMALE DAUGHTERS | O41: 3명/ (자녀 2명) | P41: Agree | Q41: 등록 | R41: bursary | S41: Paul Stephen Ataro Ayella | T41: 28186 | U41: atarodrpapa@gmail.com | V41: 생년월일 일치, 이메일 일치, 이름 완전일치
A42: 45874.23 | B42: Mugaba Proscovia Mujeere | D42: Female | E42: 28943 | F42: Uganda | G42: Uganda Christian Medical Fellowship (UCMF) | H42: Chairperson of UCMF National Executive Committee | I42: Low income | J42: drprosiemm@gmail.com | K42: Main Congress Only | L42: June 30, July 1, July 2, July 3, July 4 | P42: Agree | Q42: 등록 | R42: bursary | S42: Proscovia Mujeere Mugaba
A43: 45874.567 | B43: Mujwala Samuel Kagali | D43: Male | E43: 36651 | F43: Uganda | G43: Soroti university | H43: SOROTI UNIVRSITY CMF CHAIRPERSON | I43: Low income | J43: 2101600045@sun.ac.ug | K43: Student Conference + Main Congress | L43: June 29, June 30, July 1, July 2, July 3, July 4 | P43: Agree | Q43: 등록 | S43: Mujwala Samuel Kagali | T43: 36651 | U43: 2101600045@sun.ac.ug | V43: 생년월일 일치, 이메일 일치, 이름 완전일치
A44: 45875.633 | B44: Theodorus Hedwin Kadrianto | D44: Male | E44: 32327 | F44: Indonesia | G44: ICMDA | H44: AEO for East Asia, Southeast Asia, Oceania | I44: Middle income | J44: theodorus.hedwin@icmda.net | K44: Pre-Conference + Main Congress | L44: June 29, June 30, July 1, July 2, July 3, July 4 | P44: Agree | Q44: 등록 | R44: paid | S44: Theodorus Hedwin Kadrianto | T44: 32327 | U44: theodorus.hedwin@icmda.net | V44: 생년월일 일치, 이메일 일치, 이름 완전일치
A45: 45877.788 | B45: Sally John | C45: Sally | D45: Female | E45: 45883 | F45: South Africa | G45: ICMDA | H45: Dr Phd | I45: Middle income | J45: Johnsally728@gmail.com | K45: Pre-Conference + Main Congress | L45: June 29, June 30, July 1, July 2, July 3, July 4 | P45: Agree | Q45: 등록 | S45: Sally John | T45: 20712 | U45: johnsally728@gmail.com | V45: 이메일 일치, 이름 완전일치
A46: 45881.297 | B46: Kamanzi | C46: Umuhire Immaculée | D46: Female | E46: 24605 | F46: Rwanda | G46: Rwanda Christian Medical and Dental Organization | H46: Dental Surgeon /Member | I46: Low income | J46: immakamanziu@gmail.com | K46: Main Congress Only | L46: June 29, July 4 | M46: Kabasinge Kamanzi Icyeza Gracia, Female, Daughter, kabkamicyezagracia@gmail.com | N46: Kabasinge Kamanzi Icyeza Gracia [딸] | O46: 2명/ (자녀 1명) | P46: Agree | Q46: 미등록
A47: 45883.567 | B47: PETER SATHIYANATHAN MICHEAL JOHN | D47: Male | E47: 28573 | F47: MALAYSIA | G47: HEALTHCARE CHRISTIAN FELLOWSHIP MALAYSIA | H47: DOCTOR | I47: Middle income | J47: doctorpeter@hotmail.com | K47: Main Congress Only | L47: July 1, July 2, July 3, July 4 | M47: IRINE AARATHANA PETER SATHIYANATHAN, FEMALE, - 12 YEARS OLD DAUGHTER , doctorpeter@hotmail.com | N47: IRINE AARATHANA PETER SATHIYANATHAN [딸, 12세] | O47: 2명/ (자녀 1명) | P47: Agree | Q47: 등록 | R47: paid | S47: PETER SATHIYANATHAN MICHEAL JOHN | T47: 28573 | U47: doctorpeter@hotmail.com | V47: 생년월일 일치, 이메일 일치, 이름 완전일치
A48: 45890.989 | B48: Alina | D48: Female | E48: 36334 | F48: Belarus | G48: Belarussian CMF | H48: Ophtalmologist | I48: Middle income | J48: kurdunap@gmail.com | K48: Main Congress Only | L48: June 29, June 30, July 1, July 2, July 3, July 4 | P48: Agree | Q48: 등록 | R48: bursary | S48: Alina Kurdun
A49: 45891.188 | B49: Vincent, Benjamin Terfa | D49: Male | E49: 34606 | F49: Nigeria | G49: Christian Medical and Dental Association of Nigeria - Doctors' Arm | H49: Member | I49: Middle income | J49: benjaminvincent76@gmail.com | K49: Pre-Conference + Main Congress | L49: June 29, June 30, July 1, July 2, July 3, July 4 | P49: Agree | Q49: 등록 | S49: Vincent Benjamin Terfa
A50: 45893.857 | B50: NTAGWABIRA Ange Bernice Shekinnah | D50: Female | E50: 36839 | F50: Rwanda | G50: RCMDO | H50: Active member | I50: Low income | J50: angesheky77@gmail.com | K50: Pre-Conference + Main Congress | L50: June 29, June 30, July 1, July 2, July 3, July 4 | P50: Agree | Q50: 미등록
A51: 45893.877 | B51: Ada Mola | D51: Female | E51: 37908 | F51: Rwanda | G51: University of Global Health Equity | H51: Medical Student year 4 | I51: Low income | J51: ada.mola@student.ughe.org | K51: Student Conference + Main Congress | L51: June 29, June 30, July 1, July 2, July 3, July 4 | P51: Agree | Q51: 등록 | S51: Ada Mola | T51: 37908 | U51: ada.mola@student.ughe.org | V51: 생년월일 일치, 이메일 일치, 이름 완전일치
A52: 45893.889 | B52: DUKUZIMANA Joseph | D52: Male | E52: 36281 | F52: Rwanda | G52: Nyamata L2TH | H52: Dental Surgeon | I52: Low income | J52: dukuzimanajoseph@gmail.com | K52: Pre-Conference + Main Congress | L52: June 29, June 30, July 1, July 2, July 3, July 4 | P52: Agree | Q52: 미등록
A53: 45893.92 | B53: Atem Paul | D53: Male | E53: 21091 | F53: Cameroon | G53: Mount Zion Clinic, Bamenda, Cameroon | H53: Dr. | I53: Middle income | J53: dratempaul2015@gmail.com | K53: Pre-Conference + Main Congress | L53: 46202 | M53: Yes. One. My wife. | P53: Agree | Q53: 등록 | S53: Paul Atem | T53: 21091 | U53: dratempaul2015@gmail.com | V53: 생년월일 일치, 이메일 일치, 이름 유사도 100, 이름 토큰 포함
A54: 45894.45 | B54: Willyanna Ravanielly Oliveira de Carvalho | D54: Female | E54: 36283 | F54: Brazil | G54: MDC Brazil | H54: Young Doctor | I54: Middle income | J54: willyanna634@gmail.com | K54: Main Congress Only | L54: June 29, June 30, July 1, July 2, July 3, July 4 | P54: Agree | Q54: 등록 | S54: Willyanna Ravanielly Oliveira de Carvalho | T54: 36283 | U54: willyanna634@gmail.com | V54: 생년월일 일치, 이메일 일치, 이름 완전일치
A55: 45895.305 | B55: Semby, Johan Kyung Hwa | D55: Male | E55: 24127 | F55: Sweden | G55: Linköping University/Linköping University Hospital Department of Opthalmology/ ICMDA Sweden | H55: Senior Consultant in Ophthalmology/ Leader, organizer for the delegation from ICMDA Sweden and Finland | I55: High income | J55: johan.semby@gmail.com | K55: Pre-Conference + Main Congress | L55: June 29, June 30, July 1, July 2, July 3, July 4 | M55: 1, Joshua Semby, male, son, joshua.semby7@gmail.com | N55: Joshua Semby [아들] | O55: 2명/ (자녀 1명) | P55: Agree | Q55: 등록 | R55: paid | S55: Johan Kyung Hwa Semby | T55: 24492 | U55: johan.semby@gmail.com | V55: 이메일 일치, 이름 유사도 100, 이름 토큰 포함
A56: 45897.565 | B56: Edna Ezra Umaru | D56: Female | E56: 38276 | F56: Nigeria | G56: Gombe state university Nigeria | H56: Class Academic secretary | I56: Middle income | J56: ednaumaru044@gmail.com | K56: Student Conference + Main Congress | L56: June 29, June 30, July 1, July 2, July 3, July 4 | P56: Agree | Q56: 미등록
A57: 45900.026 | B57: NURGUL MAMYROVA | D57: Female | E57: 29297 | F57: Kyrgyz Republic | G57: ICMDA | H57: Doctor | I57: Middle income | J57: nurgulicmda@gmail.com | K57: Student Conference + Main Congress | L57: June 29, June 30, July 1, July 2, July 3, July 4 | M57: Yes: Simon Peter Nadeem-my husband, My Daughter-Shulmiyat Sarah Nadeem, and my son -Timothy Simon Nadeem) | N57: Simon Peter Nadeem [배우자(남편)] Shulmiyat Sarah Nadeem[딸, 18세] Timothy Simon Nadeem [아들, 13세] | O57: 4명/ (자녀 2명, 배우자 1명) | P57: Agree | Q57: 등록 | R57: paid | S57: Nurgul Mamyrova | T57: 29297 | U57: nurgulicmda@gmail.com | V57: 생년월일 일치, 이메일 일치, 이름 완전일치
A58: 45908.027 | B58: Tubasiime Ronald | D58: Male | E58: 29582 | F58: Rwanda | G58: Kibogora Hospital | H58: General surgeon | I58: Low income | J58: turona20@gmail.com | K58: Pre-Conference + Main Congress | L58: June 29, June 30, July 1, July 2, July 3, July 4 | P58: Agree | Q58: 등록 | S58: Ronald Tubasiime | T58: 29582 | U58: turona20@gmail.com | V58: 생년월일 일치, 이메일 일치, 이름 유사도 100, 이름 토큰 포함
A59: 45908.782 | B59: Diana | C59: Safina | D59: Female | E59: 30253 | F59: Russian Federation | G59: ICMDA | H59: Regional representative, Eurasia training administrator | I59: High income | J59: diana.safina316@gmail.com | K59: Pre-Conference + Main Congress | L59: June 29, June 30, July 1, July 2, July 3, July 4 | M59: Daria Safina, female, daughter 13 years old | N59: Daria Safina [딸, 13세] | O59: 2명/ (자녀 1명) | P59: Agree | Q59: 등록 | R59: bursary | S59: Diana Safina | T59: 30253 | U59: diana.safina316@gmail.com | V59: 생년월일 일치, 이메일 일치, 이름 유사도 100
A60: 45909.158 | B60: Grishanovich Elisei | D60: Male | E60: 37263 | F60: Russian Federation | G60: Kirov Smu | H60: Student | I60: High income | J60: elishagch@gmail.com | K60: Student Conference + Main Congress | L60: June 29, June 30, July 1, July 2, July 3, July 4 | P60: Agree | Q60: 등록 | S60: ELISEI GRISHANOVICH | T60: 37263 | U60: elishagch@gmail.com | V60: 생년월일 일치, 이메일 일치, 이름 유사도 100, 이름 토큰 포함
A61: 45909.696 | B61: BENJAMIN DUBE | D61: Male | E61: 35302 | F61: ZIMBABWE | G61: NATIONAL UNIVERSITY OF SCIENCE AND TECHNOLOGY, ZIMBABWE | H61: Chairperson, NUST Christian Medical Fellowship (CMF) | I61: Middle income | J61: benjiedube25@gmail.com | K61: Student Conference + Main Congress | L61: June 29, June 30, July 1, July 2, July 3, July 4 | P61: Agree | Q61: 등록 | R61: bursary | S61: DUBE BENJAMIN | T61: 35302 | U61: benjiedube25@gmail.com | V61: 생년월일 일치, 이메일 일치, 이름 유사도 100, 이름 토큰 포함
A62: 45916.786 | B62: Budiani Christina Natalia | D62: Female | E62: 30307 | F62: Indonesia | G62: Bethesda Serukam Mission Hospital, West Borneo, Indonesia | H62: Anesthesiologist | I62: Middle income | J62: b.christina07@gmail.com | K62: Main Congress Only | L62: July 1, July 2, July 3, July 4 | P62: Agree | Q62: 등록 | S62: Budiani Christina Natalia | T62: 30307 | U62: b.christina07@gmail.com | V62: 생년월일 일치, 이메일 일치, 이름 완전일치
A63: 45918.29 | B63: Peter Fee | D63: Male | E63: 28989 | F63: United Kingdom | G63: Royal Belfast Children's Hospital, Belfast, UK | H63: Consultant Anaesthetist | I63: High income | J63: peterfee@doctors.org.uk | K63: Pre-Conference + Main Congress | L63: June 29, June 30, July 1, July 2, July 3, July 4 | M63: 4: Kerry Fee, female, wife, thefees@me.com; Grace Fee, female, daughter; Joel Fee, male, son; Toby Fee, male, son. | N63: Kerry Fee [배우자(아내)] thefees@me.com Grace Fee [딸, 12세] Joel Fee [아들, 14세] Toby Fee [아들, 10세] | O63: 5명/ (자녀 3명, 배우자 1명) | P63: Agree | Q63: 등록 | R63: paid | S63: Peter Fee | T63: 28989 | U63: peterfee@doctors.org.uk | V63: 생년월일 일치, 이메일 일치, 이름 완전일치
A64: 45918.575 | B64: Nakanjako | C64: Sharon | D64: Female | E64: 34006 | F64: Uganda | G64: Uganda Christian medical Fellowship | H64: Clinical psychologist | I64: Middle income | J64: sharonnakanjako2023@gmail.com | K64: Pre-Conference + Main Congress | L64: June 29, June 30, July 1, July 2, July 3, July 4 | P64: Agree | Q64: 등록 | R64: bursary | S64: Sharon Nakanjako | T64: 34006 | U64: sharonnakanjako2023@gmail.com | V64: 생년월일 일치, 이메일 일치, 이름 유사도 100
A65: 45921.897 | B65: GERISI JOSEPH GERGES SHENODA ISSA | D65: Female | E65: 36404 | F65: Egypt, Arab Rep. | G65: CMF Egypt | H65: Dentist (GP) | J65: gracejoseph771999@gmail.com | K65: Pre-Conference + Main Congress | L65: June 29, June 30, July 1, July 2, July 3, July 4 | M65: 1, Jena Issa, female, sister, jena.joseph@ngu.edu.eg | P65: Agree | Q65: 등록 | S65: Gerisi Joseph Gerges Shenoda Issa
A66: 45922.815 | B66: Greta Gamal Nazir Kross | D66: Female | E66: 30328 | F66: Egypt, Arab Rep. | G66: Cmf egypt | H66: Pediatric specialist (director of operations of cmf egypt) | I66: Middle income | J66: gretagamal@hotmail.com | K66: Pre-Conference + Main Congress | L66: June 29, June 30, July 1, July 2, July 3, July 4 | M66: George robile,male,husband Jason george,male ,son Jenny george,female,daughter | N66: George robile [배우자(남편)] gretagamal@hotmail.com Jason george [아들, 13세] Jenny george [딸, 17세] | O66: 4명/ (자녀 2명, 배우자 1명) | P66: Agree | Q66: 등록 | R66: bursary | S66: Greta Gamal
A67: 45923.699 | B67: Meilani | D67: Female | E67: 30073 | F67: Indonesia | G67: CMDF Indonesia | H67: Mrs/Coordinator of Mission Department | I67: Middle income | J67: mariameilani1@gmail.com | K67: Pre-Conference + Main Congress | L67: June 29, June 30, July 1, July 2, July 3, July 4 | M67: 2. Tigor Yeheskiel, male, husband. Matthew Jordan Simanjuntak, male, son. | N67: Tigor Yeheskiel [배우자(남편)] Matthew Jordan Simanjuntak [아들, 7세] | O67: 3명/ (자녀 1명, 배우자 1명) | P67: Agree | Q67: 등록 | S67: Meilani | T67: 30073 | U67: mariameilani1@gmail.com | V67: 생년월일 일치, 이메일 일치, 이름 완전일치
A68: 45924.787 | B68: Pola Ayman Wadea Zaki | D68: Male | E68: 37309 | F68: Egypt, Arab Rep. | G68: Faculty of medicine minia university | H68: Medical student | I68: Middle income | J68: polaayman333@gmail.com | K68: Pre-Conference + Main Congress | L68: June 29, June 30, July 1, July 2, July 3, July 4 | P68: Agree | Q68: 등록 | S68: Pola ayman wadea zaki | T68: 37309 | U68: polaayman333@gmail.com | V68: 생년월일 일치, 이메일 일치, 이름 완전일치
A69: 45925.89 | B69: Ebram Adel Karem | D69: Male | E69: 45927 | F69: Egypt, Arab Rep. | G69: Faculty of Medicine-Minia university | H69: Medical student | I69: Middle income | J69: ebramadel264@gmail.com | K69: Pre-Conference + Main Congress | L69: June 29, June 30, July 1, July 2, July 3, July 4 | P69: Agree | Q69: 등록 | S69: Ebram Adel Karem | T69: 37372 | U69: ebramadel264@gmail.com | V69: 이메일 일치, 이름 완전일치
A70: 45926.518 | B70: Zawadi Virgily John | D70: Female | E70: 34121 | F70: Tanzania | G70: Mawenzi Refferal Regional Hospital | H70: Laboratory Scientist | I70: Middle income | J70: zawadijohn103@gmail.com | K70: Pre-Conference + Main Congress | L70: June 29, June 30, July 1, July 2, July 3, July 4 | P70: Agree | Q70: 등록 | S70: Zawadi John | T70: 34121 | U70: zawadijohn103@gmail.com | V70: 생년월일 일치, 이메일 일치, 이름 유사도 100, 이름 토큰 포함
A71: 45927.529 | B71: KASONGO MWENYI MAXIME | D71: Male | E71: 26111 | F71: Congo, Dem.Rep. | G71: Centre de santé pilote et maternité de Masina/Kinshasa | H71: Chef de service ophtalmologie | I71: Low income | J71: maxkasongo@gmail.com | K71: Main Congress Only | L71: June 29, June 30, July 1, July 2, July 3, July 4 | P71: Agree | Q71: 미등록
A72: 45927.904 | B72: Christa Adeline | D72: Female | E72: 35457 | F72: Indonesia | G72: ICMDA | H72: Regional Representative for Southeast Asia | I72: Middle income | J72: christa.adeline@icmda.net | K72: Pre-Conference + Main Congress | L72: June 30, July 1, July 2, July 3, July 4 | P72: Agree | Q72: 등록 | R72: paid | S72: Christa Adeline | T72: 35457 | U72: christa.adeline@icmda.net | V72: 생년월일 일치, 이메일 일치, 이름 완전일치
A73: 45927.984 | B73: Quacy Asheeke Grant | D73: Male | E73: 31257 | F73: Guyana | G73: Lausanne Movement Caribbean/ICMDA Guyana-Caribbean | H73: Regional Director (Lausanne Movement Caribbean) | I73: High income | J73: qgrant@lausanne.org | K73: Main Congress Only | L73: June 29, June 30, July 1, July 2, July 3, July 4 | P73: Agree | Q73: 등록 | R73: bursary | S73: Quacy Asheeke Grant
